Workbook

Sheet Summary
A1: Healthcare & Lab Locations
A2: Collected October 07, 2026 from each organization's public website
A4: Organization | B4: Locations | C4: States / Regions | D4: Added | E4: Removed | F4: Changed fields | G4: Checks
A5: Jefferson Health | B5: =COUNTA('Jefferson Health'!A:A)-1 -> 447 | C5: =SUMPRODUCT(('Jefferson Health'!F2:F20000<>"")/COUNTIF('Jefferson Health'!F2:F20000,'Jefferson Health'!F2:F20000&"")) -> 4 | D5: =COUNTIFS(Changes!A:A,"Jefferson Health",Changes!B:B,"Added") -> 0 | E5: =COUNTIFS(Changes!A:A,"Jefferson Health",Changes!B:B,"Removed") -> 0 | F5: =COUNTIFS(Changes!A:A,"Jefferson Health",Changes!B:B,"Changed") -> 0 | G5: OK
A6: LVHN | B6: =COUNTA(LVHN!A:A)-1 -> 843 | C6: =SUMPRODUCT((LVHN!I2:I20000<>"")/COUNTIF(LVHN!I2:I20000,LVHN!I2:I20000&"")) -> 2 | D6: =COUNTIFS(Changes!A:A,"LVHN",Changes!B:B,"Added") -> 0 | E6: =COUNTIFS(Changes!A:A,"LVHN",Changes!B:B,"Removed") -> 0 | F6: =COUNTIFS(Changes!A:A,"LVHN",Changes!B:B,"Changed") -> 0 | G6: OK
A7: Quest Diagnostics | B7: =COUNTA('Quest Diagnostics'!A:A)-1 -> 2303 | C7: =SUMPRODUCT(('Quest Diagnostics'!G2:G20000<>"")/COUNTIF('Quest Diagnostics'!G2:G20000,'Quest Diagnostics'!G2:G20000&"")) -> 49 | D7: =COUNTIFS(Changes!A:A,"Quest Diagnostics",Changes!B:B,"Added") -> 1 | E7: =COUNTIFS(Changes!A:A,"Quest Diagnostics",Changes!B:B,"Removed") -> 0 | F7: =COUNTIFS(Changes!A:A,"Quest Diagnostics",Changes!B:B,"Changed") -> 0 | G7: OK
A8: Labcorp | B8: =COUNTA(Labcorp!A:A)-1 -> 2273 | C8: =SUMPRODUCT((Labcorp!F2:F20000<>"")/COUNTIF(Labcorp!F2:F20000,Labcorp!F2:F20000&"")) -> 48 | D8: =COUNTIFS(Changes!A:A,"Labcorp",Changes!B:B,"Added") -> 0 | E8: =COUNTIFS(Changes!A:A,"Labcorp",Changes!B:B,"Removed") -> 0 | F8: =COUNTIFS(Changes!A:A,"Labcorp",Changes!B:B,"Changed") -> 0 | G8: OK
A9: Total | B9: =SUM(B5:B8) -> 5866
A10: Excluded (listed but no data) | B10: =COUNTA(Excluded!A:A)-1 -> 48
A12: Notes
A13: Every row links back to its source page (Location URL). Blank hours mean the website lists none (often "hours vary / please call").
A14: Changes tab: locations added/removed since last month and changed name, address, phone, fax or hours (only when a previous file was supplied).
A15: Quest: Location Type separates Quest patient service centers, joint ventures/affiliates, partner collection sites and international sites.
A16: Labcorp: "Labcorp at Walgreens" = Labcorp service center inside a Walgreens store.
A17: LVHN: Location Types and Services come from the lvhn.org location filters; a location can have several.

Sheet Checks
A1: Source | B1: Check | C1: Result | D1: Status
A2: Jefferson Health | B2: Note | C2: 9 locations are in the search index but their pages return 404 (kept, flagged in Note) | D2: INFO
A3: Jefferson Health | B3: Location count | C3: 447 vs 447 last month (+0.0%) | D3: OK
A4: Jefferson Health | B4: Name filled | C4: 100% (usual ~100%) | D4: OK
A5: Jefferson Health | B5: Street Address filled | C5: 100% (usual ~100%) | D5: OK
A6: Jefferson Health | B6: City filled | C6: 100% (usual ~100%) | D6: OK
A7: Jefferson Health | B7: Phone filled | C7: 98% (usual ~98%) | D7: OK
A8: Jefferson Health | B8: Latitude filled | C8: 100% (usual ~100%) | D8: OK
A9: LVHN | B9: Location count | C9: 843 vs 843 last month (+0.0%) | D9: OK
A10: LVHN | B10: Name filled | C10: 100% (usual ~100%) | D10: OK
A11: LVHN | B11: Street Address filled | C11: 100% (usual ~100%) | D11: OK
A12: LVHN | B12: City filled | C12: 100% (usual ~100%) | D12: OK
... A26: Labcorp | B26: Latitude filled | C26: 100% (usual ~100%) | D26: OK

Sheet Jefferson Health
A1: Name | B1: Location Type | C1: Facility Label | D1: Street Address | E1: City | F1: State | G1: ZIP | H1: County | I1: Latitude | J1: Longitude | K1: Phone | L1: Other Phones | M1: Fax | N1: Email | O1: Open 24 Hours | P1: Monday Hours | Q1: Tuesday Hours | R1: Wednesday Hours | S1: Thursday Hours | T1: Friday Hours | U1: Saturday Hours | V1: Sunday Hours | W1: Hours Footnote | X1: Clinical Specialties | Y1: Conditions | Z1: Treatments | AA1: Wheelchair Accessible | AB1: Public Transportation | AC1: Shuttle Service | AD1: Language Services | AE1: Einstein Location | AF1: Online Scheduling | AG1: Description | AH1: Google Maps Link | AI1: Directions/Parking Page | AJ1: Department Directory | AK1: Location URL | AL1: Last Published | AM1: Note
A2: 3706 Kennett Pike | B2: Practice | D2: 3706 Kennett Pike | E2: Greenville | F2: DE | G2: 19807 | I2: 39.774184 | J2: -75.594847 | K2: 302-477-1991 | M2: 302-477-1994 | O2: No | P2: Closed | Q2: Closed | R2: Closed | S2: Closed | T2: Closed | U2: Closed | V2: Closed | W2: *When traveling to our Wilmington location, enter through the Quillen Building, Suite 1L. | X2: Dermatology; Pigmented Lesion Care; Laser Surgery & Cosmetic Dermatology | AA2: No | AB2: No | AE2: No | AG2: Our Kennett Pike practice offers dermatology and cosmetic services. | AH2: https://www.google.com/maps/place/3706+Kennett+Pike,+Greenville,+DE+19807/@39.7741841,-75.5948468,17z/data=!3m1!4b1!4m6!3m5!1s0x89c6fc4ae6474bb3:0x457d13beacb1bc61!8m2!3d39.7741841!4d-75.5948468!16s%2Fg%2F11c1yj8619 | AK2: https://www.jeffersonhealth.org/locations/3706-kennett-pike | AL2: 2026-01-24
A3: Jefferson Gastroenterology & Hepatology Associates | B3: Practice | D3: 4735 Ogletown-Stanton Road, Suite 3301 | E3: Newark | F3: DE | G3: 19713 | I3: 39.670937 | J3: -75.708073 | K3: 215-955-8900 | O3: No | X3: Liver Transplant; Viral Hepatitis Care; Gastroenterology & Hepatology; Transplant Institute; Fatty Liver Care; Liver Tumor; Barrett's Esophagus Care | AA3: No | AB3: No | AE3: No | AF3: No | AG3: Jefferson Gastroenterology & Hepatology Associates offers its patients expert care. | AH3: https://www.google.com/maps/place/4735+Ogletown+Stanton+Rd,+Newark,+DE+19713/data=!4m2!3m1!1s0x89c700e14988170f:0xb87ad107bdbd8d9e?sa=X&ved=2ahUKEwily7qxsvv3AhWajIkEHR9LAm0Q8gF6BAgCEAE | AK3: https://www.jeffersonhealth.org/locations/4735-ogletown-stanton-road | AL3: 2026-01-24
A4: 3521 Silverside Road | B4: Practice | D4: 3521 Silverside Road, Suite 1L | E4: Wilmington | F4: DE | G4: 19810 | I4: 39.810868 | J4: -75.547463 | K4: 1-800-533-3669 | O4: No | P4: Closed | Q4: Closed | R4: Closed | S4: Closed | T4: Closed | U4: Closed | V4: Closed | W4: *When traveling to our Wilmington location, enter through the Quillen Building, Suite 1L. | AA4: No | AB4: No | AE4: No | AF4: No | AG4: Our Silverside Road practice offers dermatology and cosmetic services. | AH4: http://maps.google.com/?q=3521+Silverside+Road%2c+Wilmington%2c+DE+19810 | AK4: https://www.jeffersonhealth.org/locations/3521-silverside-road | AL4: 2026-01-24
A5: Nemours Children’s Health – Wilmington | B5: Practice | D5: 1600 Rockland Road | E5: Wilmington | F5: DE | G5: 19899 | I5: 39.778655 | J5: -75.558516 | K5: 1-800-416-4441 | O5: No | X5: Respiratory & Pulmonary Medicine; Gynecology; Surgery; Pediatric Neurosurgery; Pediatric Otolaryngology; Pediatric Allergy & Immunology; Pediatric Urology; Pediatric Rehabilitation Medicine; Otolaryngology; Ophthalmology; Pediatric General Surgery; Orthopedics; Pediatric Dermatology; Pediatric Neurology; Pediatric & Adolescent Gynecology; Pediatric Cardiology; Pediatrics; Pediatric Gastroenterology; Pediatric Endocrinology; General Surgery | AA5: Yes | AB5: Yes | AC5: No | AD5: No | AE5: No | AF5: No | AG5: Nemours Children's Health in Wilmington, DE, world-class pediatric care, close to home. | AH5: http://maps.google.com/?q=1600+Rockland+Road%2c+Wilmington%2c+DE+19899 | AK5: https://www.jeffersonhealth.org/locations/nemours-childrens-health | AL5: 2026-01-24
A6: Cherry Hill MOB General Surgery & Specialty Care | B6: Practice | D6: 2211 Chapel Avenue West | E6: Cherry Hill | F6: NJ | G6: 08002 | I6: 39.928668 | J6: -75.015803 | K6: 1-800-JEFF-NOW | O6: No | P6: 08:00 am - 04:30 pm | Q6: 08:00 am - 04:30 pm | R6: 08:00 am - 04:30 pm | S6: 08:00 am - 04:30 pm | T6: 08:00 am - 04:30 pm | U6: Closed | V6: Closed | X6: General Surgery; Breast Surgery; Bariatric Surgery Program; Medical & Surgical Weight Loss; Sleep Medicine; Colorectal Surgery; Breast Care; Comprehensive Weight Management; Obstetrics & Gynecology; Obstetrics; Obstetrics & Maternity Care; Gynecology; Vascular & Endovascular Surgery | AA6: Yes | AB6: Yes | AC6: No | AD6: Yes | AE6: No | AF6: No | AG6: General, bariatric, vascular, cardiothoracic and breast surgery specialists in Cherry Hill, NJ. | AH6: https://www.google.com/maps/place/Jefferson+Health+Cherry+Hill+General+Surgery+%26+Specialty+Care/@39.9308071,-75.0422175,15z/data=!4m9!1m2!2m1!1scherry+hill+MOB+specialty+care!3m5!1s0x89c6cb2f6c389ccd:0x86153d7440a00fae!8m2!3d39.927916!4d-75.015734!15sCh5jaGVycnkgaGlsbCBNT0Igc3BlY2lhbHR5IGNhcmWSAQ9zdXJnaWNhbF9jZW50ZXI | AJ6: https://www.jeffersonhealth.org/locations/cherry-hill-mob-general-surgery-specialty-care/department-directory | AK6: https://www.jeffersonhealth.org/locations/cherry-hill-mob-general-surgery-specialty-care | AL6: 2026-07-28
A7: Cherry Hill Primary & Specialty Care | B7: Practice | D7: 457 Haddonfield Road, Suite 110 | E7: Cherry Hill | F7: NJ | G7: 08002 | I7: 39.934396 | J7: -75.02991 | K7: 844-542-2273 | M7: 856-406-4570 | O7: No | P7: 07:30 am - 07:00 pm | Q7: 07:00 am - 05:00 pm | R7: 08:00 am - 06:00 pm | S7: 08:00 am - 07:00 pm | T7: 07:00 am - 04:00 pm | U7: Closed | V7: Closed | X7: Lung Cancer, Screening, and Nodules; Primary Care; Neuroscience; Sleep Medicine; Respiratory & Pulmonary Medicine; Family & Community Medicine; Sports Medicine; Rheumatology; Vascular & Endovascular Surgery | Y7: Lung Nodule | AA7: No | AB7: No | AC7: No | AD7: No | AE7: No | AF7: No | AG7: Jefferson Health's Cherry Hill Primary & Specialty Care offers a wide variety of services including nutrition, pain management and sleep medicine. | AH7: https://www.google.com/maps/place/Jefferson+Health+Cherry+Hill+Primary+%26+Specialty+Care/@39.9343962,-75.0299099,15.75z/data=!4m21!1m15!4m14!1m6!1m2!1s0x89c13c58e7603965:0x953d469e0f75a68c!2sTabernacle,+New+Jersey!2m2!1d-74.7107048!2d39.8433853!1m6!1m2!1s0x89c6cbb150654aab:0xa6878cabff976f9f!2sJefferson+Health+Cherry+Hill+Primary+%26+Specialty+Care,+457+Haddonfield+Rd+%23110,+Cherry+Hill,+NJ+08002!2m2!1d-75.0313455!2d39.9364238!3m4!1s0x89c6cbb150654aab:0xa6878cabff976f9f!8m2!3d39.9364238!4d-75.0313455 | AK7: https://www.jeffersonhealth.org/locations/cherry-hill-primary-specialty-care | AL7: 2026-08-26
A8: Fibroid Center - 2201 Chapel Ave West | B8: Practice | D8: 2201 Chapel Ave West | E8: Cherry Hill | F8: NJ | G8: 08002 | I8: 39.931173 | J8: -75.026067 | K8: 856-922-4347 | O8: No | P8: 07:30 am - 05:00 pm | Q8: Closed | R8: 07:30 am - 05:00 pm | S8: 07:30 am - 05:00 pm | T8: Closed | U8: Closed | V8: Closed | X8: Fibroid Care; Interventional Radiology | Z8: Uterine Fibroid Embolization | AA8: No | AB8: No | AC8: No | AD8: No | AE8: No | AF8: No | AH8: https://www.google.com/maps/place/Jefferson+Cherry+Hill+Hospital/@39.9279172,-75.0184571,17z/data=!3m1!4b1!4m5!3m4!1s0x89c6cba7982122fb:0x10ce11b5706b1486!8m2!3d39.9279172!4d-75.0162684 | AK8: https://www.jeffersonhealth.org/locations/fibroid-center-2201-chapel-ave-west | AL8: 2026-01-24
A9: Gastroenterology Cherry Hill | B9: Practice | D9: 2211 Chapel Avenue West, Suite 401 | E9: Cherry Hill | F9: NJ | G9: 08002 | I9: 39.927987 | J9: -75.015708 | K9: 215-955-8900 | M9: 856-662-2804 | O9: No | P9: 08:00 am - 04:30 pm | Q9: 08:00 am - 04:30 pm | R9: 08:00 am - 04:30 pm | S9: 08:00 am - 04:30 pm | T9: 08:00 am - 04:30 pm | U9: Closed | V9: Closed | W9: *Temporarily expanded office hours subject to change. | X9: Gastroenterology & Hepatology; Gastroesophageal Care | AA9: No | AB9: No | AC9: No | AD9: No | AE9: No | AF9: Yes | AG9: Gastroenterology services at Cherry Hill, NJ. | AH9: https://www.google.com/maps/place/Jefferson+Health+Cherry+Hill+Gastroenterology/@39.9279868,-75.0157083,15z/data=!4m2!3m1!1s0x0:0xbf023d20b5ddb2e8?sa=X&ved=2ahUKEwj4rLqG6dbzAhWsq3IEHVXqDoYQ_BJ6BAhuEAU | AK9: https://www.jeffersonhealth.org/locations/gastroenterology-cherry-hill | AL9: 2026-01-24
A10: Jefferson Cherry Hill Hospital | B10: Hospital; Imaging | C10: Hospital | D10: 2201 Chapel Ave West | E10: Cherry Hill | F10: NJ | G10: 08002 | I10: 39.928908 | J10: -75.01664 | K10: 856-488-6500 | L10: Emergency Department: 856-488-6816 | O10: Yes | P10: Closed | Q10: Closed | R10: Closed | S10: Closed | T10: Closed | U10: Closed | V10: 09:00 am - 05:00 pm | W10: Emergency Department open 24 hours daily. Please use visiting hours link for department specific hours. | X10: Balance & Hearing; Psychiatry & Human Behavior; Imaging & Radiology; Nutrition; Orthopedics; General Surgery; Sleep Medicine; Stroke; Emergency Medicine; Diabetes; Surgery; Wound Care & Hyperbaric Oxygen Therapy; Minimally Invasive & Robotic Surgery; Interventional Radiology; Fibroid Care; Hospital Medicine; Lower Extremity Orthopedics; Gastroenterology & Hepatology; Outpatient Imaging | AA10: Yes | AB10: Yes | AC10: Yes | AD10: Yes | AE10: No | AF10: No | AG10: Receive the best all-around care in the region in our recently completed $250 million hospital transformation including a new inpatient tower with private rooms. | AH10: https://www.google.com/maps/place/Jefferson+Cherry+Hill+Hospital/@39.9279172,-75.0184571,17z/data=!3m1!4b1!4m5!3m4!1s0x89c6cba7982122fb:0x10ce11b5706b1486!8m2!3d39.9279172!4d-75.0162684 | AI10: https://www.jeffersonhealth.org/locations/cherry-hill-hospital/getting-here | AJ10: https://www.jeffersonhealth.org/locations/cherry-hill-hospital/department-directory | AK10: https://www.jeffersonhealth.org/locations/cherry-hill-hospital | AL10: 2026-08-28
A11: Jefferson Moss-Magee Rehabilitation – Cherry Hill | B11: Outpatient Rehabilitation | D11: 2211 Chapel Avenue | E11: Cherry Hill | F11: NJ | G11: 08002 | I11: 39.928226 | J11: -75.015977 | K11: 856-922-5090 | M11: 856-922-5096 | O11: No | W11: Open Monday through Friday, evening hours are available | X11: Rehabilitation Medicine; Outpatient Rehabilitation; Spinal Cord Injury Rehabilitation; Physical Therapy; Stroke Rehabilitation; Orthopedic Injury Rehabilitation; Speech Therapy Program; Brain Injury Rehabilitation | Y11: Lymphedema; Pelvic Pain; Concussion & Head Injuries | Z11: Occupational Therapy; Physical Therapy; Pelvic Floor Therapy; Speech Therapy | AA11: No | AB11: Yes | AC11: No | AD11: No | AE11: No | AF11: No | AG11: Jefferson Moss-Magee Rehabilitation – Cherry Hill offers a menu of services to assist an individual's recovery of functional ability regardless of the severity of the initial injury. | AH11: https://www.google.com/maps/place/2211+Chapel+Ave,+Cherry+Hill,+NJ+08002/@39.9287739,-75.0178616,17z/data=!3m1!4b1!4m5!3m4!1s0x89c6cba7c1ea5443:0x7fc8f435933835e3!8m2!3d39.9287698!4d-75.0156729 | AK11: https://www.jeffersonhealth.org/locations/moss-magee-rehabilitation-cherry-hill | AL11: 2026-07-07
A12: Jefferson Radiation Oncology – Cherry Hill | B12: Practice | D12: 2211 Chapel Ave West | E12: Cherry Hill | F12: NJ | G12: 08002 | I12: 39.928668 | J12: -75.015803 | K12: 856-922-4800 | M12: 856-922-4801 | O12: No | P12: 07:30 am - 04:00 pm | Q12: 07:30 am - 04:00 pm | R12: 07:30 am - 04:00 pm | S12: 07:30 am - 04:00 pm | T12: 07:30 am - 04:00 pm | U12: Closed | V12: Closed | X12: Radiation Oncology | AA12: Yes | AB12: Yes | AC12: No | AD12: Yes | AE12: No | AF12: No | AG12: Radiation oncology services at the Sidney Kimmel Comprehensive Cancer Center - Cherry Hill. | AK12: https://www.jeffersonhealth.org/locations/radiation-oncology-cherry-hill | AL12: 2026-01-24
A13: Jefferson Surgery Center - Cherry Hill | B13: Surgical Center | D13: 2211 Chapel Ave West | E13: Cherry Hill | F13: NJ | G13: 08002 | I13: 39.92805 | J13: -75.017723 | K13: 856-295-9041 | O13: No | P13: 06:00 am - 04:30 pm | Q13: 06:00 am - 04:30 pm | R13: 06:00 am - 04:30 pm | S13: 06:00 am - 04:30 pm | T13: 06:00 am - 04:30 pm | U13: Closed | V13: Closed | X13: General Surgery; Surgery; Gastroenterology & Hepatology | AA13: No | AB13: No | AC13: No | AD13: No | AE13: No | AF13: No | AG13: The Surgery team at Jefferson Surgery Center - Cherry Hill offers expertise you can trust throughout the greater South Jersey area. | AH13: https://www.google.com/maps/place/2211+Chapel+Ave+W+Ste+200,+Cherry+Hill,+NJ+08002/@39.9281152,-75.0168332,18z/data=!4m6!3m5!1s0x89c6cba7bdc5783b:0x959e4b94ad83bac7!8m2!3d39.9282252!4d-75.0159773!16s%2Fg%2F11tnj6y_t4?entry=ttu | AK13: https://www.jeffersonhealth.org/locations/surgery-center-cherry-hill | AL13: 2026-01-24
A14: Jefferson Urology – Cherry Hill | B14: Practice | D14: 63 Kresson Road, Suite 103 | E14: Cherry Hill | F14: NJ | G14: 08034 | I14: 39.89448 | J14: -75.01984 | K14: 844-542-2273 | M14: 856-667-2428 | O14: No | P14: 08:00 am - 04:30 pm | Q14: 08:00 am - 04:30 pm | R14: 08:00 am - 04:30 pm | S14: 08:00 am - 04:30 pm | T14: 08:00 am - 04:30 pm | U14: Closed | V14: Closed | X14: Urology | AA14: No | AB14: No | AC14: No | AD14: No | AE14: No | AF14: No | AG14: The urologist specialist team at Jefferson Urology – Cherry Hill collaborates with other specialists across programs and centers dedicated to your unique health needs – from cancer to men's health to LGBTQIA+ care – to provide you with complete urological care, close to home. | AH14: https://www.google.com/maps/place/63+Kresson+Rd,+Cherry+Hill+Township,+NJ+08034/@39.8945748,-75.0201016,17z/data=!3m1!4b1!4m6!3m5!1s0x89c6cc7c07d8a317:0xee6a9da1ab0dff8e!8m2!3d39.8945748!4d-75.0201016!16s%2Fg%2F11c3q39h3n?entry=ttu&g_ep=EgoyMDI1MTAyNy4wIKXMDSoASAFQAw%3D%3D | AK14: https://www.jeffersonhealth.org/locations/urology-cherry-hill | AL14: 2026-09-21
A15: Jefferson–Solis Mammography – Cherry Hill | B15: Imaging | C15: A department of Jefferson Cherry Hill Hospital | D15: 2201 Chapel Ave West | E15: Cherry Hill | F15: NJ | G15: 08002 | I15: 39.928736 | J15: -75.016597 | K15: 856-214-0693 | O15: No | P15: 06:30 am - 05:00 pm | Q15: 06:30 am - 05:00 pm | R15: 06:30 am - 05:00 pm | S15: 06:30 am - 05:00 pm | T15: 06:30 am - 05:00 pm | U15: 08:00 am - 12:00 pm | V15: Closed | X15: Breast Care; Breast Imaging; Women's Imaging; Imaging & Radiology | Z15: Abnormal Mammogram; Mammogram; Bone Densitometry; Breast Ultrasound; Breast Biopsy | AA15: Yes | AB15: Yes | AC15: Yes | AD15: Yes | AE15: No | AF15: No | AG15: Jefferson Health has partnered with Solis Mammography, the nation’s leader in screening and diagnostic mammography, to serve as an on-site provider of comprehensive breast imaging services at Jefferson locations throughout the greater Philadelphia and South Jersey area. | AH15: https://www.google.com/maps/place/Jefferson+Cherry+Hill+Hospital/@39.9287357,-75.0165973,17z/data=!3m1!4b1!4m6!3m5!1s0x89c6cba7982122fb:0x10ce11b5706b1486!8m2!3d39.9287357!4d-75.0165973!16s%2Fg%2F1tfn3pyq?entry=ttu | AI15: https://www.jeffersonhealth.org/locations/cherry-hill-hospital/getting-here | AK15: https://www.jeffersonhealth.org/locations/solis-mammography-cherry-hill | AL15: 2026-01-24
A16: Otolaryngology - Head & Neck Surgery at Cherry Hill | B16: Practice | D16: 2211 Chapel Avenue West, Suite 403 | E16: Cherry Hill | F16: NJ | G16: 08002 | I16: 39.928225 | J16: -75.015977 | K16: 856-922-5030 | M16: 856-662-2545 | O16: No | P16: 08:00 am - 04:30 pm | Q16: 08:00 am - 04:30 pm | R16: 08:00 am - 04:30 pm | S16: 08:00 am - 04:30 pm | T16: 08:00 am - 04:30 pm | U16: Closed | V16: Closed | X16: Otolaryngology; Head & Neck Surgery | AA16: No | AB16: No | AC16: No | AD16: No | AE16: No | AF16: Yes | AG16: Otolaryngology, head and neck surgery in Cherry Hill, NJ. | AH16: https://www.google.com/maps/place/2211+Chapel+Ave+W,+Cherry+Hill,+NJ+08002/@39.9282244,-75.0181662,17z/data=!3m1!4b1!4m5!3m4!1s0x89c6cba7c0924529:0x2552c2dddc9ce0fc!8m2!3d39.9282244!4d-75.0159775 | AK16: https://www.jeffersonhealth.org/locations/otolaryngology-head-neck-surgery-cherry-hill | AL16: 2026-01-24
A17: Delran Primary Care | B17: Practice | D17: 8008 Route 130 | E17: Delran | F17: NJ | G17: 08075 | I17: 40.02366 | J17: -74.937555 | K17: 844-542-2273 | M17: 856-764-1840 | O17: No | P17: 07:00 am - 07:00 pm | Q17: 07:00 am - 07:00 pm | R17: 08:00 am - 03:30 pm | S17: 07:30 am - 03:30 pm | T17: 07:00 am - 03:00 pm | U17: Closed | V17: Closed | W17: *Temporarily expanded office hours subject to change. | X17: Primary Care | AA17: No | AB17: No | AC17: No | AD17: No | AE17: No | AF17: Yes | AG17: Primary care services in Delran, NJ. | AH17: https://www.google.com/maps/place/Jefferson+Health+Delran+Primary+Care/@40.0236604,-74.9397437,17z/data=!3m1!4b1!4m5!3m4!1s0x89c14bc6221e5021:0x4f8058824b1ba562!8m2!3d40.0236604!4d-74.937555 | AK17: https://www.jeffersonhealth.org/locations/delran-primary-care | AL17: 2026-01-24
A18: 2500 English Creek Avenue | B18: Outpatient Medical Center | D18: 2500 English Creek Avenue | E18: Egg Harbor Township | F18: NJ | G18: 08234 | I18: 39.348042 | J18: -74.663464 | K18: 800-533-3669 | O18: No | X18: Liver Transplant; Transplant Institute; Kidney Transplant; Nephrology; Viral Hepatitis Care; Gastroenterology & Hepatology; Rothman Institute; Fatty Liver Care; Liver Tumor; Orthopedics | AA18: No | AB18: Yes | AC18: No | AD18: No | AE18: No | AF18: No | AG18: Digestive Health, Orthopaedics and Organ transplants in Egg Harbor Township, NJ. | AH18: https://www.google.com/maps/search/2500+English+Creek+Avenue,+Atlantic+Care+Complex,+Egg+Harbor+Township,+NJ+08234/@39.4348176,-74.607614,17z/data=!3m1!4b1 | AJ18: https://www.jeffersonhealth.org/locations/2500-english-creek-avenue/department-directory | AK18: https://www.jeffersonhealth.org/locations/2500-english-creek-avenue | AL18: 2026-03-25
A19: Jefferson Foot & Ankle – Haddonfield | B19: Practice | D19: 308 N. Haddon Avenue | E19: Haddonfield | F19: NJ | G19: 08033 | I19: 39.90234 | J19: -75.03923 | K19: 856-414-8799 | M19: 215-521-7139 | O19: No | P19: Closed | Q19: Closed | R19: 08:00 am - 04:00 pm | S19: 08:00 am - 03:00 pm | T19: 08:00 am - 03:00 pm | U19: Closed | V19: Closed | W19: *Wednesday, 1st and 4th of the month only* | X19: Foot & Ankle Orthopedic Surgery; Foot Orthopedic Surgery; Lower Extremity Orthopedics | Y19: Foot Problems & Pain; Arthritis; Osteoarthritis | AA19: No | AB19: No | AC19: No | AD19: No | AE19: No | AF19: No | AG19: Jefferson Foot & Ankle – Haddonfield offers lower extremity orthopedics services to its patients. | AH19: https://www.google.com/maps/place/Jefferson+Foot+%26+Ankle+Surgery+-+Haddonfield/@39.9024466,-75.0391575,15z/data=!4m2!3m1!1s0x0:0xada2306aea499bca?sa=X&ved=1t:2428&hl=en&ictx=111 | AK19: https://www.jeffersonhealth.org/locations/foot-ankle-haddonfield | AL19: 2026-05-04
A20: Jefferson Pride Care | B20: Practice | D20: 15 E. Redman Avenue | E20: Haddonfield | F20: NJ | G20: 08033 | I20: 39.89969 | J20: -75.03466 | K20: 856-414-8758 | M20: 856-429-0891 | O20: No | P20: 08:00 am - 07:40 pm | Q20: 08:00 am - 05:00 pm | R20: 08:00 am - 07:00 pm | S20: 08:00 am - 06:00 pm | T20: 08:00 am - 04:30 pm | U20: Closed | V20: Closed | X20: Pride Care; Family & Community Medicine; Ryan White Program; Breast Care; Primary Care; Obstetrics & Gynecology; Midwifery; Sleep Medicine; Infectious Diseases; Breast Surgery | AA20: Yes | AB20: Yes | AC20: No | AD20: No | AE20: No | AF20: No | AG20: Primary care and specialty services for LGBTQIA+ patients at Jefferson Pride Care. | AH20: https://www.google.com/maps/dir//Jefferson+Pride+Care/data=!4m6!4m5!1m1!4e2!1m2!1m1!1s0x89c6cd5cf24cb433:0x987f00bb4d17feda?sa=X&ved=1t:3061&hl=en&ictx=111 | AJ20: https://www.jeffersonhealth.org/locations/pride-care/department-directory | AK20: https://www.jeffersonhealth.org/locations/pride-care | AL20: 2026-09-30
A21: Jefferson Primary & Specialty Care – Haddonfield | B21: Practice | D21: 80 Tanner Street | E21: Haddonfield | F21: NJ | G21: 08033 | I21: 39.900329 | J21: -75.039516 | K21: 856-922-9700 | M21: 856-428-6334 | O21: No | P21: 08:00 am - 08:00 pm | Q21: 07:40 am - 07:20 pm | R21: 08:00 am - 08:00 pm | S21: 08:00 am - 08:00 pm | T21: 08:00 am - 04:00 pm | U21: Closed | V21: Closed | X21: Primary Care; Family & Community Medicine | AA21: No | AB21: No | AC21: No | AD21: No | AE21: No | AF21: Yes | AG21: Jefferson Primary & Specialty Care – Haddonfield (formerly Redman Avenue Primary Care) offers primary care & family medicine services in Haddonfield, NJ. | AH21: https://www.google.com/maps/dir//Redman+Avenue+Primary+Care/data=!4m6!4m5!1m1!4e2!1m2!1m1!1s0x89c6cd448e6fe2d7:0x334b1218a755116a?sa=X&ved=1t:3061&hl=en&ictx=111 | AK21: https://www.jeffersonhealth.org/locations/primary-specialty-haddonfield | AL21: 2026-08-31
A22: Jefferson Outpatient Imaging – Marlton | B22: Imaging | D22: 999 Route 73 North | E22: Marlton | F22: NJ | G22: 08053 | I22: 39.907864 | J22: -74.942703 | K22: 215-503-4900 | M22: 215-521-6432 | O22: No | X22: Outpatient Imaging; Imaging & Radiology | AA22: No | AB22: No | AC22: No | AD22: No | AE22: No | AF22: No | AG22: The Jefferson Outpatient Imaging – Marlton location offers outpatient imaging services to its patients. | AH22: https://maps.app.goo.gl/JyWYfuDGsCwp7zqEA | AK22: https://www.jeffersonhealth.org/locations/999-route-73 | AL22: 2026-02-02
A23: Marlton Primary & Specialty Care | B23: Practice | D23: 73 North Maple Avenue, Suite A, B, C | E23: Marlton | F23: NJ | G23: 08053 | I23: 39.907203 | J23: -74.921992 | K23: 844-542-2273 | M23: 856-596-4043 | O23: No | P23: 07:40 am - 07:00 pm | Q23: 07:20 am - 07:00 pm | R23: 07:20 am - 05:40 pm | S23: 07:40 am - 07:00 pm | T23: 07:40 am - 03:40 pm | U23: Closed | V23: Closed | W23: *Temporarily expanded office hours subject to change. | X23: Primary Care; Neuroscience; Family & Community Medicine; Endocrinology, Diabetes, & Metabolic Diseases; Comprehensive Weight Management; Rheumatology; Colorectal Surgery; Nutrition; Neurology | AA23: No | AB23: No | AC23: No | AD23: No | AE23: No | AF23: No | AG23: Primary & specialty care services in Marlton, NJ. | AH23: https://www.google.com/maps/place/Jefferson+Health+Marlton+Primary+%26+Specialty+Care/@39.9072033,-74.9241808,17z/data=!3m1!4b1!4m5!3m4!1s0x89c1348830201adb:0xf8ccde9caeff6d31!8m2!3d39.9072033!4d-74.9220035 | AJ23: https://www.jeffersonhealth.org/locations/marlton-primary-specialty-care/department-directory | AK23: https://www.jeffersonhealth.org/locations/marlton-primary-specialty-care | AL23: 2026-09-23
A24: 445 Hurffville Crosskeys Road | B24: Practice | D24: 445 Hurffville-Crosskeys Road | E24: Sewell | F24: NJ | G24: 08080 | I24: 39.735518 | J24: -75.137406 | K24: 1-800-JEFF-NOW | M24: 856-256-7595 | O24: No | X24: Spine Care; Neuroscience; Neurosurgery; Stroke Care | AA24: No | AB24: Yes | AC24: No | AD24: No | AE24: No | AF24: No | AG24: Neurosurgery, Spine Program, and Comprehensive Stroke Center in Sewell, NJ. | AH24: https://www.google.com/maps/place/Parking+lot,+445+Hurffville+-+Cross+Keys+Rd,+Sewell,+NJ+08080/@39.7357444,-75.0677309,17z/data=!3m1!4b1!4m5!3m4!1s0x89c6d6af5a66d70b:0x503a9727938554f7!8m2!3d39.7357444!4d-75.0677309 | AK24: https://www.jeffersonhealth.org/locations/445-hurffville-crosskeys-road | AL24: 2026-01-24
A25: Fibroid Center - 555 Egg Harbor Road | B25: Practice | D25: 555 Egg Harbor Road | E25: Sewell | F25: NJ | G25: 08080 | I25: 39.735838 | J25: -75.065937 | K25: 856-582-2555 | O25: No | P25: 07:30 am - 05:00 pm | Q25: 07:30 am - 05:00 pm | R25: 07:30 am - 05:00 pm | S25: 07:30 am - 05:00 pm | T25: 07:30 am - 05:00 pm | U25: Closed | V25: Closed | X25: Fibroid Care; Interventional Radiology | Z25: Uterine Fibroid Embolization | AA25: No | AB25: No | AC25: No | AD25: No | AE25: No | AF25: No | AH25: https://goo.gl/maps/ZCSS28x6dng1vUNy5 | AK25: https://www.jeffersonhealth.org/locations/fibroid-center-555-egg-harbor-road | AL25: 2026-01-24
A26: Gynecologic Oncology - 900 Medical Center Drive | B26: Practice | D26: 900 Medical Center Drive, Suite 205 | E26: Sewell | F26: NJ | G26: 08080 | I26: 39.73857 | J26: -75.064683 | K26: 856-557-5400 | M26: 856-553-6713 | O26: No | P26: 08:00 am - 04:30 pm | Q26: 08:00 am - 04:30 pm | R26: 08:00 am - 04:30 pm | S26: 08:00 am - 04:30 pm | T26: 08:00 am - 04:30 pm | U26: Closed | V26: Closed | W26: *Temporarily expanded office hours subject to change. | X26: Gynecologic Oncology | AA26: Yes | AB26: Yes | AC26: Yes | AD26: Yes | AE26: No | AF26: No | AG26: Gynecologic oncology services at Sidney Kimmel Comprehensive Cancer Center - Washington Township. | AH26: https://www.google.com/maps/place/Jefferson+Health+Washington+Township+Gynecologic+Oncology/@39.7384935,-75.0668592,17z/data=!3m1!4b1!4m5!3m4!1s0x89c6d73f04855df1:0x54b13acb9d075f3b!8m2!3d39.7384004!4d-75.0648703 | AK26: https://www.jeffersonhealth.org/locations/gynecologic-oncology-900-medical-center-drive | AL26: 2026-01-24
A27: Jefferson Breast Surgery – Washington Township | B27: Practice | D27: 900 Medical Center Drive, Suite 201 | E27: Sewell | F27: NJ | G27: 08080 | I27: 39.738613 | J27: -75.064674 | K27: 856-218-2100 | M27: 856-218-2101 | O27: No | P27: 08:30 am - 05:00 pm | Q27: 08:30 am - 05:00 pm | R27: 08:30 am - 05:00 pm | S27: 08:30 am - 05:00 pm | T27: 08:30 am - 05:00 pm | U27: Closed | V27: Closed | X27: Breast Surgery; Breast Care; Breast Medical Oncology | Z27: Top Surgery | AA27: Yes | AB27: Yes | AC27: Yes | AD27: Yes | AE27: No | AF27: No | AG27: Jefferson Breast Surgery at Sidney Kimmel Comprehensive Cancer Center – Washington Township offers comprehensive breast care to its patients. | AH27: https://www.google.com/maps/place/Jefferson+Health+Comprehensive+Breast+Center/@39.7386168,-75.0668625,17z/data=!3m1!4b1!4m5!3m4!1s0x89c6d789172fa219:0x5abf66759f91cc70!8m2!3d39.7384896!4d-75.064938 | AK27: https://www.jeffersonhealth.org/locations/comprehensive-breast-center-900-medical-center-drive | AL27: 2026-04-15
A28: Jefferson Outpatient Imaging – Washington Township | B28: Imaging | D28: 243 Hurffville Crosskeys Road | E28: Sewell | F28: NJ | G28: 08080 | I28: 39.722378 | J28: -75.045057 | K28: 215-503-4900 | O28: No | X28: Outpatient Imaging; Women's Imaging; Ultrasound; Imaging & Radiology | Z28: Ultrasound; Abnormal Mammogram; Mammogram | AA28: No | AB28: No | AC28: No | AD28: No | AE28: No | AF28: No | AG28: Jefferson Outpatient Imaging – Washington Township offers outpatient imaging services to its patients. | AH28: https://goo.gl/maps/a2cybUkZdoHbdPNBA | AK28: https://www.jeffersonhealth.org/locations/243-hurffville-crosskeys-road | AL28: 2026-01-24
A29: Jefferson Primary & Specialty Care – Fish Pond Road | B29: Practice | D29: 354 Hurffville - Cross Keys Road | E29: Sewell | F29: NJ | G29: 08080 | I29: 39.730275 | J29: -75.058859 | K29: 1-800-JEFF-NOW | O29: No | P29: 07:30 am - 05:00 pm | Q29: 07:30 am - 05:00 pm | R29: 07:30 am - 05:00 pm | S29: 07:30 am - 05:00 pm | T29: 07:30 am - 05:00 pm | U29: Closed | V29: Closed | X29: Primary Care; Nutrition; Infectious Diseases; Family & Community Medicine; Endocrinology, Diabetes, & Metabolic Diseases; Urology; Behavioral Medicine; Gastroenterology & Hepatology; General Surgery; Pain Management; Rheumatology; Vascular Surgery; Colorectal Surgery; Allergy & Immunology; Otolaryngology; Comprehensive Weight Management; Ryan White Program; Bariatric Surgery; Bariatric Surgery Program | AA29: Yes | AB29: Yes | AC29: No | AD29: No | AE29: No | AF29: No | AG29: Jefferson Primary & Specialty Care – Fish Pond Road offers both primary and specialty care services in Washington Township, NJ. | AH29: https://www.google.com/maps/place/Jefferson+Health+Fish+Pond+Primary+%26+Specialty+Care/@39.7293674,-75.0589016,15z/data=!4m2!3m1!1s0x0:0x68d496400eda2d0e?sa=X&ved=2ahUKEwjg9pXYkt7zAhUrU98KHZ-_D2oQ_BJ6BAhSEAU | AJ29: https://www.jeffersonhealth.org/locations/primary-specialty-care-fish-pond-road/department-directory | AK29: https://www.jeffersonhealth.org/locations/primary-specialty-care-fish-pond-road | AL29: 2026-08-06
A30: Jefferson Radiation Oncology – Washington Township | B30: Practice | D30: 900 Medical Center Drive, Suite 100 | E30: Sewell | F30: NJ | G30: 08080 | I30: 39.73864 | J30: -75.06423 | K30: 856-582-3008 | M30: 856-582-3009 | O30: No | P30: 08:30 am - 05:00 pm | Q30: 08:30 am - 05:00 pm | R30: 08:30 am - 05:00 pm | S30: 08:30 am - 05:00 pm | T30: 08:30 am - 05:00 pm | U30: Closed | V30: Closed | X30: Radiation Oncology | AA30: Yes | AB30: Yes | AC30: Yes | AD30: Yes | AE30: No | AF30: No | AG30: Radiation oncology services at the Sidney Kimmel Comprehensive Cancer Center - Washington Township. | AH30: https://maps.app.goo.gl/AfVC3maQZBTstM4g7 | AK30: https://www.jeffersonhealth.org/locations/jefferson-radiation-oncology-at-washington-township | AL30: 2026-01-24
A31: Jefferson Specialty Care – Washington Township | B31: Practice | D31: 400 Medical Center Drive, Suite F | E31: Sewell | F31: NJ | G31: 08080 | I31: 39.737662 | J31: -75.066067 | K31: 1-800-JEFF-NOW | O31: No | P31: 08:00 am - 04:30 pm | Q31: 08:00 am - 04:30 pm | R31: 08:00 am - 04:30 pm | S31: 08:00 am - 04:30 pm | T31: 08:00 am - 04:30 pm | U31: Closed | V31: Closed | X31: Cancer; Breast Care; Cardiology; Heart & Vascular; Breast Surgery | Y31: Breast Cancer; Heart Failure | AA31: Yes | AB31: Yes | AC31: No | AD31: No | AE31: No | AF31: No | AG31: Jefferson Health offers breast surgery and cardiology care in Washington Township, NJ. | AH31: https://www.google.com/maps/place/Jefferson+Specialty+Care+%E2%80%93+Washington+Township/data=!4m2!3m1!1s0x0:0x9f05de5f8d6f551d?sa=X&ved=1t:2428&hl=en&ictx=111 | AJ31: https://www.jeffersonhealth.org/locations/specialty-care-washington-township/department-directory | AK31: https://www.jeffersonhealth.org/locations/specialty-care-washington-township | AL31: 2026-04-15
A32: Jefferson–Solis Mammography – Washington Township | B32: Imaging | C32: A department of Jefferson Washington Township Hospital | D32: 900 Medical Center Drive, Suite 101 | E32: Sewell | F32: NJ | G32: 08080 | I32: 39.789111 | J32: -75.055274 | K32: 856-474-1445 | O32: No | P32: 07:00 am - 06:00 pm | Q32: 07:00 am - 06:00 pm | R32: 07:00 am - 06:00 pm | S32: 07:00 am - 06:00 pm | T32: 07:00 am - 05:00 pm | U32: Closed | V32: Closed | W32: * Sat: Call for Information. | X32: Breast Care; Breast Imaging; Women's Imaging; Imaging & Radiology | Z32: Abnormal Mammogram; Mammogram; Breast Ultrasound; Breast Biopsy | AA32: Yes | AB32: Yes | AC32: No | AD32: Yes | AE32: No | AF32: No | AG32: Jefferson Health has partnered with Solis Mammography, the nation’s leader in screening and diagnostic mammography, to serve as an on-site provider of comprehensive breast imaging services at Jefferson locations throughout the greater Philadelphia and South Jersey area. | AH32: https://maps.app.goo.gl/FEHTcenWXY5XLmPm9 | AI32: https://www.jeffersonhealth.org/locations/washington-township-hospital/getting-here | AK32: https://www.jeffersonhealth.org/locations/solis-mammography-washington-township | AL32: 2026-01-24
A33: Medical Oncology & Infusion Suite - 900 Medical Center Drive | B33: Practice | D33: 900 Medical Center Drive, Suite 200 | E33: Sewell | F33: NJ | G33: 08080 | I33: 39.738613 | J33: -75.066862 | K33: 856-557-7900 | M33: 856-589-3989 | O33: No | P33: 08:30 am - 05:00 pm | Q33: 08:30 am - 05:00 pm | R33: 08:30 am - 05:00 pm | S33: 08:30 am - 05:00 pm | T33: 08:30 am - 05:00 pm | U33: Closed | V33: Closed | X33: Medical Oncology; Hematology; Brain Tumor Care | AA33: Yes | AB33: Yes | AC33: Yes | AD33: Yes | AE33: No | AF33: No | AG33: Medical oncology services at Sidney Kimmel Comprehensive Cancer Center - Washington Township. | AH33: https://www.google.com/maps/place/900+Medical+Center+Dr,+Blackwood,+NJ+08012/@39.7386127,-75.0668625,17z/data=!3m1!4b1!4m5!3m4!1s0x89c6d6a90e6333a5:0x5acc727456308c35!8m2!3d39.7386127!4d-75.0646738 | AK33: https://www.jeffersonhealth.org/locations/medical-oncology-infusion-suite-900-medical-center-drive | AL33: 2026-01-24
A34: Neurosciences Center Washington Township | B34: Practice | D34: 445 Hurffville Cross Keys Road, Suite B16 | E34: Sewell | F34: NJ | G34: 08080 | I34: 39.735539 | J34: -75.067366 | K34: 856-352-6660 | M34: 856-269-4258 | O34: No | P34: 08:00 am - 05:00 pm | Q34: 08:00 am - 05:00 pm | R34: 08:00 am - 05:00 pm | S34: 08:00 am - 05:00 pm | T34: 08:00 am - 05:00 pm | U34: Closed | V34: Closed | X34: Neuroscience; Neurology | AA34: No | AB34: No | AC34: No | AD34: No | AE34: No | AF34: Yes | AG34: Neuroscience services in Washington Township, NJ. | AH34: https://www.google.com/maps/place/Parking+lot,+445+Hurffville+-+Cross+Keys+Rd+B16,+Sewell,+NJ+08080/data=!4m2!3m1!1s0x89c6d6af56baaaab:0x5e65d2451ebaccf?sa=X&ved=2ahUKEwjDmr7hsd7zAhUrhOAKHS_6Dh4Q8gF6BAgSEAE | AK34: https://www.jeffersonhealth.org/locations/neurosciences-center-washington-township | AL34: 2026-04-28
A35: Point Plaza - Jefferson Gastroenterology | B35: Practice | D35: 565 Egg Harbor Road | E35: Sewell | F35: NJ | G35: 08080 | I35: 39.735304 | J35: -75.06434 | K35: 844-542-2273 | M35: 856-256-1188 | O35: No | P35: 08:00 am - 05:00 pm | Q35: 08:00 am - 05:00 pm | R35: 08:00 am - 05:00 pm | S35: 08:00 am - 05:00 pm | T35: 08:00 am - 05:00 pm | U35: Closed | V35: Closed | X35: Primary Care; Gastroenterology & Hepatology | AA35: No | AB35: No | AC35: No | AD35: No | AE35: No | AF35: Yes | AG35: Primary and specialty care services in Sewell, NJ. | AH35: https://www.google.com/maps/place/Jefferson+Health+Washington+Township+Care+Now/@39.7345942,-75.0663995,17z/data=!3m1!4b1!4m5!3m4!1s0x89c6d6a7c889d3e7:0x98d78d4eb6fe9ca1!8m2!3d39.7346179!4d-75.0642296 | AK35: https://www.jeffersonhealth.org/locations/point-plaza-primary-care | AL35: 2026-01-24
A36: Sewell Primary Care | B36: Practice | D36: 485 Hurffville Cross Keys Road | E36: Sewell | F36: NJ | G36: 08080 | I36: 39.73913 | J36: -75.07323 | K36: 856-557-5555 | M36: 856-218-8192 | O36: No | P36: 08:00 am - 05:00 pm | Q36: 08:00 am - 07:30 pm | R36: 08:00 am - 05:00 pm | S36: 08:00 am - 05:00 pm | T36: 08:00 am - 05:00 pm | U36: Closed | V36: Closed | X36: Psychiatry & Human Behavior; Primary Care; Nutrition | AA36: No | AB36: No | AC36: No | AD36: No | AE36: No | AF36: Yes | AG36: Primary care, behavioral health, and nutrition services in Sewell, NJ. | AH36: https://www.google.com/maps/place/Jefferson+Health+Sewell+Obstetrics+%26+Gynecology/@39.7390546,-75.0759425,17z/data=!3m1!4b1!4m5!3m4!1s0x89c6d4084c044083:0xbbf79d5ade0f6cb!8m2!3d39.7389967!4d-75.073809 | AK36: https://www.jeffersonhealth.org/locations/sewell-primary-care | AL36: 2026-02-27
A37: Sidney Kimmel Comprehensive Cancer Center — Washington Township | B37: Imaging; Outpatient Medical Center | D37: 900 Medical Center Drive | E37: Sewell | F37: NJ | G37: 08080 | I37: 39.738524 | J37: -75.064677 | K37: 856-218-5324 | M37: 856-218-5327 | O37: No | P37: 08:30 am - 05:00 pm | Q37: 08:30 am - 05:00 pm | R37: 08:30 am - 05:00 pm | S37: 08:30 am - 05:00 pm | T37: 08:30 am - 05:00 pm | U37: Closed | V37: Closed | X37: Radiation Oncology; Medical Oncology; Nutrition; Neurosurgery; Breast Medical Oncology; Lung Cancer, Screening, and Nodules; Cardiothoracic Surgery; Imaging & Radiology; Respiratory & Pulmonary Medicine; Sleep Medicine; Cancer; Senior Adult Oncology Center; Breast Care; Outpatient Imaging | Y37: Throat Cancer; Ovarian Cancer; Parathyroid Cancer | AA37: Yes | AB37: Yes | AC37: Yes | AD37: Yes | AE37: No | AF37: No | AG37: Comprehensive cancer services in Washington Township, NJ. | AH37: https://www.google.com/maps/place/Sidney+Kimmel+Cancer+Center+-+Washington+Township/@39.7385238,-75.0668656,17z/data=!3m1!4b1!4m5!3m4!1s0x89c6d6a90d701b4d:0xb264e85f4f581ea3!8m2!3d39.738425!4d-75.064889 | AJ37: https://www.jeffersonhealth.org/locations/sidney-kimmel-cancer-center-washington-township/department-directory | AK37: https://www.jeffersonhealth.org/locations/sidney-kimmel-cancer-center-washington-township | AL37: 2026-03-25
A38: Surgery Center - Washington Township | B38: Surgical Center | D38: 540 Egg Harbor Road | E38: Sewell | F38: NJ | G38: 08080 | I38: 39.948189 | J38: -75.002697 | K38: 856-218-4900 | M38: 856-256-1276 | O38: No | P38: 06:00 am - 04:30 pm | Q38: 06:00 am - 04:30 pm | R38: 06:00 am - 04:30 pm | S38: 06:00 am - 04:30 pm | T38: 06:00 am - 04:30 pm | U38: Closed | V38: Closed | X38: General Surgery; Surgery; Gastroenterology & Hepatology | AA38: Yes | AB38: Yes | AC38: No | AD38: No | AE38: No | AF38: No | AG38: The Surgery team at Jefferson Surgery Center - Washington Township offers expertise you can trust throughout the greater South Jersey area. | AH38: https://www.google.com/maps/dir//washington+township+surgical+center/data=!4m6!4m5!1m1!4e2!1m2!1m1!1s0x89c6d6a8ff2ae6f3:0x9dc4dcd0d1358f4a?sa=X&ved=2ahUKEwjcp--V1J75AhXWFFkFHf0oDyYQ9Rd6BAgOEAU | AK38: https://www.jeffersonhealth.org/locations/surgery-center-washington-township | AL38: 2026-01-24
A39: Jefferson Moss-Magee Rehabilitation – Stratford | B39: Outpatient Rehabilitation | D39: 18 Laurel Rd | E39: Stratford | F39: NJ | G39: 08084 | I39: 39.824483 | J39: -75.012932 | K39: 856-346-7842 | M39: 856-346-6013 | O39: No | X39: Rehabilitation Medicine; Outpatient Rehabilitation; Physical Therapy; Occupational Therapy; Speech Therapy Program; Brain Injury Rehabilitation | Y39: Pelvic Floor Disorder; Lymphedema; Concussion & Head Injuries | Z39: Physical Therapy; Occupational Therapy; Speech Therapy; Pelvic Floor Therapy | AA39: No | AB39: No | AC39: No | AD39: No | AE39: No | AF39: No | AG39: Jefferson Moss-Magee Rehabilitation – Stratford is the largest provider of Physical Medicine and Rehabilitation in the New Jersey region. | AH39: https://www.google.com/maps/place/18+Laurel+Rd,+Stratford,+NJ+08084/@39.8244827,-75.0129319,17z/data=!3m1!4b1!4m6!3m5!1s0x89c6cd793c62866b:0xf10697feea62a4c5!8m2!3d39.8244786!4d-75.010357!16s%2Fg%2F11bw42j31h?entry=ttu | AK39: https://www.jeffersonhealth.org/locations/moss-magee-rehabilitation-stratford | AL39: 2026-07-07
A40: Jefferson Stratford Hospital | B40: Hospital; Imaging | C40: Hospital | D40: 18 East Laurel Road | E40: Stratford | F40: NJ | G40: 08084 | I40: 39.828168 | J40: -75.008266 | K40: 856-346-6000 | L40: Emergency Department: 856-346-7816 | O40: Yes | P40: Open 24 hours | Q40: Open 24 hours | R40: Open 24 hours | S40: Open 24 hours | T40: Open 24 hours | U40: Open 24 hours | V40: Open 24 hours | X40: Neurology; Balance & Hearing; Psychiatry & Human Behavior; Imaging & Radiology; Nutrition; Stroke; Acute Care For Elders Unit; Pelvic Health; Emergency Medicine; Minimally Invasive & Robotic Surgery; Interventional Radiology; Fibroid Care; Hospital Medicine; Hospice & Palliative Care; Outpatient Imaging | Y40: Lymphedema | Z40: Kidney Dialysis | AA40: Yes | AB40: Yes | AC40: No | AD40: Yes | AE40: No | AF40: No | AG40: Expert healthcare, close to home. | AH40: https://www.google.com/maps/place/18+E+Laurel+Rd,+Stratford,+NJ+08084/data=!4m2!3m1!1s0x89c6cd7a0038b1a5:0xfa79a1ef90d1a29a?sa=X&ved=2ahUKEwjSu6mkpPv3AhXpjYkEHZ8CAYsQ8gF6BAgKEAE | AI40: https://www.jeffersonhealth.org/locations/stratford-hospital/getting-here | AJ40: https://www.jeffersonhealth.org/locations/stratford-hospital/department-directory | AK40: https://www.jeffersonhealth.org/locations/stratford-hospital | AL40: 2026-08-28
A41: Jefferson Health – Turnersville | B41: Practice | D41: 188 Fries Mill Road | E41: Turnersville | F41: NJ | G41: 08012 | I41: 39.789111 | J41: -75.055274 | K41: 1-800-JEFF-NOW | O41: No | P41: 08:00 am - 05:00 pm | Q41: 08:00 am - 05:00 pm | R41: 08:00 am - 05:00 pm | S41: 08:00 am - 05:00 pm | T41: 08:00 am - 05:00 pm | U41: Closed | V41: Closed | X41: Otolaryngology; Neurology | AA41: No | AB41: No | AC41: No | AD41: No | AE41: No | AF41: No | AG41: Multidisciplinary outpaitent practice in Turnersville, NJ. | AH41: http://maps.google.com/?q=188+Fries+Mill+Road%2c+Turnersville%2c+NJ+08012 | AJ41: https://www.jeffersonhealth.org/locations/turnersville/department-directory | AK41: https://www.jeffersonhealth.org/locations/turnersville | AL41: 2026-05-26
A42: Jefferson Moss-Magee Rehabilitation – Washington Township | B42: Outpatient Rehabilitation | D42: 405 Hurffville-Cross Keys Road | E42: Turnersville | F42: NJ | G42: 08012 | I42: 39.732921 | J42: -75.061335 | K42: 856-256-7871 | M42: 856-582-3415 | O42: No | X42: Brain Injury Rehabilitation; Occupational Therapy; Rehabilitation Medicine; Pediatric Rehabilitation Medicine; Outpatient Rehabilitation; Physical Therapy; Speech Therapy Program | Y42: Lymphedema; Concussion & Head Injuries | Z42: Occupational Therapy; Vestibular Therapy; Speech Therapy | AA42: No | AB42: No | AC42: No | AD42: No | AE42: No | AF42: No | AG42: Jefferson Moss-Magee Rehabilitation – Washington Township offer outpatient rehabilitation and physical therapy in Washington Township, New Jersey. | AH42: https://www.google.com/maps/place/405+Hurffville+-+Cross+Keys+Rd,+Sewell,+NJ+08080/@39.732921,-75.0613351,17z/data=!3m1!4b1!4m5!3m4!1s0x89c6d41d5ffb0023:0x8d996b9332215771!8m2!3d39.732921!4d-75.0613351 | AK42: https://www.jeffersonhealth.org/locations/jefferson-rehabilitation-washington-township | AL42: 2026-03-25
A43: Jefferson Specialty Care – Turnersville | B43: Practice | D43: 188 Fries Mill Road | E43: Turnersville | F43: NJ | G43: 08012 | I43: 39.7373 | J43: -75.04669 | K43: 1-800-JEFF-NOW | O43: No | P43: 08:00 am - 04:00 pm | Q43: Closed | R43: Closed | S43: 08:00 am - 03:30 pm | T43: Closed | U43: Closed | V43: Closed | W43: Open 8:00am-4:00pm the 2nd Wednesday of the month and 7:00am-4:00pm the 3rd Wednesday of the month | X43: Foot Orthopedic Surgery; Foot & Ankle Orthopedic Surgery; Lower Extremity Orthopedics; Nephrology; Podiatry | Y43: Foot Problems & Pain; Arthritis; Osteoarthritis | AA43: No | AB43: No | AC43: No | AD43: No | AE43: No | AF43: No | AG43: Jefferson Specialty Care – Turnersville offers lower extremity orthopedics and nephrology services to its patients. | AH43: https://www.google.com/maps/place/Jefferson+Foot+%26+Ankle+Surgery+-+Turnersville/@39.7370651,-75.0468507,15z/data=!4m6!3m5!1s0x89c6d5ede8c01371:0x96e48e1a0f00ed4b!8m2!3d39.7370651!4d-75.0468507!16s%2Fg%2F11wfjmzz1b?hl=en-US&entry=ttu&g_ep=EgoyMDI0MDkyMi4wIKXMDSoASAFQAw%3D%3D | AJ43: https://www.jeffersonhealth.org/locations/specialty-care-turnersville/department-directory | AK43: https://www.jeffersonhealth.org/locations/specialty-care-turnersville | AL43: 2026-04-29
A44: Jefferson Washington Township Hospital | B44: Hospital | C44: Hospital | D44: 435 Hurffville-Cross Keys Road | E44: Turnersville | F44: NJ | G44: 08012 | I44: 39.735263 | J44: -75.065316 | K44: 856-582-2500 | L44: Emergency Department: 856-582-2816 | O44: Yes | P44: Open 24 hours | Q44: Open 24 hours | R44: Open 24 hours | S44: Open 24 hours | T44: Open 24 hours | U44: Open 24 hours | V44: Open 24 hours | X44: Cancer Rehabilitation; Maternal & Fetal Medicine; Neurology; Balance & Hearing; Behavioral Medicine; Psychiatry & Human Behavior; Cancer; Obstetrics & Maternity Care; Obstetrics; Neuroscience; Nutrition; Orthopedics; General Surgery; Sleep Medicine; Stroke; Wound Care & Hyperbaric Oxygen Therapy; Emergency Medicine; Pediatric Emergency Medicine; Interventional Cardiology; Surgery; CenteringPregnancy®; Interventional Radiology; Fibroid Care; Hospital Medicine; Stroke Care; Physical Therapy; Occupational Therapy; Speech Therapy Program; Pediatric Rehabilitation Medicine; Lower Extremity Orthopedics; Pediatrics; Gastroenterology & Hepatology | Z44: Cardiac Catheterization; Kidney Dialysis; Coronary Angioplasty; Hand & Upper Limb Therapy; Cancer Rehabilitation; Parkinsons Disease Rehabilitation; Vestibular Therapy | AA44: Yes | AB44: Yes | AC44: No | AD44: Yes | AE44: No | AF44: No | AG44: This newly renovated hospital serves the communities healthcare needs in South Jersey with amenities including private rooms, a state-of-the-art cafeteria & more. | AH44: https://maps.app.goo.gl/FxzjxRfPWawfHqXq7 | AI44: https://www.jeffersonhealth.org/locations/washington-township-hospital/getting-here | AJ44: https://www.jeffersonhealth.org/locations/washington-township-hospital/department-directory | AK44: https://www.jeffersonhealth.org/locations/washington-township-hospital | AL44: 2026-10-01
A45: Regulus Specialty Care | B45: Practice | D45: 1A Regulus Drive | E45: Turnersville | F45: NJ | G45: 08012 | I45: 39.73364 | J45: -75.06647 | K45: 844-542-2273 | M45: 856-553-4390 | O45: No | P45: 07:45 am - 05:40 pm | Q45: 07:45 am - 05:00 pm | R45: 07:45 am - 05:00 pm | S45: 07:45 am - 05:00 pm | T45: 07:45 am - 03:00 pm | U45: Closed | V45: Closed | X45: Cardiothoracic Surgery; Lung Cancer, Screening, and Nodules; Sleep Medicine; Respiratory & Pulmonary Medicine; Cardiology; Thoracic Surgery; Thoracic & Esophageal Surgery; Heart & Vascular; Heart Failure Care | AA45: No | AB45: No | AC45: No | AD45: No | AE45: No | AF45: No | AG45: Regulus Specialty Care in Turnersville, NJ offers multiple specialties to its patients, including cardiology, thoracic surgery and sleep medicine. | AH45: https://www.google.com/maps/place/1A+Regulus+Dr,+Turnersville,+NJ+08012/@39.733511,-75.069258,17z/data=!3m1!4b1!4m5!3m4!1s0x89c6d6a5d8580683:0xcf4e9d6a2000c4bb!8m2!3d39.733511!4d-75.0670693 | AJ45: https://www.jeffersonhealth.org/locations/regulus-specialty-care/department-directory | AK45: https://www.jeffersonhealth.org/locations/regulus-specialty-care | AL45: 2026-04-28
A46: Washington Township Primary Care | B46: Practice | D46: 188 Fries Mill Road, Suite N3 | E46: Turnersville | F46: NJ | G46: 08012 | I46: 39.737407 | J46: -75.046698 | K46: 856-875-8000 | M46: 856-875-8494 | O46: No | P46: 07:30 am - 08:00 pm | Q46: 07:15 am - 08:00 pm | R46: 07:15 am - 08:00 pm | S46: 07:15 am - 07:30 pm | T46: 07:30 am - 04:00 pm | U46: Closed | V46: Closed | W46: *Temporarily expanded office hours subject to change. | X46: Primary Care; Family & Community Medicine | AA46: No | AB46: No | AC46: No | AD46: No | AE46: No | AF46: Yes | AG46: Primary care and family medicine services in Washington Township, NJ. | AH46: https://www.google.com/maps/place/Jefferson+Health+Washington+Township+Primary+%26+Specialty+Care/@39.7374069,-75.0488868,17z/data=!3m1!4b1!4m5!3m4!1s0x89c6d5a37e73e627:0x9e40e4fe1a6d2f77!8m2!3d39.7373348!4d-75.0467141 | AK46: https://www.jeffersonhealth.org/locations/washington-township-primary-care | AL46: 2026-08-19
A47: Voorhees Primary Care | B47: Practice | D47: 443 Laurel Oak Road, Suite 130 | E47: Voorhees | F47: NJ | G47: 08043 | I47: 39.838378 | J47: -74.932568 | K47: 844-542-2273 | M47: 856-770-9194 | O47: No | P47: 08:00 am - 05:00 pm | Q47: 08:00 am - 07:00 pm | R47: 08:00 am - 07:00 pm | S47: 08:00 am - 08:00 pm | T47: 08:00 am - 04:00 pm | U47: Closed | V47: Closed | X47: Internal Medicine; Family & Community Medicine; Primary Care; Psychiatry & Human Behavior; Nutrition; Dietetics; Allergy & Immunology | AA47: Yes | AB47: Yes | AC47: No | AD47: No | AE47: No | AF47: No | AG47: Multidisciplinary outpatient services in Voorhees, NJ. | AH47: http://maps.google.com/?q=443+Laurel+Oak+Road%2c+Voorhees%2c+NJ+08043 | AJ47: https://www.jeffersonhealth.org/locations/voorhees/department-directory | AK47: https://www.jeffersonhealth.org/locations/voorhees | AL47: 2026-03-30
A48: Voorhees Specialty Care | B48: Practice | D48: 333 Laurel Oak Road | E48: Voorhees | F48: NJ | G48: 08043 | I48: 39.84515 | J48: -74.98554 | K48: 844-542-2273 | O48: No | P48: 08:00 am - 05:00 pm | Q48: 08:00 am - 05:00 pm | R48: 08:00 am - 08:00 pm | S48: 08:00 am - 05:00 pm | T48: 08:00 am - 05:00 pm | U48: Closed | V48: Closed | W48: *Temporarily expanded hours subject to change. | X48: Nephrology; Infectious Diseases; Neurology; Neurosurgery; Vascular & Endovascular Surgery; Bariatric Surgery Program; Nutrition; Respiratory & Pulmonary Medicine; Medical & Surgical Weight Loss; General Surgery; Endocrinology, Diabetes, & Metabolic Diseases; Comprehensive Weight Management; Heart & Vascular; Cardiology; Heart Failure Care; Psychiatry & Human Behavior; Child & Adolescent Psychiatry | Y48: Lung Nodule | AA48: Yes | AB48: Yes | AC48: No | AD48: No | AE48: No | AF48: No | AG48: Specialty care services in Voorhees, NJ. | AH48: https://www.google.com/maps/place/Jefferson+Health+Voorhees+Primary+%26+Specialty+Care/@39.8446101,-74.9879302,17z/data=!4m9!1m2!2m1!1sjefferson+voorhees+specialty+care!3m5!1s0x89c6cd3cb5bbfc1b:0xc17ee1cb51873cc4!8m2!3d39.8450257!4d-74.986151!15sCiFqZWZmZXJzb24gdm9vcmhlZXMgc3BlY2lhbHR5IGNhcmWSAQZkb2N0b3I | AJ48: https://www.jeffersonhealth.org/locations/voorhees-specialty-care/department-directory | AK48: https://www.jeffersonhealth.org/locations/voorhees-specialty-care | AL48: 2026-08-10
A49: West Berlin Specialty Care | B49: Practice | D49: 301 Route 73 North | E49: West Berlin | F49: NJ | G49: 08091 | I49: 39.81045 | J49: -74.92615 | O49: No | P49: 07:30 am - 05:00 pm | Q49: 07:30 am - 05:00 pm | R49: 07:30 am - 05:00 pm | S49: 07:30 am - 06:00 pm | T49: 08:00 am - 04:30 pm | U49: Closed | V49: Closed | W49: *Temporarily expanded office hours subject to change. PHONE : Kindly check Department Directory Contacts | X49: Dermatology; Neuroscience; Plastic & Reconstructive Surgery; Comprehensive Weight Management | Y49: Weight Management | AA49: Yes | AB49: Yes | AC49: No | AD49: Yes | AE49: No | AF49: No | AG49: Plastic Surgery, Dermatology & Neuroscience services in West Berlin, NJ. | AH49: https://www.google.com/maps/place/Jefferson+Health+West+Berlin+Primary+%26+Specialty+Care/@39.8098126,-74.9302501,15z/data=!4m2!3m1!1s0x0:0xf5e9e7818c8f674e?sa=X&ved=2ahUKEwin64_Bo-vzAhWKUt8KHTXlAPYQ_BJ6BAhJEAU | AJ49: https://www.jeffersonhealth.org/locations/west-berlin-specialty-care/department-directory | AK49: https://www.jeffersonhealth.org/locations/west-berlin-specialty-care | AL49: 2026-01-24
A50: OB/GYN – West Deptford | B50: Practice | C50: Delivery Location: Jefferson Washington Township Hospital | D50: 165 Princeton Avenue | E50: West Deptford | F50: NJ | G50: 08096 | I50: 39.827797 | J50: -75.165783 | K50: 856-557-7530 | M50: 856-875-9556 | O50: No | P50: 08:00 am - 05:00 pm | Q50: 08:00 am - 06:30 pm | R50: 08:00 am - 05:00 pm | S50: 08:00 am - 05:00 pm | T50: 08:00 am - 04:30 pm | U50: Closed | V50: Closed | W50: *Temporarily expanded office hours subject to change. | X50: Obstetrics & Gynecology; Midwifery; Gynecology; Obstetrics & Maternity Care; Obstetrics | AA50: No | AB50: No | AC50: No | AD50: No | AE50: No | AF50: Yes | AG50: Jefferson OB/GYN – West Deptford (formerly West Deptford OBGYN & Midwifery Care) provides OB/GYN and midwifery services in West Deptford, NJ. | AH50: https://www.google.com/maps/place/Jefferson+Health+West+Deptford+Obstetrics+%26+Gynecology/@39.8277968,-75.1679718,17z/data=!3m1!4b1!4m5!3m4!1s0x89c6daa54b896cd3:0xacc1e4a1a62127d4!8m2!3d39.8278052!4d-75.165763 | AK50: https://www.jeffersonhealth.org/locations/obgyn-deptford | AL50: 2026-03-12
A51: 26 East Red Bank Avenue | B51: Practice | D51: 26 East Red Bank Avenue | E51: Woodbury | F51: NJ | G51: 08096 | I51: 39.843573 | J51: -75.14829 | K51: 800-533-3669 | O51: No | X51: Gastroenterology & Hepatology; Gastroesophageal Care | AA51: No | AB51: No | AC51: No | AD51: No | AE51: No | AF51: Yes | AG51: Jefferson Health's 26 East Red Bank Avenue location offers gastroenterology & hepatology services. | AH51: https://goo.gl/maps/trCsQYk8oHWHszyX7 | AK51: https://www.jeffersonhealth.org/locations/26-east-red-bank-avenue | AL51: 2026-01-24
A52: Woodbury Primary & Specialty Care | B52: Practice | D52: 159 South Broad Street | E52: Woodbury | F52: NJ | G52: 08096 | I52: 39.83649 | J52: -75.15159 | K52: 844-542-2273 | M52: 856-384-0218 | O52: No | P52: 08:00 am - 08:00 pm | Q52: 08:00 am - 07:00 pm | R52: 08:00 am - 07:00 pm | S52: 08:00 am - 07:00 pm | T52: 08:00 am - 05:00 pm | U52: Closed | V52: Closed | W52: *Temporarily expanded office hours subject to change. | X52: Primary Care; Nutrition; General Surgery; Family & Community Medicine; Psychiatry & Human Behavior | AA52: No | AB52: No | AC52: No | AD52: No | AE52: No | AF52: No | AG52: Primary and specialty care services in Woodbury, NJ. | AH52: https://www.google.com/maps/place/Jefferson+Health+Woodbury+Primary+%26+Specialty+Care/@39.8357202,-75.1552786,15z/data=!4m5!3m4!1s0x0:0xd85a0578041f552a!8m2!3d39.8356948!4d-75.1552154 | AK52: https://www.jeffersonhealth.org/locations/woodbury-primary-specialty-care | AL52: 2026-07-29
A53: Sidney Kimmel Comprehensive Cancer Center — Cherry Hill | B53: Outpatient Medical Center | D53: 2211 Chapel Avenue | E53: Cherry Hill | F53: NJ | G53: 08002 | I53: 39.928668 | J53: -75.015803 | K53: 856-922-5180 | M53: 215-521-6194 | O53: No | P53: 08:00 am - 05:00 pm | Q53: 08:00 am - 05:00 pm | R53: 08:00 am - 05:00 pm | S53: 08:00 am - 05:00 pm | T53: 08:00 am - 05:00 pm | U53: Closed | V53: Closed | X53: Medical Oncology; Cancer | Y53: Cancer; Throat Cancer; Ovarian Cancer; Parathyroid Cancer | Z53: Infusion Therapy | AA53: Yes | AB53: Yes | AC53: No | AD53: Yes | AE53: No | AF53: No | AG53: Access nationally ranked cancer care from our renowned specialists at Sidney Kimmel Comprehensive Cancer Center in Cherry Hill, NJ. | AH53: https://www.google.com/maps/place/Jefferson+Health+Cherry+Hill+General+Surgery+%26+Specialty+Care/@39.9308071,-75.0422175,15z/data=!4m9!1m2!2m1!1scherry+hill+MOB+specialty+care!3m5!1s0x89c6cb2f6c389ccd:0x86153d7440a00fae!8m2!3d39.927916!4d-75.015734!15sCh5jaGVycnkgaGlsbCBNT0Igc3BlY2lhbHR5IGNhcmWSAQ9zdXJnaWNhbF9jZW50ZXI | AJ53: https://www.jeffersonhealth.org/locations/sidney-kimmel-cancer-center-cherry-hill/department-directory | AK53: https://www.jeffersonhealth.org/locations/sidney-kimmel-cancer-center-cherry-hill | AL53: 2026-03-25
A54: AMS Cardiology - Abington | B54: Practice | D54: Levy Medical Plaza | E54: Abington | F54: PA | G54: 19001 | H54: Montgomery County | I54: 40.118434 | J54: -75.118859 | K54: 215-517-1000 | M54: 215-517-1049 | O54: No | X54: Cardiology; Angioplasty; Cardiac Electrophysiology; Cardiovascular Oncology; Cardiothoracic Imaging; Heart & Vascular; Interventional Cardiology; Nuclear Medicine & Molecular Imaging; Structural Heart Program | AA54: No | AB54: No | AE54: No | AF54: No | AG54: AMS Cardiology in Abington offers cardiology services to its patients. | AH54: https://www.google.com/maps/place/1235+Old+York+Rd,+Abington,+PA+19001/@40.118438,-75.1210479,17z/data=!3m1!4b1!4m5!3m4!1s0x89c6b0575a253b6b:0xe904487d71e64afc!8m2!3d40.1184339!4d-75.1188592 | AK54: https://www.jeffersonhealth.org/locations/ams-cardiology-abington | AL54: 2026-01-24
A55: Abington Adult Medical Associates | B55: Practice | D55: 1235 Old York Road, Suite 214 | E55: Abington | F55: PA | G55: 19001 | H55: Montgomery County | I55: 40.11859 | J55: -75.11814 | K55: 215-481-4811 | M55: 215-576-1787 | O55: No | P55: 08:30 am - 05:00 pm | Q55: 08:30 am - 05:00 pm | R55: 08:30 am - 05:00 pm | S55: 08:30 am - 05:00 pm | T55: 08:30 am - 04:30 pm | U55: Closed | V55: Closed | W55: After hours, please visit one of our Jefferson Urgent Care Centers. | X55: Primary Care | AA55: No | AB55: No | AC55: No | AD55: No | AE55: No | AF55: Yes | AG55: Abington Adult Medical Associates is committed to being your most trusted healthcare partner. We are dedicated to improving the quality of life for all by fostering healing, easing suffering and promoting wellness in a culture of safety, learning and respect. | AH55: https://goo.gl/maps/LXfTdm2iA8tyRpQCA | AK55: https://www.jeffersonhealth.org/locations/abington-adult-medical-associates | AL55: 2026-01-24
A56: Abington Plaza Medical Associates – Abington | B56: Practice | D56: 1235 Old York Road, Suite 113 | E56: Abington | F56: PA | G56: 19001 | H56: Montgomery County | I56: 40.11859 | J56: -75.1178 | K56: 215-491-5057 | M56: 215-491-5607 | O56: No | P56: 08:00 am - 05:00 pm | Q56: 08:00 am - 05:00 pm | R56: 08:00 am - 05:00 pm | S56: 08:00 am - 05:00 pm | T56: 08:00 am - 05:00 pm | U56: Closed | V56: Closed | W56: Phones are available from 8 a.m. to 5 p.m daily. After hours, please visit one of our Jefferson Urgent Care Centers . | X56: Internal Medicine; Primary Care | AA56: No | AB56: No | AC56: No | AD56: No | AE56: No | AF56: Yes | AG56: Abington Plaza Medical Associates is committed to being your most trusted healthcare partner. We are dedicated to improving the quality of life for all by fostering healing, easing suffering and promoting wellness in a culture of safety, learning and respect. | AH56: https://goo.gl/maps/FenhiVLq423MtuqE8 | AK56: https://www.jeffersonhealth.org/locations/abington-plaza-medical-associates | AL56: 2026-01-24
A57: Abington Primary Care Medicine | B57: Practice | D57: 1235 Old York Road | E57: Abington | F57: PA | G57: 19001 | H57: Montgomery County | I57: 40.11742 | J57: -75.119202 | K57: 215-576-1776 | M57: 215-576-1784 | O57: No | P57: 08:00 am - 07:30 pm | Q57: 08:00 am - 07:30 pm | R57: 07:30 am - 05:15 pm | S57: 07:00 am - 06:00 pm | T57: 07:00 am - 04:30 pm | U57: Closed | V57: Closed | W57: Phone Hours The practice is available for phone calls during the following hours: 8 a.m. to 5 p.m. Monday - Friday After hours, please visit one of our Jefferson Urgent Care Centers . | X57: Internal Medicine; Primary Care | AA57: No | AB57: No | AC57: No | AD57: No | AE57: No | AF57: Yes | AG57: Jefferson Health's Abington Primary Care Medicine practice offers internal medicine and primary care services. | AH57: https://goo.gl/maps/2hnPAiQu1Lrr9fAs6 | AK57: https://www.jeffersonhealth.org/locations/abington-primary-care-medicine | AL57: 2026-09-09
A58: Abington Pulmonary & Critical Care Associates | B58: Practice | D58: 1235 Old York Road, Suite 121 | E58: Abington | F58: PA | G58: 19001 | H58: Montgomery County | I58: 40.118243 | J58: -75.119089 | K58: 215-517-1200 | M58: 215-517-1219 | O58: No | P58: 08:00 am - 05:00 pm | Q58: 08:00 am - 05:00 pm | R58: 08:00 am - 05:00 pm | S58: 08:00 am - 05:00 pm | T58: 08:00 am - 04:30 pm | U58: Closed | V58: Closed | X58: Pulmonary Vascular Disorders; Critical Care Medicine; Respiratory & Pulmonary Medicine | AA58: No | AB58: No | AC58: No | AD58: No | AE58: No | AF58: No | AG58: Our staff consists of highly qualified professionals who work together as a team to bring you the highest quality of care with compassion, confidentiality and respect. We welcome all questions and suggestions about your care. | AH58: https://goo.gl/maps/FgVKqwivoMyn6Kzm6 | AK58: https://www.jeffersonhealth.org/locations/abington-pulmonary-critical-care-associates | AL58: 2026-06-16
A59: Abington at Price 504 – OB/GYN | B59: Practice | C59: Delivery Location: Jefferson Abington Hospital | D59: 1245 Highland Ave | E59: Abington | F59: PA | G59: 19001 | H59: Montgomery County | I59: 40.119779 | J59: -75.122081 | K59: 215-657-8430 | M59: 215-657-8439 | O59: No | P59: 08:00 am - 03:30 pm | Q59: Closed | R59: 08:00 am - 03:30 pm | S59: 08:00 am - 03:30 pm | T59: 08:00 am - 03:30 pm | U59: Closed | V59: Closed | X59: Obstetrics & Maternity Care; Gynecology; Obstetrics; Obstetrics & Gynecology; Pediatric & Adolescent Gynecology; Women's Primary Care; Midwifery; Menopause Care | AA59: No | AB59: No | AC59: No | AD59: No | AE59: No | AF59: No | AG59: Jefferson OB/GYN – Abington at Price 504 (formerly Abington OB/GYN Associates - Abington) provides OB/GYN and midwifery services in Abington, PA. | AH59: https://www.google.com/maps/place/PRICE+MEDICAL+BUILDING/@40.1197788,-75.122081,18z/data=!3m1!5s0x89c6b005884f4959:0xe93ee610d320d33a!4m12!1m6!3m5!1s0x89c6b1ed96bf8bcb:0x1b1ad9e1ab7e366d!2sPRICE+MEDICAL+BUILDING!8m2!3d40.1197009!4d-75.1212012!3m4!1s0x89c6b1ed96bf8bcb:0x1b1ad9e1ab7e366d!8m2!3d40.1197009!4d-75.1212012?hl=en-US | AK59: https://www.jeffersonhealth.org/locations/obgyn-abington-price-504 | AL59: 2026-01-24
A60: Abington at Price G01 – OB/GYN | B60: Practice | C60: Delivery Location: Jefferson Abington Hospital | D60: 1245 Highland Ave | E60: Abington | F60: PA | G60: 19001 | H60: Montgomery County | I60: 40.119128 | J60: -75.120732 | K60: 215-443-0660 | M60: 215-517-1059 | O60: No | X60: Obstetrics & Gynecology; Obstetrics; Obstetrics & Maternity Care; Gynecology; Women's Primary Care; Pediatric & Adolescent Gynecology; Menopause Care | AA60: No | AB60: No | AC60: No | AD60: No | AE60: No | AF60: No | AG60: Jefferson OB/GYN – Abington at Price G01 (formerly Womencare Obstetrics & Gynecology - Abington) provides OB/GYN and midwifery services in Abington, PA. | AH60: https://goo.gl/maps/9uK532CRAaqJGFRC9 | AK60: https://www.jeffersonhealth.org/locations/obgyn-abington-price-g01 | AL60: 2026-01-24
A61: Abington at Toll – OB/GYN | B61: Practice | C61: Delivery Location: Jefferson Abington Hospital | D61: 1200 Old York Road | E61: Abington | F61: PA | G61: 19001 | H61: Montgomery County | I61: 40.118181 | J61: -75.120408 | K61: 215-481-6784 | M61: 215-481-4787 | O61: No | P61: 08:00 am - 04:30 pm | Q61: 08:00 am - 07:00 pm | R61: 08:00 am - 04:30 pm | S61: 08:00 am - 04:30 pm | T61: 08:00 am - 04:00 pm | U61: Closed | V61: Closed | X61: Obstetrics & Gynecology; Obstetrics & Maternity Care; Obstetrics; Gynecology; Women's Primary Care; Pediatric & Adolescent Gynecology; Midwifery | AA61: No | AB61: No | AC61: No | AD61: No | AE61: No | AF61: No | AG61: Jefferson OB/GYN – Abington at Toll (formerly OB/GYN Center) provides OB/GYN and midwifery services in Abington, PA. | AH61: https://goo.gl/maps/YceE6gGsYEEkmFa19 | AK61: https://www.jeffersonhealth.org/locations/obgyn-abington-toll | AL61: 2026-01-24
A62: Associates in Infectious Diseases | B62: Practice | D62: 1235 Old York Road, Suite 220 | E62: Abington | F62: PA | G62: 19001 | H62: Montgomery County | I62: 40.118434 | J62: -75.118859 | K62: 215-481-6350 | M62: 215-481-6359 | O62: No | P62: 09:00 am - 12:00 pm, 01:00 pm - 04:00 pm | Q62: 09:00 am - 12:00 pm, 01:00 pm - 04:00 pm | R62: 09:00 am - 12:00 pm, 01:00 pm - 04:00 pm | S62: 09:00 am - 12:00 pm, 01:00 pm - 04:00 pm | T62: 09:00 am - 12:00 pm, 01:00 pm - 04:00 pm | U62: Closed | V62: Closed | W62: Lunch (Closed): 12 pm to 1 pm | X62: Infectious Diseases | AA62: No | AB62: No | AC62: No | AD62: No | AE62: No | AF62: No | AG62: Jefferson Health's Associates in Infectious Diseases practice offers infectious disease services to its patients. | AH62: https://www.google.com/maps/place/1235+Old+York+Rd,+Abington,+PA+19001/@40.1184339,-75.1188592,17z/data=!3m1!4b1!4m5!3m4!1s0x89c6b0575a253b6b:0xe904487d71e64afc!8m2!3d40.1184339!4d-75.1188592 | AK62: https://www.jeffersonhealth.org/locations/associates-in-infectious-diseases | AL62: 2026-01-24
A63: Family Practice of Willow Grove | B63: Practice | D63: 1235 Old York Road, Suite 210 | E63: Abington | F63: PA | G63: 19001 | H63: Montgomery County | I63: 40.11836 | J63: -75.119255 | K63: 215-659-3220 | M63: 215-659-8967 | O63: No | P63: 08:00 am - 05:00 pm | Q63: 08:00 am - 07:00 pm | R63: 08:00 am - 07:00 pm | S63: 08:00 am - 07:00 pm | T63: 08:00 am - 05:00 pm | U63: Closed | V63: Closed | W63: Saturdays: Occasional After hours, please visit one of our Jefferson Urgent Care locations . | X63: Internal Medicine; Family & Community Medicine | AA63: No | AB63: No | AC63: No | AD63: No | AE63: No | AF63: Yes | AG63: Family Practice of Willow Grove is a family and community and internal medicine office in Willow Grove, PA. | AH63: https://goo.gl/maps/bRf3XN1UmtP7R4Vz6 | AK63: https://www.jeffersonhealth.org/locations/family-practice-of-willow-grove | AL63: 2026-01-24
A64: Gastroenterology Suite - Jefferson Abington Hospital | B64: Practice | D64: Levy Medical Plaza, 1235 Old York Road, Suite G-23 | E64: Abington | F64: PA | G64: 19001 | I64: 40.118346 | J64: -75.118955 | K64: 215-517-1060 | O64: No | X64: Gastrointestinal Motility | AA64: No | AB64: No | AE64: No | AF64: No | AG64: Learn more about the Gastrointestinal Motility Program offered at the Gastroenterology Suite at Jefferson Abington Hospital in Abington, PA. | AH64: https://www.google.com/maps/place/1235+Old+York+Rd,+Abington,+PA+19001/@40.118438,-75.1210479,17z/data=!3m1!4b1!4m5!3m4!1s0x89c6b0575a253b6b:0xe904487d71e64afc!8m2!3d40.1184339!4d-75.1188592 | AK64: https://www.jeffersonhealth.org/locations/gastroenterology-suite---jefferson-abington-hospital | AL64: 2026-01-24
A65: Heart and Vascular Institute – Porter Institute | B65: Practice | C65: Bruce & Robbi Toll Heart and Vascular Institute – Porter Institute | D65: Jefferson Abington Hospital, 1200 Old York Road, 5 Toll | E65: Abington | F65: PA | G65: 19001 | H65: Montgomery County | I65: 40.11925 | J65: -75.11934 | K65: 215-481-4200 | M65: 215-881-9587 | O65: No | P65: 08:30 am - 03:30 pm | Q65: 08:30 am - 03:30 pm | R65: 08:30 am - 03:30 pm | S65: 08:30 am - 03:30 pm | T65: 08:30 am - 03:30 pm | U65: Closed | V65: Closed | X65: Cardiology; Advanced Heart Failure & Transplant; Aortic Care; Cardiothoracic Surgery; Heart & Vascular; Heart Failure Care; Mechanical Circulatory Support; Structural Heart Program; Surgery; Transplant Institute | AA65: No | AB65: No | AC65: No | AD65: No | AE65: No | AF65: No | AG65: Bruce & Robbi Toll Heart and Vascular Institute – Porter Institute at Jefferson Abington Hospital offers expert cardiology and cardiovascular care in Abington, PA. | AH65: https://www.google.com/maps/place/1200+Old+York+Rd,+Abington,+PA+19001/@40.119084,-75.120285,15z/data=!4m5!3m4!1s0x89c6b1435cd80bcd:0x5a813aeb823767f6!8m2!3d40.1179838!4d-75.1204083?hl=en-US | AK65: https://www.jeffersonhealth.org/locations/abington-cardiac-surgical-specialists | AL65: 2026-04-22
A66: Jefferson Abington Hospital | B66: Hospital; Imaging | C66: Hospital | D66: 1200 Old York Road | E66: Abington | F66: PA | G66: 19001 | H66: Montgomery County | I66: 40.119069 | J66: -75.119906 | K66: 215-481-2000 | O66: Yes | P66: Open 24 hours | Q66: Open 24 hours | R66: Open 24 hours | S66: Open 24 hours | T66: Open 24 hours | U66: Open 24 hours | V66: Open 24 hours | X66: Hospitalist; Structural Heart Program; ElderMed; Hospital Medicine; Transplant Institute; Neonatology; Drug Addiction & Recovery Services; Pathology, Anatomy, & Cell Biology; Palliative Care; Stroke Rehabilitation; Hospice & Palliative Care; Obstetrics & Maternity Care; Anesthesiology; Cardiothoracic Surgery; Travel Medicine; Mechanical Circulatory Support; Gynecology; Endovascular Neurosurgery; Fatty Liver Care; Psychiatry & Human Behavior; Medical & Surgical Weight Loss; Emergency Medicine; Sleep Disorders Center; Heart Home Care; Internal Medicine; Advanced Heart Failure & Transplant; Bariatric Surgery Program; General Surgery; Voice & Swallowing Care; Stroke Care; Pharmacy; Minimally Invasive & Robotic Surgery; COVID-19 Program; Gynecologic Oncology; Respiratory & Pulmonary Medicine; Women's Primary Care; Neurology; Surgery; Rothman Institute; Center For Genetic & Metabolic Liver Disease; Endoscopic Bariatric Care; Hematology Oncology; Urologic Oncology; Obstetrics & Gynecology; Primary Care; Pediatric Neonatology; Sleep Medicine; Infectious Diseases; Pastoral Care; Comprehensive Weight Management; Heart Failure Care; Women's Imaging; Pulmonology; Home Care; Heart & Vascular; Cardiovascular Oncology; Hematology; Amyloidosis Care; Obstetrics; Pulmonary Critical Care; Urology; Ultrasound; Women's Heart Health; JeffSTAT; Geriatric Medicine; Neuroscience; Maternal & Fetal Medicine; Vascular & Endovascular Surgery; Balance & Hearing; JeffConnect; Occupational Health; Aortic Care; Behavioral Medicine; Vascular Medicine; Maternal-Child Home Care; Cardiology; Pharmacology; Thoracic & Esophageal Surgery; Pediatrics; Lung Cancer, Screening, and Nodules; Traumatic Injury Care; Lower Extremity Orthopedics; Spine Care; Family Planning; Outpatient Imaging; Imaging & Radiology; Headache Medicine; Headaches; Neurosurgery; Bariatric Surgery | Y66: Stroke | Z66: Cardiac Catheterization | AA66: Yes | AB66: Yes | AC66: No | AD66: Yes | AE66: No | AF66: No | AG66: Jefferson Abington Hospital improves lives thru award-winning care in Greater Philadelphia including emergency trauma medicine & advanced clinical specialties. | AH66: https://www.google.com/maps/place/Jefferson+Abington+Hospital/@40.1190689,-75.1199064,15z/data=!3m1!5s0x89c6b005884f4959:0xe93ee610d320d33a!4m5!3m4!1s0x89c6b050929d6641:0x4408eaeb5ba81dcc!8m2!3d40.1190689!4d-75.1199064 | AI66: https://www.jeffersonhealth.org/locations/abington-hospital/getting-here | AJ66: https://www.jeffersonhealth.org/locations/abington-hospital/department-directory | AK66: https://www.jeffersonhealth.org/locations/abington-hospital | AL66: 2026-09-03
A67: Jefferson Dermatology – Abington | B67: Practice | D67: 1400 Old York Road | E67: Abington | F67: PA | G67: 19001 | I67: 40.121925 | J67: -75.117683 | K67: 215-481-3309 | M67: 215-521-6438 | O67: No | X67: Dermatology | AA67: No | AB67: No | AC67: No | AD67: No | AE67: No | AF67: No | AG67: Jefferson Dermatology – Abington in Abington, PA offers dermatology services to its patients. | AH67: https://www.google.com/maps/place/1400+Old+York+Rd+Ste+A,+Abington,+PA+19001/@40.1213068,-75.1183237,17z/data=!3m1!4b1!4m6!3m5!1s0x89c6b0508bcff749:0x8f4be5c731b29097!8m2!3d40.1213068!4d-75.1183237!16s%2Fg%2F11x20lr757?hl=en&entry=ttu&g_ep=EgoyMDI2MDgzMS4wIKXMDSoASAFQAw%3D%3D | AK67: https://www.jeffersonhealth.org/locations/dermatology-abington | AL67: 2026-09-03
A68: Jefferson Otolaryngology – Abington | B68: Practice | D68: 1235 Old York Road | E68: Abington | F68: PA | G68: 19001 | H68: Montgomery County | I68: 40.121034 | J68: -75.118007 | K68: 215-886-1482 | M68: 215-886-1492 | O68: No | P68: 08:00 am - 05:00 pm | Q68: 08:00 am - 05:00 pm | R68: 08:00 am - 05:00 pm | S68: 08:00 am - 05:00 pm | T68: 08:00 am - 05:00 pm | U68: Closed | V68: Closed | X68: Balance & Hearing; Head & Neck Surgery; Otolaryngology; Thyroid & Parathyroid Care | AA68: No | AB68: No | AC68: No | AD68: No | AE68: No | AF68: No | AG68: Jefferson Otolaryngology – Abington offers various clinical specialties including otolaryngology services. | AK68: https://www.jeffersonhealth.org/locations/jefferson-otolaryngology-abington | AL68: 2026-01-24
A69: Nemours Children’s Health – Abington | B69: Practice | D69: 1245 Highland Ave | E69: Abington | F69: PA | G69: 19001 | I69: 40.119738 | J69: -75.121677 | K69: 1-800-416-4441 | M69: 215-449-7145 | O69: No | X69: Pediatrics; Pediatric Cardiology; Pediatric Endocrinology; Pediatric Gastroenterology; Nephrology; Pediatric Neurology; Nutrition; Orthopedics; Pediatric Pulmonology | Z69: Echocardiogram; Electrocardiogram | AA69: Yes | AB69: No | AC69: No | AD69: No | AE69: No | AF69: No | AG69: Nemours Children’s Health in Abington offers world-class pediatric care, close to home. | AH69: https://www.google.com/maps/place/Nemours+Children's+Health,+Abington/@40.1199237,-75.1208825,15z/data=!4m2!3m1!1s0x0:0x22f44d643d50ec82?sa=X&ved=2ahUKEwi_vbzUnrj7AhWHFlkFHegNCa0Q_BJ6BAhsEAg | AK69: https://www.jeffersonhealth.org/locations/nemours-childrens-health-abington | AL69: 2026-01-24
A70: Neurosurgical Associates of Abington | B70: Practice | D70: Jefferson Abington Hospital - 1 Widener, 1200 Old York Road | E70: Abington | F70: PA | G70: 19001 | H70: Montgomery County | I70: 40.119069 | J70: -75.119906 | K70: 215-481-3255 | M70: 215-481-3781 | O70: No | P70: 08:00 am - 04:00 pm | Q70: 08:00 am - 04:00 pm | R70: 08:00 am - 04:00 pm | S70: 08:00 am - 04:00 pm | T70: 08:00 am - 04:00 pm | U70: Closed | V70: Closed | X70: Neuroscience; Neurosurgery | AA70: Yes | AB70: No | AC70: No | AD70: No | AE70: No | AF70: No | AG70: Neurosurgical Associates of Abington consists of board-certified neurosurgeons and highly qualified clinical and support professionals working together to provide the highest quality of care. | AH70: https://goo.gl/maps/5sektpTU7K49XS7t7 | AK70: https://www.jeffersonhealth.org/locations/neurosurgical-associates-of-abington | AL70: 2026-04-15
A71: Neurovascular Associates of Abington – Abington | B71: Practice | D71: Jefferson Abington Hospital - 1 Widener, 1200 Old York Road | E71: Abington | F71: PA | G71: 19001 | H71: Montgomery County | I71: 40.118776 | J71: -75.120542 | K71: 215-481-3145 | M71: 215-481-5971 | O71: No | P71: 08:00 am - 04:00 pm | Q71: 08:00 am - 04:00 pm | R71: 08:00 am - 04:00 pm | S71: 08:00 am - 04:00 pm | T71: 08:00 am - 04:00 pm | U71: Closed | V71: Closed | X71: Neuroscience; Stroke Care | Y71: Stroke | AA71: Yes | AB71: No | AC71: No | AD71: No | AE71: No | AF71: Yes | AG71: Our staff consists of board-certified physicians with fellowship training in Stroke, in Neurocritical Care and in Endovascular Surgical Neuroradiology, and highly qualified clinical and support professionals working together to provide the highest quality of care. | AH71: https://goo.gl/maps/rqf4DUNhGgPJiwAc8 | AK71: https://www.jeffersonhealth.org/locations/neurovascular-associates-of-abington | AL71: 2026-07-27
A72: Horsham Family Practice | B72: Practice | D72: 1116 Horsham Road, Suite 10 | E72: Ambler | F72: PA | G72: 19002 | H72: Montgomery County | I72: 40.21102 | J72: -75.18196 | K72: 215-643-8500 | M72: 215-643-6999 | O72: No | P72: 08:00 am - 04:00 pm | Q72: 08:00 am - 04:00 pm | R72: 01:00 pm - 09:00 pm | S72: 08:00 am - 12:00 pm | T72: 08:00 am - 04:00 pm | U72: 08:00 am - 12:00 pm | V72: Closed | W72: Saturdays (once a month) After hours, please visit one of our Jefferson Urgent Care Centers . | X72: Family & Community Medicine | AA72: No | AB72: No | AC72: No | AD72: No | AE72: No | AG72: Horsham Family Practice in Horsham, PA offers family and community medicine services to its patients. | AH72: https://goo.gl/maps/6huBRMyaaH5r9sUj6 | AK72: https://www.jeffersonhealth.org/locations/horsham-family-practice | AL72: 2026-01-24
A73: Jefferson Moss-Magee Rehabilitation – Ambler | B73: Outpatient Rehabilitation | D73: 250 North Bethlehem Pike | E73: Ambler | F73: PA | G73: 19002 | H73: Montgomery County | I73: 40.166883 | J73: -75.221143 | K73: 215-481-2160 | L73: Main Office: 215-540-0763 | M73: 215-540-0923 | O73: No | X73: Rehabilitation Medicine; Outpatient Rehabilitation; Physical Therapy | Y73: Arthritis; Chronic Pain; Multiple Sclerosis; Balance & Dizziness Disorders; Rheumatoid Arthritis | Z73: Physical Therapy | AA73: No | AB73: No | AC73: No | AD73: No | AE73: No | AF73: No | AG73: Our expert team of rehabilitation specialists at Jefferson Moss-Magee Rehabilitation – Ambler provides physical therapy, along with aquatic therapy, for a wide range of simple and complex conditions and injuries. | AH73: https://www.google.com/maps/place/The+Becoming+Center/@40.1668871,-75.2237179,17z/data=!3m1!4b1!4m6!3m5!1s0x89c6bb34b680ff51:0xaf32243ef4ce1498!8m2!3d40.166883!4d-75.221143!16s%2Fg%2F1tg5_lh0?entry=ttu | AK73: https://www.jeffersonhealth.org/locations/moss-magee-rehabilitation-ambler | AL73: 2026-03-25
A74: Einstein Physicians Shannondell | B74: Practice | D74: 20000 Shannondell Drive | E74: Audubon | F74: PA | G74: 19403 | H74: Montgomery County | I74: 40.131841 | J74: -75.409616 | K74: 484-392-4045 | O74: No | P74: Closed | Q74: 11:00 am - 03:00 pm | R74: Closed | S74: 08:00 am - 05:00 pm | T74: Closed | U74: Closed | V74: Closed | W74: * Dr. Burkholder is at Trappe Family Practice on Wednesday and Friday. Call Trappe Family Practice at 484-622-6300 to schedule an appointment. | X74: Primary Care; Family & Community Medicine; Palliative Care | AA74: No | AB74: No | AC74: No | AD74: No | AE74: Yes | AF74: No | AG74: Einstein Physicians Shannondell, PA that offers Primary Care specialty services. | AH74: https://www.google.com/maps/place/20000+Shannondell+Dr,+Audubon,+PA+19403/@40.1318406,-75.4096165,17z/data=!4m5!3m4!1s0x89c696eacb03bbdb:0x388d6b88e000bc74!8m2!3d40.1318406!4d-75.4096165 | AK74: https://www.jeffersonhealth.org/locations/einstein-physicians-shannondell | AL74: 2026-09-01
A75: Endoscopy Center at Bala | B75: Practice | D75: 130 Presidential Boulevard | E75: Bala Cynwyd | F75: PA | G75: 19004 | H75: Montgomery County | I75: 40.011392 | J75: -75.216411 | K75: 267-443-2040 | O75: No | P75: 06:30 am - 04:00 pm | Q75: 06:30 am - 04:00 pm | R75: 06:30 am - 04:00 pm | S75: 06:30 am - 04:00 pm | T75: 06:30 am - 04:00 pm | U75: Closed | V75: Closed | X75: Gastroenterology & Hepatology | AA75: No | AB75: No | AC75: No | AD75: No | AE75: No | AF75: No | AG75: Jefferson Endoscopy Center at Bala makes it easier and more convenient for patients to obtain necessary screening, diagnostic and therapeutic studies. | AH75: http://maps.google.com/?q=130+Presidential+Boulevard%2c+Bala+Cynwyd%2c+PA+19004 | AI75: https://www.jeffersonhealth.org/locations/endoscopy-center-at-bala/directions-and-parking | AK75: https://www.jeffersonhealth.org/locations/endoscopy-center-at-bala | AL75: 2026-01-24
A76: Jefferson Health – Bala Cynwyd | B76: Outpatient Medical Center | D76: 225 East City Avenue, Suite 10 | E76: Bala Cynwyd | F76: PA | G76: 19004 | I76: 40.005623 | J76: -75.219343 | K76: 1-800-JEFF-NOW | O76: No | X76: Nephrology; Inflammatory Bowel Disease; Lupus Care; Cardiac Electrophysiology; Gastroenterology & Hepatology; Scleroderma; Internal Medicine; Comprehensive Weight Management; Cardiology; Rheumatology; Gastrointestinal Motility; Gastroesophageal Care; Bariatric Surgery Program; Colorectal Surgery; Heart & Vascular; Heart Failure Care | Z76: Bariatric Surgery | AA76: Yes | AB76: Yes | AC76: No | AD76: No | AE76: No | AF76: No | AG76: Jefferson Health – Bala Cynwyd is a multidisciplinary practice in Philadelphia, PA, located at 225 East City Avenue. | AH76: http://maps.google.com/?q=225+East+City+Avenue%2c+Bala+Cynwyd%2c+PA+19004 | AI76: https://www.jeffersonhealth.org/locations/bala-cynwyd/directions-and-parking | AJ76: https://www.jeffersonhealth.org/locations/bala-cynwyd/department-directory | AK76: https://www.jeffersonhealth.org/locations/bala-cynwyd | AL76: 2026-08-17
A77: Heart and Vascular Institute – Bensalem | B77: Practice | C77: Bruce & Robbi Toll Heart and Vascular Institute | D77: 2685 Knights Road | E77: Bensalem | F77: PA | G77: 19020 | H77: Bucks County | I77: 40.100793 | J77: -74.954408 | K77: 215-750-6566 | M77: 215-750-7288 | O77: No | X77: Cardiology; Heart & Vascular | AA77: No | AB77: No | AE77: No | AF77: Yes | AG77: Bruce & Robbi Toll Heart and Vascular Institute – Bensalem offers expert cardiology and cardiovascular care in Bensalem, PA. | AK77: https://www.jeffersonhealth.org/locations/cardiology-associates-at-oxford-valley-bensalem | AL77: 2026-03-10
A78: Jefferson Radiation Oncology Associates | B78: Practice | D78: 3300 Tillman Drive | E78: Bensalem | F78: PA | G78: 19020 | H78: Bucks County | I78: 40.112667 | J78: -74.962121 | K78: 215-244-7407 | M78: 215-639-7515 | O78: No | X78: Radiation Oncology | AA78: No | AB78: No | AC78: No | AD78: No | AE78: No | AG78: Jefferson Radiation Oncology Associates is a radiation oncology practice in Northeast Philadelphia. | AH78: https://www.google.com/maps/place/3300+Tillman+Dr,+Bensalem,+PA+19020/data=!4m2!3m1!1s0x89c14d35f6758b8b:0x375b7e7fc368db13?sa=X&ved=2ahUKEwjhrbTwgNP5AhUFM1kFHTctCOgQ8gF6BAgCEAE | AK78: https://www.jeffersonhealth.org/locations/jefferson-radiation-oncology-associates | AL78: 2026-01-24
A79: Neshaminy Medical | B79: Practice | D79: 2426 Bristol Road | E79: Bensalem | F79: PA | G79: 19020 | H79: Montgomery County | I79: 40.131295 | J79: -74.925054 | K79: 215-757-1533 | M79: 215-757-7297 | O79: No | P79: 08:00 am - 08:00 pm | Q79: 08:00 am - 08:00 pm | R79: 08:00 am - 05:00 pm | S79: 08:00 am - 05:00 pm | T79: 08:00 am - 01:00 pm | U79: Closed | V79: Closed | X79: Family & Community Medicine; Primary Care | AA79: No | AB79: No | AC79: No | AD79: No | AE79: No | AF79: Yes | AG79: Neshaminy Medical is a primary care and family medicine practice in Northeast Philadelphia. | AH79: https://www.google.com/maps/place/Aria+Neshaminy+Medical/@40.1312124,-74.9250676,15z/data=!4m2!3m1!1s0x0:0x8d0d374a5d4334e1?sa=X&ved=2ahUKEwjhnoywtMv3AhVvkYkEHa0jDogQ_BJ6BAhNEAU | AK79: https://www.jeffersonhealth.org/locations/neshaminy-medical | AL79: 2026-01-24
A80: Rothman Orthopaedic Specialty Hospital at Bensalem | B80: Hospital; Outpatient Medical Center | D80: 3300 Tillman Drive | E80: Bensalem | F80: PA | G80: 19020 | H80: Bucks County | I80: 40.113391 | J80: -74.962931 | K80: 215-244-7400 | M80: 215-244-7480 | O80: Yes | P80: Open 24 hours | Q80: Open 24 hours | R80: Open 24 hours | S80: Open 24 hours | T80: Open 24 hours | U80: Open 24 hours | V80: Open 24 hours | X80: Rothman Institute; Hand Surgery; Head & Neck Surgery; Hip & Knee Orthopedic Surgery; Occupational Therapy; Orthopedic Injury Rehabilitation; Orthopedic Oncology; Orthopedic Trauma; Orthopedics; Pain Management; Physical Medicine & Rehabilitation; Physical Therapy; Spinal Cord Injury Medicine; Spinal Cord Injury Rehabilitation; Spine Care; Spine Surgery; Sports Medicine; Lower Extremity Orthopedics | Y80: Back & Neck Pain; Back & Spine Conditions; Elbow Problems & Pain; Foot Problems & Pain; Tendonitis; Tennis Elbow; Whiplash; Fractures; Hand Problems & Pain; Herniated Disc; Hip Pain; Rib Fracture; Rotator Cuff Injury; Shoulder Pain; Spinal Cord Injury; Sports Injury; Torn Meniscus | AA80: Yes | AB80: Yes | AC80: Yes | AD80: No | AE80: No | AF80: No | AG80: Rothman Orthopaedic Specialty Hospital specializes in orthopedic surgery, pain management, & sports medicine. | AH80: https://www.google.com/maps/place/Rothman+Orthopaedic+Specialty+Hospital/@40.1123117,-74.9648618,17.43z/data=!3m1!5s0x89c6c75063ecc541:0xad9d8fa1966f11bc!4m6!3m5!1s0x89c14d4966c498d5:0x794c0ae6e701ff81!8m2!3d40.1128228!4d-74.9627114!16s%2Fg%2F12hkp997b | AI80: https://www.jeffersonhealth.org/locations/rothman-orthopaedic-specialty-hospital-at-bensalem/getting-here | AJ80: https://www.jeffersonhealth.org/locations/rothman-orthopaedic-specialty-hospital-at-bensalem/department-directory | AK80: https://www.jeffersonhealth.org/locations/rothman-orthopaedic-specialty-hospital-at-bensalem | AL80: 2026-03-25
A81: Abington Cancer Care Specialists – Blue Bell | B81: Practice | D81: 721 Arbor Way, Suite 103 | E81: Blue Bell | F81: PA | G81: 19422 | H81: Montgomery County | I81: 40.139852 | J81: -75.284817 | K81: 215-481-2400 | M81: 215-481-7438 | O81: No | U81: Closed | V81: Closed | Y81: Cancer | AA81: No | AB81: No | AC81: No | AD81: No | AE81: No | AF81: No | AG81: Part of the Sidney Kimmel Comprehensive Cancer Center at Jefferson Health, Abington Cancer Care Specialists offer cancer care to its patients. | AH81: https://goo.gl/maps/UoU79f15yfvyShxm6 | AK81: https://www.jeffersonhealth.org/locations/abington-cancer-care-specialists/abington-cancer-care-specialists-blue-bell | AL81: 2026-01-24
A82: Abington Plaza Medical Associates – Blue Bell | B82: Practice | D82: 721 Arbor Way, Suite 102 | E82: Blue Bell | F82: PA | G82: 19422 | H82: Bucks County | I82: 40.139182 | J82: -75.284948 | K82: 215-491-5057 | M82: 215-491-5607 | O82: No | P82: 08:00 am - 05:00 pm | Q82: 08:00 am - 05:00 pm | R82: 08:00 am - 05:00 pm | S82: 08:00 am - 05:00 pm | T82: 08:00 am - 05:00 pm | U82: Closed | V82: Closed | W82: Phones are available from 8 a.m. to 5 p.m daily. After hours, please visit one of our Jefferson Urgent Care Centers . | X82: Family & Community Medicine | AA82: No | AB82: No | AC82: No | AD82: No | AE82: No | AF82: No | AG82: Jefferson Health's Abington Plaza Medical Associates in Blue Bell, PA offers primary care and family and community medicine services to its patients. | AH82: https://www.google.com/maps/place/Jefferson+Health+-+Blue+Bell/@40.1391817,-75.2849481,15z/data=!4m6!3m5!1s0x89c6bcf980ca3b27:0x8d63e88d5e4a0814!8m2!3d40.1391817!4d-75.2849481!16s%2Fg%2F11f55mm_8y?hl=en | AK82: https://www.jeffersonhealth.org/locations/abington-plaza-medical-associates-blue-bell | AL82: 2026-01-24
A83: Abington Pulmonary & Critical Care Associates - Blue Bell | B83: Practice | D83: 721 Arbor Way, Suite 103 | E83: Blue Bell | F83: PA | G83: 19422 | H83: Montgomery County | I83: 40.139852 | J83: -75.284817 | K83: 215-517-1200 | M83: 215-517-1219 | O83: No | P83: 08:00 am - 05:00 pm | Q83: 08:00 am - 05:00 pm | R83: 08:00 am - 05:00 pm | S83: 08:00 am - 05:00 pm | T83: 08:00 am - 04:30 pm | U83: Closed | V83: Closed | X83: Critical Care Medicine; Pulmonary Vascular Disorders; Respiratory & Pulmonary Medicine | AA83: No | AB83: No | AC83: No | AD83: No | AE83: No | AF83: No | AG83: Abington Pulmonary & Critical Care Associates in Blue Bell offers critical care medicine services to its patients. | AH83: https://goo.gl/maps/GbmnVgzAgYXyRSTX7 | AK83: https://www.jeffersonhealth.org/locations/abington-pulmonary-critical-care-associates/abington-pulmonary-critical-care-associates-blue-bell | AL83: 2026-06-16
A84: Blue Bell at Arbor Way – OB/GYN | B84: Practice | C84: Delivery Location: Jefferson Abington Hospital | D84: 721 Arbor Way | E84: Blue Bell | F84: PA | G84: 19422 | H84: Montgomery County | I84: 40.139804 | J84: -75.284887 | K84: 215-657-8430 | M84: 215-657-8439 | O84: No | P84: 08:00 am - 05:00 pm | Q84: 08:00 am - 05:00 pm | R84: 08:00 am - 05:00 pm | S84: 08:00 am - 05:00 pm | T84: Closed | U84: Closed | V84: Closed | X84: Gynecology; Obstetrics & Maternity Care; Obstetrics; Obstetrics & Gynecology; Pediatric & Adolescent Gynecology; Women's Primary Care; Midwifery; Menopause Care; Gynecologic Oncology | AA84: No | AB84: No | AC84: No | AD84: No | AE84: No | AF84: No | AG84: Jefferson OB/GYN – Blue Bell at Arbor Way (formerly Abington OB/GYN Associates - Blue Bell) provides OB/GYN and midwifery services in Blue Bell, PA. | AH84: https://goo.gl/maps/bz2KuVMDCYTQNQJB8 | AK84: https://www.jeffersonhealth.org/locations/obgyn-blue-bell-arbor-way | AL84: 2026-01-24
A85: Broad Axe Family Medicine | B85: Practice | D85: 721 Skippack Pike | E85: Blue Bell | F85: PA | G85: 19422 | H85: Montgomery County | I85: 40.155132 | J85: -75.268718 | K85: 484-622-6700 | O85: No | P85: 08:00 am - 07:00 pm | Q85: 08:00 am - 07:00 pm | R85: 08:00 am - 07:00 pm | S85: 08:00 am - 07:00 pm | T85: 08:00 am - 04:00 pm | U85: Closed | V85: Closed | X85: Primary Care; Family & Community Medicine | AA85: No | AB85: No | AC85: No | AD85: No | AE85: Yes | AF85: No | AG85: Broad Axe Family Medicine is an practice in Montgomery County, PA that offers primary care services. | AH85: https://goo.gl/maps/dbx1fJPo7kFSwx267 | AK85: https://www.jeffersonhealth.org/locations/broad-axe-family-medicine | AL85: 2026-03-20
A86: Einstein Gastroenterology Associates at Blue Bell | B86: Practice | D86: 676 Dekalb Pike | E86: Blue Bell | F86: PA | G86: 19422 | H86: Montgomery County | I86: 40.175797 | J86: -75.281609 | K86: 610-233-3175 | M86: 610-272-4182 | O86: No | P86: 08:00 am - 04:00 pm | Q86: 08:00 am - 04:00 pm | R86: 08:00 am - 04:00 pm | S86: 08:00 am - 04:00 pm | T86: 08:00 am - 04:00 pm | U86: Closed | V86: Closed | X86: Gastroenterology & Hepatology | AA86: No | AB86: No | AC86: No | AD86: No | AE86: Yes | AF86: No | AG86: Einstein Gastroenterology Associates at Blue Bell is a medical group practice located in Blue Bell, PA that specializes in Gastroenterology. | AH86: https://www.google.com/maps/place/Einstein+Gastroenterology+Associates+at+Blue+Bell/data=!4m2!3m1!1s0x0:0x4a5346ced46c969e?sa=X&ved=1t:2428&hl=en&ictx=111 | AK86: https://www.jeffersonhealth.org/locations/gastroenterology-blue-bell | AL86: 2026-09-01
A87: Jefferson Endoscopy – Blue Bell at Dekalb Pike | B87: Practice | D87: 676 DeKalb Pike | E87: Blue Bell | F87: PA | G87: 19422 | H87: Montgomery County | I87: 40.17042 | J87: -75.28538 | K87: 610-233-3177 | O87: No | P87: 06:00 am - 04:30 pm | Q87: 06:00 am - 04:30 pm | R87: 06:00 am - 04:30 pm | S87: 06:00 am - 04:30 pm | T87: 06:00 am - 04:30 pm | U87: Closed | V87: Closed | X87: Gastroenterology & Hepatology | AA87: No | AB87: No | AC87: No | AD87: No | AE87: No | AF87: No | AG87: Jefferson Endoscopy – Blue Bell at Dekalb Pike makes it easier and more convenient for patients to obtain necessary screening, diagnostic and therapeutic studies. | AH87: https://www.google.com/maps/place/Jefferson+Endoscopy+Center+at+Blue+Bell/data=!4m2!3m1!1s0x0:0x9287cb0ff771f70c?sa=X&ved=1t:2428&hl=en&ictx=111 | AK87: https://www.jeffersonhealth.org/locations/endoscopy-center-blue-bell | AL87: 2026-01-24
A88: Jefferson Health – Blue Bell at Arbor Way | B88: Laboratory; Imaging; Outpatient Medical Center | D88: 721 Arbor Way | E88: Blue Bell | F88: PA | G88: 19422 | H88: Montgomery County | I88: 40.140358 | J88: -75.285295 | K88: 215-619-6400 | O88: No | P88: 08:00 am - 04:00 pm | Q88: 08:00 am - 04:00 pm | R88: 08:00 am - 04:00 pm | S88: 08:00 am - 04:00 pm | T88: 08:00 am - 04:00 pm | U88: Closed | V88: Closed | X88: Primary Care; Podiatry; Respiratory & Pulmonary Medicine; Obstetrics & Maternity Care; Gynecology; Neurology; Imaging & Radiology; Dermatology; Nephrology; Neurosurgery; Hematology Oncology; Women's Imaging; Sleep Medicine; Obstetrics; Outpatient Imaging | AA88: Yes | AB88: Yes | AC88: No | AD88: No | AE88: No | AF88: No | AG88: Renowned patient care, dedicated physicians and medical resources including primary care, obstetrics, gynecology, neurology, cardiology, pulmonary medicine, nephrology, rehab medicine, neurosurgery, oncology, podiatry and dermatology in Blue Bell, PA. | AH88: https://www.google.com/maps/dir//jefferson+blue+bell/data=!4m6!4m5!1m1!4e2!1m2!1m1!1s0x89c6bcf980ca3b27:0x8d63e88d5e4a0814?sa=X&ved=2ahUKEwjw5K3Y5dz1AhUJpXIEHYl-DG8Q9Rd6BAgTEAU | AI88: https://www.jeffersonhealth.org/locations/blue-bell-arbor-way/directions-and-parking | AJ88: https://www.jeffersonhealth.org/locations/blue-bell-arbor-way/department-directory | AK88: https://www.jeffersonhealth.org/locations/blue-bell-arbor-way | AL88: 2026-03-25
A89: Jefferson Health – Blue Bell at Dekalb Pike | B89: Outpatient Medical Center | D89: 676 DeKalb Pike | E89: Blue Bell | F89: PA | G89: 19422 | I89: 40.171416 | J89: -75.285244 | K89: 610-233-3895 | O89: No | P89: 08:00 am - 04:30 pm | Q89: 08:00 am - 04:30 pm | R89: 08:00 am - 04:30 pm | S89: 08:00 am - 04:30 pm | T89: 08:00 am - 04:30 pm | U89: Closed | V89: Closed | X89: Endocrinology, Diabetes, & Metabolic Diseases; Gastroenterology & Hepatology | Z89: Upper Endoscopy | AA89: No | AB89: No | AC89: No | AD89: No | AE89: Yes | AF89: No | AG89: Jefferson Health – Blue Bell at Dekalb Pike is a multi-speciality outpatient center that provides endocrinology, mammography and gastroenterology services to its patients. | AH89: https://goo.gl/maps/ZRA6V5qgsBDCEBtw5 | AJ89: https://www.jeffersonhealth.org/locations/blue-bell-dekalb-pike/department-directory | AK89: https://www.jeffersonhealth.org/locations/blue-bell-dekalb-pike | AL89: 2026-03-25
A90: Jefferson Moss-Magee Rehabilitation – Blue Bell at Arbor Way | B90: Outpatient Rehabilitation | D90: 721 Arbor Way | E90: Blue Bell | F90: PA | G90: 19422 | H90: Montgomery County | I90: 40.140178 | J90: -75.285274 | K90: 215-481-2160 | M90: 215-646-2753 | O90: No | X90: Outpatient Rehabilitation; Physical Therapy; Brain Injury Rehabilitation; Rehabilitation Medicine | Y90: Concussion & Head Injuries | Z90: Vestibular Therapy | AA90: No | AB90: No | AC90: No | AD90: No | AE90: No | AF90: No | AG90: Jefferson Moss-Magee Rehabilitation – Blue Bell at Arbor Way is dedicated to improving the quality of life by providing a comprehensive, team-based approach to physical therapy for adults and children. | AH90: https://www.google.com/maps/place/721+Arbor+Way,+Blue+Bell,+PA+19422/@40.140178,-75.285274,17z/data=!3m1!4b1!4m5!3m4!1s0x89c6bcf98bbb24f1:0xdbe0ea2585175ad0!8m2!3d40.140178!4d-75.285274 | AK90: https://www.jeffersonhealth.org/locations/jefferson-rehabilitation-blue-bell | AL90: 2026-03-25
A91: Jefferson–Solis Mammography – Blue Bell at Arbor Way | B91: Imaging | C91: A department of Jefferson Abington Hospital | D91: 721 Arbor Way | E91: Blue Bell | F91: PA | G91: 19422 | H91: Philadelphia County | I91: 40.140358 | J91: -75.285295 | K91: 267-464-1105 | O91: No | P91: 08:00 am - 04:30 pm | Q91: 08:00 am - 04:30 pm | R91: 08:00 am - 04:30 pm | S91: 08:00 am - 04:30 pm | T91: 08:00 am - 04:30 pm | U91: Closed | V91: Closed | X91: Imaging & Radiology; Women's Imaging | Z91: Mammogram | AA91: Yes | AB91: Yes | AC91: No | AD91: No | AE91: No | AF91: No | AG91: Jefferson Health has partnered with Solis Mammography, the nation’s leader in screening and diagnostic mammography, to serve as an on-site provider of comprehensive breast imaging services at Jefferson locations throughout the greater Philadelphia and South Jersey area. | AH91: https://maps.app.goo.gl/qhoBEMn62X37DFKW6 | AI91: https://www.jeffersonhealth.org/locations/blue-bell-arbor-way/directions-and-parking | AK91: https://www.jeffersonhealth.org/locations/solis-mammography-blue-bell-arbor-way | AL91: 2026-01-24
A92: Jefferson–Solis Mammography – Blue Bell at Dekalb Pike | B92: Imaging | D92: 676 Dekalb Pike | E92: Blue Bell | F92: PA | G92: 19422 | H92: Philadelphia County | I92: 40.170391 | J92: -75.284244 | K92: 484-672-7421 | O92: No | P92: 07:00 am - 03:30 pm | Q92: 08:30 am - 07:30 pm | R92: 08:30 am - 05:00 pm | S92: 08:30 am - 05:00 pm | T92: 07:00 am - 03:30 pm | U92: Closed | V92: Closed | X92: Breast Care; Breast Imaging; Women's Imaging; Imaging & Radiology | Z92: Bone Densitometry; Mammogram | AA92: No | AB92: No | AC92: No | AD92: No | AE92: No | AF92: No | AG92: Jefferson Health has partnered with Solis Mammography, the nation’s leader in screening and diagnostic mammography, to serve as an on-site provider of comprehensive breast imaging services at Jefferson locations throughout the greater Philadelphia and South Jersey area. | AH92: https://maps.app.goo.gl/krK7Xei62ZobAY498 | AK92: https://www.jeffersonhealth.org/locations/solis-mammography-blue-bell-dekalb-pike | AL92: 2026-01-24
A93: Neurovascular Associates of Abington – Blue Bell | B93: Practice | D93: 721 Arbor Way, Suite 103 | E93: Blue Bell | F93: PA | G93: 19422 | H93: Montgomery County | I93: 40.139182 | J93: -75.284948 | K93: 215-481-3145 | M93: 215-481-5971 | O93: No | P93: 07:00 am - 03:00 pm | Q93: 07:00 am - 03:00 pm | R93: 07:00 am - 03:00 pm | S93: 07:00 am - 03:00 pm | T93: 07:00 am - 03:00 pm | U93: Closed | V93: Closed | X93: Stroke Care; Neuroscience | Y93: Stroke | AA93: No | AB93: No | AC93: No | AD93: No | AE93: No | AF93: No | AG93: Jefferson Health's Neurovascular Associates of Abington in Blue Bell is a neuroscience practice that has a comprehensive stroke center for its patients. | AH93: https://www.google.com/maps/place/Jefferson+Health+-+Blue+Bell/@40.1391817,-75.2849481,15z/data=!4m2!3m1!1s0x0:0x8d63e88d5e4a0814?sa=X&ved=2ahUKEwiQt9OVg9D2AhUMkYkEHUlRBFgQ_BJ6BAglEAU | AK93: https://www.jeffersonhealth.org/locations/neurovascular-associates-of-abington/neurovascular-associates-of-abington-blue-bell | AL93: 2026-01-24
A94: The Neurology Group – Blue Bell | B94: Practice | D94: 721 Arbor Way, Suite 101 | E94: Blue Bell | F94: PA | G94: 19422 | H94: Montgomery County | I94: 40.140178 | J94: -75.287463 | K94: 610-279-7443 | M94: 610-279-3784 | O94: No | P94: 09:00 am - 05:00 pm | Q94: 09:00 am - 05:00 pm | R94: 09:00 am - 05:00 pm | S94: 09:00 am - 05:00 pm | T94: 09:00 am - 04:00 pm | U94: Closed | V94: Closed | X94: Neurology; Neuroscience; Stroke; Stroke Care; Brain Injury | Y94: Traumatic Brain Injury; Stroke | AA94: Yes | AB94: No | AC94: No | AD94: No | AE94: No | AF94: No | AG94: Part of Jefferson Abington Hospital’s Neuroscience Institute, The Neurology Group is committed to being your most trusted healthcare partner. | AH94: https://goo.gl/maps/QxU7629qQ3rzNo2h6 | AK94: https://www.jeffersonhealth.org/locations/the-neurology-group | AL94: 2026-01-24
A95: Center for Autism & Neurodiversity | B95: Practice | D95: 1084 East Lancaster Ave, Units 101 & 104 | E95: Bryn Mawr | F95: PA | G95: 19010 | I95: 40.026466 | J95: -75.328761 | K95: 484-380-2167 | O95: No | X95: Autism & Neurodiversity | Y95: Autism & Autism Spectrum Disorder | AA95: Yes | AB95: No | AC95: No | AD95: No | AE95: No | AF95: No | AH95: https://www.google.com/maps?hl=en&mat=CVAl6LetRMJFElYBTVDHnnVk08ECKE-Pmsw4KKxE2BLAYZ0Sv1dVo4MghjUfEGFTa-XtgwlpqT7NILyNy2C5RIhQwaAR7lyALfG34dydLKe6I1ynhnT8KF8Hn918z-UsUg&authuser=0&um=1&ie=UTF-8&fb=1&gl=us&sa=X&geocode=Kb9w__hIv8aJMb44GV3FRQSh&daddr=1084+E+Lancaster+Ave+Units+101+%26+104,+Bryn+Mawr,+PA+19010 | AK95: https://www.jeffersonhealth.org/locations/center-for-autism-neurodiversity | AL95: 2026-01-24
A96: Jefferson Oral Surgery Associates | B96: Practice | D96: 135 South Bryn Mawr Avenue, Suite 108 | E96: Bryn Mawr | F96: PA | G96: 19010 | H96: Montgomery County | I96: 40.025218 | J96: -75.323726 | K96: 610-519-9125 | M96: 610-519-9127 | O96: No | P96: 08:00 am - 05:00 pm | Q96: 08:00 am - 05:00 pm | R96: 08:00 am - 05:00 pm | S96: 08:00 am - 05:00 pm | T96: 07:00 am - 03:30 pm | U96: Closed | V96: Closed | X96: Oral & Maxillofacial Surgery | AA96: No | AB96: No | AC96: No | AD96: No | AE96: No | AF96: Yes | AG96: Jefferson Oral Surgery Associates offers Oral & Maxillofacial Surgery and Dentistry services in Bryn Mawr, PA. | AH96: http://maps.google.com/?q=135+South+Bryn+Mawr+Avenue%2c+Bryn+Mawr%2c+PA+19010 | AK96: https://www.jeffersonhealth.org/locations/135-bryn-mawr-ave | AL96: 2026-01-24
A97: Jefferson Primary Care – Chalfont | B97: Practice | D97: 1700 Horizon Drive, Suite 203 | E97: Chalfont | F97: PA | G97: 18914 | H97: Bucks County | I97: 40.26054 | J97: -75.21762 | K97: 215-997-0890 | M97: 215-997-9652 | O97: No | P97: 08:00 am - 05:00 pm | Q97: 08:00 am - 05:00 pm | R97: 08:00 am - 05:00 pm | S97: 08:00 am - 05:00 pm | T97: 08:00 am - 05:00 pm | U97: Closed | V97: Closed | W97: After hours, please visit one of our Jefferson Urgent Care Centers . | X97: Family & Community Medicine; Primary Care | AA97: No | AB97: No | AC97: No | AD97: No | AE97: No | AF97: Yes | AG97: Find a family doctor or community medicine specialist near you in Chalfont, PA. Recognized as having one of the strongest family medicine programs in the U.S. | AH97: https://goo.gl/maps/xupPAidRsFUzSeZJ6 | AK97: https://www.jeffersonhealth.org/locations/jefferson-primary-care-chalfont | AL97: 2026-10-02
A98: 213 Reeceville Road | B98: Practice | D98: 213 Reeceville Road, Suite 17 | E98: Coatesville | F98: PA | G98: 19320 | H98: Philadelphia County | I98: 40.01032 | J98: -75.789853 | K98: 1-800-JEFF-NOW | O98: No | X98: Gastroenterology & Hepatology; Fatty Liver Care; Liver Tumor; Liver Transplant | AA98: No | AB98: No | AC98: No | AD98: No | AE98: No | AF98: No | AG98: Digestive Health, Fatty Liver Center and Liver Tumor Center services in Coatesville, PA. | AH98: https://www.google.com/maps/place/213+Reeceville+Rd+%23+17,+Coatesville,+PA+19320/@40.01032,-75.7898527 | AK98: https://www.jeffersonhealth.org/locations/213-reeceville-road | AL98: 2026-01-24
A99: Jefferson Moss-Magee Rehabilitation – Collegeville | B99: Outpatient Rehabilitation | D99: 100 Market Street, Suite 100 | E99: Collegeville | F99: PA | G99: 19426 | H99: Philadelphia County | I99: 40.167456 | J99: -75.477829 | K99: 484-622-6450 | M99: 484-622-6453 | O99: No | P99: 07:00 am - 07:00 pm | Q99: 08:00 am - 07:00 pm | R99: 07:00 am - 07:00 pm | S99: 08:00 am - 07:00 pm | T99: 07:00 am - 12:00 pm | U99: Closed | V99: Closed | X99: Cancer Rehabilitation; Rehabilitation Medicine; Pediatric Rehabilitation Medicine; Parkinson's Disease & Movement Disorders; Physical Therapy; Stroke Rehabilitation; Speech Therapy Program; Brain Injury Rehabilitation; Sports Medicine; Occupational Therapy; Balance & Hearing; Outpatient Rehabilitation; Worker's Compensation Rehabilitation; Occupational Health; Voice & Swallowing Care; Amputee Rehabilitation; Orthopedic Injury Rehabilitation | Y99: Stroke; Parkinson's Disease; Concussion & Head Injuries; Balance & Dizziness Disorders | Z99: Hand & Upper Limb Therapy; Vestibular Therapy; Rehabilitation; Cancer Rehabilitation; Amputation; Occupational Therapy; Physical Therapy; Parkinsons Disease Rehabilitation; Speech Therapy; Swallowing Therapy | AA99: No | AB99: No | AC99: No | AD99: No | AE99: No | AF99: No | AG99: Jefferson Moss-Magee Rehabilitation – Collegeville located in 100 Market Street offers outpatient services center with an expert team of rehabilitation specialists who provide physical, occupational and speech therapy for a wide range of simple and complex conditions, injuries and diseases. | AH99: https://goo.gl/maps/5Y8mTsf5hWbiRFfZ7 | AK99: https://www.jeffersonhealth.org/locations/moss-magee-rehabilitation-collegeville | AL99: 2026-03-25
A100: Jefferson Outpatient Imaging – Collegeville | B100: Imaging | D100: 534 West 2nd Avenue, Suite 102 | E100: Collegeville | F100: PA | G100: 19426 | H100: Philadelphia County | I100: 40.177898 | J100: -75.460467 | K100: 215-503-4900 | M100: 610-831-8989 | O100: No | P100: 08:00 am - 04:00 pm | Q100: 08:00 am - 08:00 pm | R100: 08:00 am - 04:00 pm | S100: 08:00 am - 08:00 pm | T100: 08:00 am - 04:00 pm | U100: Closed | V100: Closed | X100: Outpatient Imaging; Imaging & Radiology; Women's Imaging; Ultrasound | Z100: Ultrasound | AA100: No | AB100: No | AC100: No | AD100: No | AE100: No | AF100: No | AG100: Jefferson Outpatient Imaging in Collegeville, PA. | AH100: https://goo.gl/maps/rLz7VyaNH6EodA2r6 | AK100: https://www.jeffersonhealth.org/locations/joi-outpatient-imaging-collegeville | AL100: 2026-01-24
...

Sheet LVHN
A1: Name | B1: Location Types | C1: Located At | D1: Part Of (Institute) | E1: Street Address | F1: Address Line 1 | G1: Address Line 2 | H1: City | I1: State | J1: ZIP | K1: Latitude | L1: Longitude | M1: Phone | N1: Fax | O1: Hours Note | P1: Monday Hours | Q1: Tuesday Hours | R1: Wednesday Hours | S1: Thursday Hours | T1: Friday Hours | U1: Saturday Hours | V1: Sunday Hours | W1: Other Hours | X1: Hours Text | Y1: Services | Z1: Description | AA1: Alert | AB1: Location URL | AC1: Node ID | AD1: Note
A2: Community Health & Wellness Center | B2: Community Clinics | C2: Lehigh Valley Hospital–17th Street | K2: 40.6 | L2: -75.47 | M2: 610-969-2800 | P2: 8:00-17:00 | Q2: 8:00-17:00 | R2: 8:00-17:00 | S2: 8:00-17:00 | T2: 8:00-17:00 | U2: Closed | V2: Closed | Z2: VHP Mark J. Young Community Health and Wellness Center services include: Health classes in English and Spanish Diabetes self-management education Education and support for people with chronic health conditions and caregivers Medication management Help with weight management Classes on exercise and healthy eating High-risk breast program Well-woman exams (free for uninsured women) We are easily accessible by public transportation. Feel free to bring family members with you. They can learn how to be healthy and prevent illness, too. | AA2: Services Temporarily Relocated to VHP Lehigh Valley Physicians Practice VHP Lehigh Valley Physicians Practice | AB2: https://www.lvhn.org/locations/community-health-wellness-center | AC2: 54583
A3: VHP Center for Women's Medicine-Fairgrounds | B3: Physician Practices | E3: 400 N 17th St., Suite 204 | F3: 400 N 17th St. | G3: Suite 204 | H3: Allentown | J3: 18104-5052 | K3: 40.602157 | L3: -75.495196 | M3: (610) 969-3630 | N3: (610) 433-0949 | O3: Hours vary by service | Y3: Adolescent Gynecology; Prenatal Care | Z3: Learn more about VHP Center for Women's Medicine-Fairgrounds on ValleyHealthPartners.org | AB3: https://www.lvhn.org/locations/vhp-center-womens-medicine-fairgrounds | AC3: 118240
A4: North American Partners In Anesthesia | E4: 68 S Service Road, Suite 350 | F4: 68 S Service Road | G4: Suite 350 | H4: Melville | I4: NY | J4: 11747-2354 | K4: 40.781462 | L4: -73.438495 | M4: (516) 945-3000 | N4: (570) 420-2479 | O4: Hours vary by service | AB4: https://www.lvhn.org/locations/north-american-partners-anesthesia | AC4: 68440
A5: AMC Medical Associates | B5: Physician Practices | E5: 798 Hausman Road, Suite 270 | F5: 798 Hausman Road | G5: Suite 270 | H5: Allentown | I5: PA | J5: 18104-9103 | K5: 40.592883 | L5: -75.563574 | M5: (610) 432-6862 | N5: (610) 432-9705 | O5: General Facility Hours | P5: 8:00 am - 5:00 pm | Q5: 8:00 am - 5:00 pm | R5: 8:00 am - 5:00 pm | S5: 8:00 am - 5:00 pm | T5: 8:00 am - 5:00 pm | U5: Closed | V5: Closed | Y5: Primary Care | AB5: https://www.lvhn.org/locations/amc-medical-associates | AC5: 64633
A6: Advanced Dermatology Associates, Ltd | B6: Physician Practices | E6: 1259 S Cedar Crest Blvd, Suite 100 | F6: 1259 S Cedar Crest Blvd | G6: Suite 100 | H6: Allentown | I6: PA | J6: 18103-6206 | K6: 40.564533 | L6: -75.517025 | M6: (610) 437-4134 | N6: (434) 825-9193 | O6: General Facility Hours | P6: 9:00 am - 5:00 pm | Q6: 8:00 am - 4:00 pm | R6: 1:00 pm - 4:00 pm | S6: Closed | T6: Closed | U6: Closed | V6: Closed | Y6: Pediatric Dermatology | AB6: https://www.lvhn.org/locations/advanced-dermatology-associates-ltd | AC6: 64449
A7: Audiology at Lehigh Valley Hospital–Cedar Crest | B7: Testing and Imaging Centers | C7: Lehigh Valley Hospital–Cedar Crest | E7: 1200 S. Cedar Crest Blvd., Pool Family Pavilion, 1st Floor | F7: 1200 S. Cedar Crest Blvd. | G7: Pool Family Pavilion, 1st Floor | H7: Allentown | I7: PA | J7: 18103 | K7: 40.56671 | L7: -75.523755 | O7: Hours vary by service | Y7: Rehabilitation Services | Z7: Hours vary. Call 888-402-LVHN to schedule an appointment. | AB7: https://www.lvhn.org/locations/audiology-lehigh-valley-hospital-cedar-crest | AC7: 65484
A8: Bognet Medical Associates, PC | B8: Physician Practices | E8: 1275 S Cedar Crest Blvd, Suite 5 | F8: 1275 S Cedar Crest Blvd | G8: Suite 5 | H8: Allentown | I8: PA | J8: 18103-6207 | K8: 40.562861 | L8: -75.517079 | M8: (610) 821-2820 | N8: (610) 821-2859 | O8: Hours vary by service | Y8: Adolescent Gynecology; Primary Care; Smoking Cessation Counseling; Sports Medicine | AB8: https://www.lvhn.org/locations/bognet-medical-associates-pc | AC8: 64472
A9: Breast Health Services at 1405 N. Cedar Crest | B9: Specialty Care Facilities; Testing and Imaging Centers | E9: 1405 N Cedar Crest Blvd, Suite 200 | F9: 1405 N Cedar Crest Blvd | G9: Suite 200 | H9: Allentown | I9: PA | J9: 18104 | K9: 40.612017 | L9: -75.529353 | M9: 610-402- 8378 | O9: General Facility Hours | P9: 7:00 am - 3:30 pm | Q9: 7:00 am - 3:30 pm | R9: 7:00 am - 3:30 pm | S9: 7:00 am - 3:30 pm | T9: 7:00 am - 3:30 pm | U9: Closed | V9: Closed | X9: Walk-ins welcomed. | Y9: Breast Health Services; Mammogram | Z9: Our Breast Health Services team provides you with convenient access to advanced breast cancer screening technologies, including: Screening 3D mammograms (tomosynthesis) Our dedicated care team includes mammography- and ultrasound-certified technologists, board-certified radiologists and oncology-certified nurses who will support you throughout every stage of your care journey. The American College of Radiology™ has recognized LVHN as an ACR Designated Comprehensive Breast Imaging Center . This designation means we deliver safe and accurate breast cancer screenings. Our additional accreditations and recognitions from quality programs include: National Accreditation Program for Breast Centers through the American College of Surgeons National Quality Measures for Breast Centers® through the National Consortium of Breast Centers™ | AB9: https://www.lvhn.org/locations/breast-health-services-1405-n-cedar-crest | AC9: 99217
A10: Breast Health Services at Lehigh Valley Hospital–17th Street | B10: Testing and Imaging Centers | C10: Lehigh Valley Hospital–17th Street | E10: 1627 W. Chew St. | F10: 1627 W. Chew St. | H10: Allentown | I10: PA | J10: 18102 | K10: 40.601282 | L10: -75.494303 | M10: 610-402-2791 | O10: General Facility Hours | P10: 7:00 am - 5:00 pm | Q10: 7:00 am - 5:00 pm | R10: 7:00 am - 5:00 pm | S10: 7:00 am - 5:00 pm | T10: 7:00 am - 4:00 pm | U10: Closed | V10: Closed | Y10: Breast Health Services; Mammogram | Z10: We provide advanced breast imaging for breast cancer screening and diagnosis. Breast Health Services offers: Screening mammograms Tomosynthesis (also called 3D mammograms) Diagnostic mammograms for new clinical breast problems Follow-up imaging after an abnormal mammogram Breast ultrasounds Breast biopsy procedures, including ultrasound-guided core biopsy and stereotactic core biopsy Breast Health Services is an American College of Radiology Accredited Center of Excellence. We also maintain accreditation in other quality programs, including: National Accreditation Program for Breast Centers (NAPBC) through the American College of Surgeons National Quality Measure of Breast Centers through the National Consortium of Breast Centers | AB10: https://www.lvhn.org/locations/breast-health-services-lehigh-valley-hospital-17th-street | AC10: 54574
A11: Breast Health Services at Lehigh Valley Hospital–Cedar Crest | B11: Testing and Imaging Centers | C11: Lehigh Valley Hospital–Cedar Crest | E11: 1240 S Cedar Crest Blvd, Suite 203 | F11: 1240 S Cedar Crest Blvd | G11: Suite 203 | H11: Allentown | I11: PA | J11: 18103-6218 | K11: 40.566494 | L11: -75.521491 | M11: 610-402-0690 | O11: General Facility Hours | P11: 7:00 am - 6:00 pm | Q11: 7:00 am - 6:00 pm | R11: 7:00 am - 6:00 pm | S11: 7:00 am - 6:00 pm | T11: 7:00 am - 4:00 pm | U11: 7:00 am - 3:30 pm (1st and 3rd Saturdays only) | V11: Closed | Y11: Breast Health Services; Breast Magnetic Resonance Imaging (MRI); Mammogram; Oncology | Z11: Our services Breast Health Services is an ACR Accredited Center of Excellence, maintaining accreditation in many quality programs , including: NAPBC (National Accreditation Program for Breast Centers through the American College of Surgeons) NQMBC (National Quality Measure of Breast Centers through the National Consortium of Breast Centers). Our dedicated, professional staff includes mammography-certified technologists, board-certified dedicated radiologists, and oncology-certified nurses. We provide advanced breast imaging for breast cancer screening and diagnosis. Breast Health Services offers: Screening mammograms Automated Breast Ultrasound (ABUS) Tomosynthesis , or 3D mammography Diagnostic mammograms for new clinical breast problems Follow up from an abnormal mammogram Breast ultrasounds Breast biopsy procedures via either ultrasound-guided core biopsy or stereotactic core biopsy | AB11: https://www.lvhn.org/locations/breast-health-services-lehigh-valley-hospital-cedar-crest | AC11: 54571
A12: Breidegam Family Children’s ER at Lehigh Valley Hospital-Cedar Crest | B12: Children's Hospital; Emergency Rooms | E12: 1200 S Cedar Crest Blvd, PO Box 689 | F12: 1200 S Cedar Crest Blvd | G12: PO Box 689 | H12: Allentown | I12: PA | J12: 18103-6202 | K12: 40.566346 | L12: -75.523839 | M12: (610) 402-9750 | N12: (610) 402-9763 | O12: Open 24 hours | P12: Open 24 hours | Q12: Open 24 hours | R12: Open 24 hours | S12: Open 24 hours | T12: Open 24 hours | U12: Open 24 hours | V12: Open 24 hours | Y12: Children\u2019s ER; Pediatric Trauma Care | Z12: Lehigh Valley Reilly Children’s Hospital has the region’s most experienced 24/7 emergency room dedicated to children. Located at Lehigh Valley Hospital–Cedar Crest and built just for kids, the 27-bed Breidegam Family Children’s ER is staffed by board-certified pediatric emergency medicine physicians who skillfully and compassionately care for ill and injured kids. Serving families from Allentown, Emmaus and Lehigh County to the Lehigh Valley and beyond, our Children’s ER is one of the most trusted emergency rooms for pediatric care. Highly trained staff provide emergency care for kids The Breidegam Family Children’s ER is run by board-certified pediatric emergency physicians. They are supported by: Advanced practice clinicians who are experienced in caring for kids A nursing team specially trained in pediatric emergency nursing Pediatric pharmacists for accurate medication dosing Child-life specialists who make the hospital experience less stressful for children Pediatric respiratory t | AB12: https://www.lvhn.org/locations/breidegam-family-childrens-er-lehigh-valley-hospital-cedar-crest | AC12: 78696
A13: Burn Recovery Center | B13: Specialty Care Facilities | C13: Lehigh Valley Hospital–Cedar Crest | D13: Lehigh Valley Institute for Surgical Excellence | E13: 1200 S. Cedar Crest Blvd, 3rd Floor Kasych Pavilion | F13: 1200 S. Cedar Crest Blvd | G13: 3rd Floor Kasych Pavilion | H13: Allentown | I13: PA | J13: 18103-6202 | K13: 40.566346 | L13: -75.523839 | M13: (610) 402-8355 | N13: (610) 402-2877 | O13: General Facility Hours | P13: 8:00 am - 5:00 pm | Q13: 8:00 am - 5:00 pm | R13: 8:00 am - 5:00 pm | S13: 8:00 am - 5:00 pm | T13: 8:00 am - 5:00 pm | U13: Closed | V13: Closed | Y13: Adolescent Gynecology; Burn Treatment; Pediatric Trauma Care; Primary Care; Smoking Cessation Counseling; Sports Medicine | Z13: In addition to providing leading-edge burn care and rehabilitation services, we provide state-of-the-art scar management, including: Evaluation for reconstructive or plastic surgery Scar massage Splint fabrication Pressure garment therapy Laser and light therapy Cosmetic consultations Permanent makeup to hide scars Therapy to help you cope with emotional challenges LVHN’s Burn Recovery Center is the only one in northeastern Pennsylvania certified by the American Burn Association and the American College of Surgeons to care for adults and children. | AB13: https://www.lvhn.org/locations/burn-recovery-center | AC13: 54575
A14: Cancer Support Services-Cedar Crest | B14: Specialty Care Facilities | C14: Lehigh Valley Hospital–Cedar Crest | D14: Lehigh Valley Topper Cancer Institute | E14: 1240 S Cedar Crest Blvd, Allentown, PA 18103, Suite 310 | F14: 1240 S Cedar Crest Blvd, Allentown, PA 18103 | G14: Suite 310 | H14: Allentown | I14: PA | J14: 18103-6369 | K14: 40.566494 | L14: -75.521491 | M14: 610-402-9546 | N14: 610-402-9576 | O14: Hours vary by service | Y14: Young Adult SurvivorPLACE | Z14: A physician or nurse practitioner will perform an exam and routine surveillance screening. Our team of oncology professionals also can provide recommendations for lasting effects related to cancer or its treatment. The Young Adult Survivor PLACE team also includes a rehabilitation specialist, dietitian, social worker, and a nurse navigator. | AB14: https://www.lvhn.org/locations/cancer-support-services-cedar-crest | AC14: 94898
A15: Cardiac Diagnostic Center at Lehigh Valley Hospital–Cedar Crest | B15: Testing and Imaging Centers | C15: Lehigh Valley Hospital–Cedar Crest | D15: Lehigh Valley Heart and Vascular Institute | E15: 1250 S. Cedar Crest Blvd., Suite 305 | F15: 1250 S. Cedar Crest Blvd. | G15: Suite 305 | H15: Allentown | I15: PA | J15: 18103 | K15: 40.566568 | L15: -75.519745 | O15: Hours vary by service | X15: Hours vary by test | Y15: Echocardiogram; Exercise Treadmill Stress Test; Heart Imaging; Holter Monitor; Nuclear Stress Test; Stress Echocardiogram; Vascular Studies | Z15: The Cardiac Diagnostic Center at Lehigh Valley Hospital–Cedar Crest is also known as the Heart Station. Hours by test are listed below: Echocardiogram Mon.-Fri. 7:30 a.m. to 5 p.m. Exercise treadmill stress test Mon.-Fri. 7:30 a.m. to 3 p.m. Holter monitor Mon.-Fri. 7:30 a.m. to 3 p.m. Nuclear stress test Mon.-Fri. 7:30 a.m. to 3 p.m. Stress echocardiogram Mon.-Fri. 7:30 a.m. to 3 p.m. Vascular studies Tues. and Fri. 8 a.m. to 4:30 p.m. A service of Lehigh Valley Hospital. | AB15: https://www.lvhn.org/locations/cardiac-diagnostic-center-lehigh-valley-hospital-cedar-crest | AC15: 65411
A16: Cardiac Rehabilitation–1250 Cedar Crest | B16: Rehabilitation Locations | C16: Lehigh Valley Hospital–Cedar Crest | D16: Lehigh Valley Heart and Vascular Institute | E16: 1250 S. Cedar Crest Blvd., Suite 112 | F16: 1250 S. Cedar Crest Blvd. | G16: Suite 112 | H16: Allentown | I16: PA | J16: 18103 | K16: 40.566568 | L16: -75.519745 | M16: 610-402-5915 | O16: General Facility Hours | P16: 7:30 am - 5:30 pm | Q16: 7:30 am - 4:30 pm | R16: 7:30 am - 5:30 pm | S16: 7:30 am - 4:30 pm | T16: 7:30 am - 5:30 pm | U16: Closed | V16: Closed | Y16: Cardiac Rehabilitation; Pulmonary Rehabilitation | Z16: A service of Lehigh Valley Hospital. | AB16: https://www.lvhn.org/locations/cardiac-rehabilitation-1250-cedar-crest | AC16: 80879
A17: Center for Advanced Health Care | B17: Specialty Care Facilities | C17: Lehigh Valley Hospital–Cedar Crest | E17: 1250 S. Cedar Crest Blvd. | F17: 1250 S. Cedar Crest Blvd. | H17: Allentown | I17: PA | J17: 18103-6224 | K17: 40.566568 | L17: -75.519745 | O17: Hours vary by service | Z17: The Center for Advanced Health Care on the campus of Lehigh Valley Hospital–Cedar Crest is home to the following physician practices and services: First Floor Imaging services (CT) LVPG Orthopedics and Sports Medicine Second Floor LVPG Infectious Diseases–1250 Cedar Crest LVPG Pulmonary and Critical Care Medicine–1250 Cedar Crest LVPG Transplant Surgery–1250 Cedar Crest LVPG Urology–1250 Cedar Crest Third Floor LVPG Cardiology–1250 Cedar Crest Cardiac Diagnostic Center LVPG Cardiac and Thoracic Surgery–1250 Cedar Crest Fourth Floor Neuroscience Center LVPG Neurology–1250 Cedar Crest Neuropsychiatry services Valet parking is available Monday – Friday: 7 a.m. – 5 p.m. (last vehicle accepted at 4 p.m.). A service of Lehigh Valley Hospital. | AB17: https://www.lvhn.org/locations/center-advanced-health-care | AC17: 54624
A18: Center for Orthopedic Medicine–Tilghman | B18: Specialty Care Facilities | C18: Lehigh Valley Health Network–Tilghman | D18: Lehigh Valley Orthopedic Institute | E18: 4815 Tilghman Street | F18: 4815 Tilghman Street | H18: Allentown | I18: PA | J18: 18104 | K18: 40.590734 | L18: -75.562906 | M18: 610-402-3903 | O18: Hours vary by service | Y18: Orthopedics; Robotic-Assisted Knee Replacement; Sports Medicine; Surgery | AB18: https://www.lvhn.org/locations/center-orthopedic-medicine-tilghman | AC18: 69477
A19: Children's Hospital of Philadelphia-Cardiac Center Allentown | B19: Children's Hospital; Physician Practices | E19: 1605 N Cedar Crest Blvd, Suites 117 & 119 | F19: 1605 N Cedar Crest Blvd | G19: Suites 117 & 119 | H19: Allentown | I19: PA | J19: 18104-2351 | K19: 40.614893 | L19: -75.531593 | M19: (610) 437-6687 | N19: (610) 437-5232 | O19: Hours vary by service | AB19: https://www.lvhn.org/locations/childrens-hospital-philadelphia-cardiac-center-allentown | AC19: 67441
A20: Children’s Cancer and Multipurpose Infusion Center | B20: Children's Hospital | C20: Lehigh Valley Hospital–Cedar Crest | D20: Lehigh Valley Reilly Children’s Hospital | E20: 1210 South Cedar Crest Blvd., Suite 1000 | F20: 1210 South Cedar Crest Blvd. | G20: Suite 1000 | H20: Allentown | I20: PA | J20: 18103 | K20: 40.566715 | L20: -75.523667 | M20: 610-402-1026 | O20: General Facility Hours | P20: 8:00 am - 5:00 pm | Q20: 8:00 am - 5:00 pm | R20: 8:00 am - 5:00 pm | S20: 8:00 am - 5:00 pm | T20: 8:00 am - 5:00 pm | U20: Closed | V20: Closed | Z20: The Children’s Cancer and Multipurpose Infusion Center at Lehigh Valley Reilly Children’s Hospital is a kid-friendly, dedicated space for children to receive infusions for blood disorders or cancer care. The team has specialty training in caring for kids with these specific conditions. Located at the Children’s Specialty Center , this dedicated space for children offers a caring, kid-friendly environment where our specialty-trained team treats children who are receiving cancer care. We also treat children with blood disorders including: Anemia and sickle cell disease Immunodeficiency disorders like HIV/AIDS Iron disorders like hemochromatosis Juvenile arthritis Crohn’s disease and inflammatory bowel syndrome (IBS) We treat cancers and other blood conditions by offering infusions of: Biologic medications Chemotherapy drugs Disease-modifying antirheumatic drugs (DMARDs) Iron or drugs that remove excess iron Immunoglobulins (antibodies that support the immune system) Immunosuppressants Sy | AB20: https://www.lvhn.org/locations/childrens-cancer-and-multipurpose-infusion-center | AC20: 66973
A21: Community Health and Wellness Center | E21: 17th & Chew Streets | F21: 17th & Chew Streets | H21: Allentown | I21: PA | J21: 18105 | K21: 40.600778 | L21: -75.49423 | M21: 610-969-2800 | N21: 610-969-2802 | O21: Hours vary by service | AB21: https://www.lvhn.org/locations/community-health-and-wellness-center-0 | AC21: 78383
A22: Comprehensive Pain Centers | B22: Specialty Care Facilities | E22: 1146 S Cedar Crest Blvd, 2nd Floor | F22: 1146 S Cedar Crest Blvd | G22: 2nd Floor | H22: Allentown | I22: PA | J22: 18103-7938 | K22: 40.570562 | L22: -75.519519 | M22: (610) 366-9000 | N22: (610) 366-9229 | O22: Hours vary by service | Y22: Physiatry (Physical Medicine and Rehabilitation) | AB22: https://www.lvhn.org/locations/comprehensive-pain-centers | AC22: 66645
A23: David and Jackie Jaindl Family Birth and Newborn Center | B23: Birthing Centers | C23: Lehigh Valley Hospital–Cedar Crest | E23: 1200 S Cedar Crest Boulevard | F23: 1200 S Cedar Crest Boulevard | H23: Allentown | I23: PA | J23: 18103 | K23: 40.56671 | L23: -75.523755 | O23: Hours vary by service | Y23: Childbirth (Labor and Delivery); Pregnancy Care and Childbirth; Prenatal Care | Z23: Every birth is special. At the David and Jackie Jaindl Family Birth and Newborn Center at Lehigh Valley Hospital (LVH)–Cedar Crest , we feel fortunate to be trusted to care for you and your baby. As the leader in complete management of pregnancy and delivery care services, your safety and comfort are top priorities. We are committed to providing mother, newborn and family with excellence in maternity and newborn care in a welcoming environment. Our highly skilled team of physicians, midwives and nurses work together to make your birth experience the safe, personalized and joyous event you have imagined. If you have a high-risk condition or a medical complication of pregnancy, our maternal fetal medicine specialists are always available to you. We also offer the region’s highest level IV neonatal intensive care unit (NICU) in case your baby needs more intensive, specialized care. And Lehigh Valley Reilly Children’s Hospital , the region’s only children’s hospital for comprehensive pedia | AB23: https://www.lvhn.org/locations/david-and-jackie-jaindl-family-birth-and-newborn-center | AC23: 68928
A24: Dental Clinic at Lehigh Valley Hospital-17th Street | B24: Community Clinics | C24: Lehigh Valley Hospital–17th Street | E24: 1627 W. Chew St. | F24: 1627 W. Chew St. | H24: Allentown | I24: PA | J24: 18102 | K24: 40.601282 | L24: -75.494303 | M24: 610-969-3955 | O24: General Facility Hours | P24: 8:00 am - 5:00 pm | Q24: 8:00 am - 5:00 pm | R24: 8:00 am - 5:00 pm | S24: 8:00 am - 5:00 pm | T24: 8:00 am - 5:00 pm | U24: Closed | V24: Closed | Y24: Dental Medicine | Z24: We offer: Routine dental care, including cleaning Cavity fillings Tooth extractions Root canals Fluoride treatments Education on proper brushing, flossing and healthy eating The Dental Clinic participates in Give Kids a Smile Day, an annual event that provides free dental care for children. It also helps staff Miles of Smiles, a mobile dental clinic with two treatment rooms that helps an estimated 11,000 children in Allentown who need dental care but can't afford a trip to the dentist. | AB24: https://www.lvhn.org/locations/dental-clinic-lehigh-valley-hospital-17th-street | AC24: 54585
A25: Diagnostic Care Center at Lehigh Valley Hospital–17th Street | B25: Testing and Imaging Centers | C25: Lehigh Valley Hospital–17th Street | E25: 1627 W. Chew St. | F25: 1627 W. Chew St. | H25: Allentown | I25: PA | J25: 18102 | K25: 40.601131 | L25: -75.493992 | M25: 888-402-5896 | O25: Hours vary by service | Y25: Audiology; Electrocardiogram (EKG or ECG); Lab Tests; Pre-Admission Testing; Pre-Procedure COVID-19 Testing; Pulmonary Function Test (PFT); X-Ray | Z25: Schedule Online Using MyLVHN Schedule your diagnostic tests and rehabilitation services online. Just sign in to your MyLVHN account and click on “schedule an appointment.” All eligible diagnostic tests will appear, and you will be able to schedule your tests at a time and location convenient for you. If you don't have an account, sign up for one today at MyLVHN.org or through the free MyLVHN app available on the App Store or Google Play . A service of Lehigh Valley Hospital. | AB25: https://www.lvhn.org/locations/diagnostic-care-center-lehigh-valley-hospital-17th-street | AC25: 65462
A26: Diagnostic Care Center at Lehigh Valley Hospital–Cedar Crest | B26: Testing and Imaging Centers | C26: Lehigh Valley Hospital–Cedar Crest | E26: 1200 S. Cedar Crest Blvd.,, Jaindl Family Pavilion, 1st floor | F26: 1200 S. Cedar Crest Blvd., | G26: Jaindl Family Pavilion, 1st floor | H26: Allentown | I26: PA | J26: 18103 | K26: 40.566755 | L26: -75.524163 | O26: Hours vary by service | X26: Hours vary by test Echocardiogram Open | Y26: Audiology; Echocardiogram; Electrocardiogram (EKG or ECG); Electroencephalogram (EEG); Electromyogram (EMG); Endocrine Testing; Exercise Treadmill Stress Test; Holter Monitor; Lab Tests; Nuclear Stress Test; Pre-Admission Testing; Pre-Procedure COVID-19 Testing; Pulmonary Function Test (PFT); Stress Echocardiogram | Z26: Our services View the diagnostic tests and hours at this location . Schedule Online Using MyLVHN Schedule your diagnostic tests and rehabilitation services online. Just sign in to your MyLVHN account and click on “schedule an appointment.” All eligible diagnostic tests will appear, and you will be able to schedule your tests at a time and location convenient for you. If you don't have an account, sign up for one today at MyLVHN.org or through the free MyLVHN app available on the App Store or Google Play . A service of Lehigh Valley Hospital. | AB26: https://www.lvhn.org/locations/diagnostic-care-center-lehigh-valley-hospital-cedar-crest | AC26: 65464
A27: Eastern Pennsylvania Endoscopy Center | B27: Specialty Care Facilities; Testing and Imaging Centers | E27: 1501 N Cedar Crest Blvd, Suite 100 | F27: 1501 N Cedar Crest Blvd | G27: Suite 100 | H27: Allentown | I27: PA | J27: 18104 | K27: 40.612861 | L27: -75.53138 | M27: (610) 289-2172 | N27: (610) 289-2542 | O27: Hours vary by service | Y27: Colonoscopy; Endoscopy; Gastroenterology; Motility Center | Z27: The Eastern Pennsylvania Endoscopy Center is a joint venture between Lehigh Valley Health Network and board-certified gastroenterology physicians. At the endoscopy center, patients receive upper and lower endoscopies, including colonoscopies, at a state-of-the-art location from highly-trained gastroenterology specialists. This provides greater access, convenience and savings to the community. Non-hospital setting: Patients may prefer visiting smaller facilities for the same level of care and safety measures. Convenient: There is no need to look at a hospital map. These services are offered at locations with plenty of parking close to the main entrance. Accessible: With more locations, patients can choose the facility that best suits them. Affordable: Depending on a patient’s health plan, receiving care in an outpatient facility rather than in a hospital-based outpatient setting may mean increased savings for the patient. | AB27: https://www.lvhn.org/locations/eastern-pennsylvania-endoscopy-center | AC27: 111279
A28: Emergency Room at Lehigh Valley Hospital-17th Street | B28: Emergency Rooms | C28: Lehigh Valley Hospital–17th Street | E28: 1627 W. Chew St. | F28: 1627 W. Chew St. | H28: Allentown | I28: PA | J28: 18102 | K28: 40.601131 | L28: -75.493992 | M28: 610-969-2226 | O28: Open 24 hours | P28: Open 24 hours | Q28: Open 24 hours | R28: Open 24 hours | S28: Open 24 hours | T28: Open 24 hours | U28: Open 24 hours | V28: Open 24 hours | Y28: Emergency Care | Z28: When you or a loved one needs urgent care, finding the closest emergency room (ER) is critical. The emergency room at Lehigh Valley Hospital–17th Street in Allentown provides 24/7 care for major and minor medical issues, making it one of the most trusted emergency rooms in Lehigh County. Located near the corner of 17th and Chew streets, our ER is the closest hospital emergency room for residents in Allentown and surrounding neighborhoods. If you're searching for “emergency rooms close to me” or “emergency rooms nearby,” we're here for you. Our full-service ER evaluates and treats a wide range of conditions. Whether you're wondering when to go to the emergency room or need help now, our team is ready to provide expert care in a safe, welcoming environment. Emergency medicine for heart attack If you are experiencing heart attack symptoms, including chest pain, shortness of breath or pain in your arms, neck, jaw or back – call 911. Lehigh Valley Heart and Vascular Institute consistently r | AB28: https://www.lvhn.org/locations/emergency-room-lehigh-valley-hospital-17th-street | AC28: 54566
A29: Emergency Room at Lehigh Valley Hospital-Cedar Crest | B29: Emergency Rooms | C29: Lehigh Valley Hospital–Cedar Crest | E29: 1270 South Cedar Crest Boulevard | F29: 1270 South Cedar Crest Boulevard | H29: Allentown | I29: PA | J29: 18103 | K29: 40.567646 | L29: -75.518814 | M29: 610-402-8111 | O29: Open 24 hours | P29: Open 24 hours | Q29: Open 24 hours | R29: Open 24 hours | S29: Open 24 hours | T29: Open 24 hours | U29: Open 24 hours | V29: Open 24 hours | Y29: Emergency Care | Z29: Emergency Room at LVH–Cedar Crest offers: Comprehensive trauma, burn and neurology emergency services, 24/7. MI Alert for heart attacks and stroke alert programs designed to deliver fast, gold-standard care for the best outcomes possible. The Walter J. and June H. Okunski Burn Recovery Center is Pennsylvania’s largest burn center and is verified to treat adults and children. A quick care area for patients with less severe injuries, like fractures or cuts. When seconds count, you need an ER near you that delivers expert care fast. At Lehigh Valley Hospital–Cedar Crest, our ER is open 24/7 to serve Allentown and surrounding communities. Watch this video to learn about the triage process in the ER ( also available with Spanish subtitles ). Emergency medicine for heart attack If you are experiencing heart attack symptoms, including chest pain, shortness of breath or pain in your arms, neck, jaw or back – call 911. Lehigh Valley Heart and Vascular Institute consistently ranks among the nati | AB29: https://www.lvhn.org/locations/emergency-room-lehigh-valley-hospital-cedar-crest | AC29: 54606
A30: Fairmont Medical Center | E30: 1720 W Fairmont Street | F30: 1720 W Fairmont Street | H30: Allentown | I30: PA | J30: 18104-3118 | K30: 40.615388 | L30: -75.502021 | M30: (610) 841-2798 | N30: (610) 841-2796 | O30: Hours vary by service | Y30: Adolescent Gynecology; Primary Care; Smoking Cessation Counseling; Sports Medicine | AB30: https://www.lvhn.org/locations/fairmont-medical-center-0 | AC30: 70286
A31: Fleming Memory Center | B31: Specialty Care Facilities | E31: 1627 W. Chew St. | F31: 1627 W. Chew St. | H31: Allentown | I31: PA | J31: 18102 | K31: 40.601131 | L31: -75.493992 | M31: 610-969-3390 | O31: General Facility Hours | P31: 8:00 am - 4:30 pm | Q31: 8:00 am - 4:30 pm | R31: 8:00 am - 4:30 pm | S31: 8:00 am - 4:30 pm | T31: 8:00 am - 4:30 pm | U31: Closed | V31: Closed | Y31: Lecanemab Monoclonal Antibody Treatment; Memory Care | Z31: At Fleming Memory Center we provide complete assessments of geriatric patients with memory loss, including a review of medical and social history, a physical exam, medication management and cognitive testing. After this evaluation, we create specialized treatment and care plans that are communicated with the caregiver, primary care physician and other specialists. Resources for caregivers include: Monthly caregiver support groups (call 610-969-3390 for schedule) Quarterly educational sessions Social worker drop-in hours | AB31: https://www.lvhn.org/locations/fleming-memory-center | AC31: 69293
A32: Forensic Pathology Associates Inc | B32: Physician Practices | E32: 1255 S Cedar Crest Blvd, Suite 3800 | F32: 1255 S Cedar Crest Blvd | G32: Suite 3800 | H32: Allentown | I32: PA | J32: 18103-6240 | K32: 40.565378 | L32: -75.515204 | M32: (610) 402-8144 | N32: (610) 402-5637 | O32: Hours vary by service | AB32: https://www.lvhn.org/locations/forensic-pathology-associates-inc | AC32: 64714
A33: Gregory and Lorraine Harper Cancer Risk and Genetic Assessment Program | B33: Cancer Centers; Specialty Care Facilities | C33: John and Dorothy Morgan Cancer Center | D33: Lehigh Valley Topper Cancer Institute | E33: 1240 S. Cedar Crest Blvd., Suite 310 | F33: 1240 S. Cedar Crest Blvd. | G33: Suite 310 | H33: Allentown | I33: PA | J33: 18103 | K33: 40.566517 | L33: -75.522369 | M33: 610-402-8787 | N33: 610-402-2754 | O33: General Facility Hours | P33: 7:30 am - 4:00 pm | Q33: 7:30 am - 4:00 pm | R33: 7:30 am - 4:00 pm | S33: 7:30 am - 4:00 pm | T33: 7:30 am - 4:00 pm | U33: Closed | V33: Closed | Y33: Cancer Risk and Genetic Assessment Program | Z33: The Gregory and Lorraine Harper Cancer Risk and Genetic Assessment Program is the largest of its kind in the region, offering expert cancer risk assessment to more than 600 new patients each year. In addition to comprehensive genetic counseling and testing, the program features a high-risk multidisciplinary clinic designed for individuals identified as having an elevated cancer risk. This clinic provides annual follow-up appointments, personalized care plans and ongoing support. To schedule an appointment, call 610-402-8787. | AB33: https://www.lvhn.org/locations/gregory-and-lorraine-harper-cancer-risk-and-genetic-assessment-program | AC33: 118410
A34: HNL Lab Medicine | B34: Testing and Imaging Centers | C34: Lehigh Valley Hospital–Cedar Crest | E34: 1200 S Cedar Crest Boulevard | F34: 1200 S Cedar Crest Boulevard | H34: Allentown | I34: PA | J34: 18103-6202 | K34: 40.56671 | L34: -75.523755 | M34: (610) 402-8426 | N34: (610) 402-1691 | O34: Hours vary by service | AB34: https://www.lvhn.org/locations/hnl-lab-medicine | AC34: 69482
A35: HNL Lab Medicine–Allentown - 1251 S Cedar Crest | B35: Children's Hospital; Testing and Imaging Centers | E35: 1251 South Cedar Crest Boulevard, Ste. 105 | F35: 1251 South Cedar Crest Boulevard | G35: Ste. 105 | H35: Allentown | I35: PA | J35: 18103 | K35: 40.56587 | L35: -75.516663 | M35: (484) 425-5271 | N35: (484) 425-5345 | O35: General Facility Hours | P35: 7:00 am - 5:30 pm | Q35: 7:00 am - 5:30 pm | R35: 7:00 am - 5:30 pm | S35: 7:00 am - 5:30 pm | T35: 7:00 am - 5:30 pm | U35: 7:00 am - 12:00 pm | V35: Closed | Y35: COVID-19 Testing for People Without Symptoms; COVID-19 Testing for People with Symptoms; Lab Tests; Pediatric Blood Draws; Prueba de COVID-19 para personas sin s\u00edntomas; Pruebas de detecci\u00f3n y atenci\u00f3n para el coronavirus (COVID-19) para personas con s\u00edntomas | AB35: https://www.lvhn.org/locations/hnl-lab-medicine-allentown-1251-s-cedar-crest | AC35: 79341
A36: HNL Lab Medicine–Allentown - Crest Plaza | B36: Testing and Imaging Centers | E36: 1630 North Cedar Crest Boulevard | F36: 1630 North Cedar Crest Boulevard | H36: Allentown | I36: PA | J36: 18104 | K36: 40.613755 | L36: -75.535511 | M36: (484) 425-5277 | N36: (484) 425-5345 | O36: General Facility Hours | P36: 6:30 am - 5:00 pm | Q36: 6:30 am - 5:00 pm | R36: 6:30 am - 5:00 pm | S36: 6:30 am - 5:00 pm | T36: 6:30 am - 5:00 pm | U36: 7:00 am - 11:00 am | V36: Closed | Y36: COVID-19 Testing for People Without Symptoms; COVID-19 Testing for People with Symptoms; Lab Tests; Prueba de COVID-19 para personas sin s\u00edntomas; Pruebas de detecci\u00f3n y atenci\u00f3n para el coronavirus (COVID-19) para personas con s\u00edntomas | AB36: https://www.lvhn.org/locations/hnl-lab-medicine-allentown-crest-plaza | AC36: 79347
A37: HNL Lab Medicine–Allentown - Fairgrounds Medical Center | B37: Testing and Imaging Centers | E37: 400 North 17th Street, Ste. 202 | F37: 400 North 17th Street | G37: Ste. 202 | H37: Allentown | I37: PA | J37: 18104 | K37: 40.602199 | L37: -75.495298 | M37: (484) 425-5272 | N37: (484) 425-5345 | O37: General Facility Hours | P37: 7:00 am - 3:00 pm | Q37: 7:00 am - 3:00 pm | R37: 7:00 am - 3:00 pm | S37: 7:00 am - 3:00 pm | T37: 7:00 am - 3:00 pm | U37: 7:00 am - 11:00 am | V37: Closed | Y37: COVID-19 Testing for People Without Symptoms; COVID-19 Testing for People with Symptoms; COVID-19 Vaccine Boosters and Third Shots; Lab Tests; Prueba de COVID-19 para personas sin s\u00edntomas; Pruebas de detecci\u00f3n y atenci\u00f3n para el coronavirus (COVID-19) para personas con s\u00edntomas | AB37: https://www.lvhn.org/locations/hnl-lab-medicine-allentown-fairgrounds-medical-center | AC37: 79339
A38: HNL Lab Medicine–Allentown - Hanover Ave | B38: Testing and Imaging Centers | E38: 1302 Hanover Avenue, Allentown Commons Suite 1312 | F38: 1302 Hanover Avenue | G38: Allentown Commons Suite 1312 | H38: Allentown | I38: PA | J38: 18109 | K38: 40.618051 | L38: -75.433471 | M38: (484) 425-5267 | N38: (484) 425-5345 | O38: General Facility Hours | P38: 7:00 am - 3:00 pm | Q38: 7:00 am - 3:00 pm | R38: 7:00 am - 3:00 pm | S38: 7:00 am - 3:00 pm | T38: 7:00 am - 3:00 pm | U38: 7:00 am - 12:00 pm | V38: Closed | Y38: COVID-19 Testing for People Without Symptoms; COVID-19 Testing for People with Symptoms; Lab Tests; Pre-Procedure COVID-19 Testing; Prueba de COVID-19 para personas sin s\u00edntomas; Pruebas de detecci\u00f3n y atenci\u00f3n para el coronavirus (COVID-19) para personas con s\u00edntomas | AB38: https://www.lvhn.org/locations/hnl-lab-medicine-allentown-hanover-ave | AC38: 79353
A39: HNL Lab Medicine–Allentown - Hausman Rd | B39: Testing and Imaging Centers | E39: 798 Hausman Road, Ste. 260 | F39: 798 Hausman Road | G39: Ste. 260 | H39: Allentown | I39: PA | J39: 18104 | K39: 40.592883 | L39: -75.563574 | M39: (484) 425-5266 | N39: (484) 425-5345 | O39: General Facility Hours | P39: 8:00 am - 12:00 pm | Q39: 8:00 am - 12:00 pm | R39: 8:00 am - 12:00 pm | S39: 8:00 am - 12:00 pm | T39: 8:00 am - 12:00 pm | U39: Closed | V39: Closed | Y39: COVID-19 Testing for People Without Symptoms; COVID-19 Testing for People with Symptoms; Lab Tests; Prueba de COVID-19 para personas sin s\u00edntomas; Pruebas de detecci\u00f3n y atenci\u00f3n para el coronavirus (COVID-19) para personas con s\u00edntomas | AB39: https://www.lvhn.org/locations/hnl-lab-medicine-allentown-hausman-rd | AC39: 79963
A40: HNL Lab Medicine–Allentown - Lehigh St | B40: Children's Hospital; Testing and Imaging Centers | E40: 2402 Sunshine Road | F40: 2402 Sunshine Road | H40: Allentown | I40: PA | J40: 18103 | K40: 40.568627 | L40: -75.481888 | M40: (484) 425-5261 | N40: (484) 425-5345 | O40: General Facility Hours | P40: 7:00 am - 2:30 pm | Q40: 7:00 am - 2:30 pm | R40: 7:00 am - 2:30 pm | S40: 7:00 am - 2:30 pm | T40: 7:00 am - 2:30 pm | U40: Closed | V40: Closed | Y40: COVID-19 Testing for People Without Symptoms; COVID-19 Testing for People with Symptoms; Lab Tests; Pediatric Blood Draws; Prueba de COVID-19 para personas sin s\u00edntomas; Pruebas de detecci\u00f3n y atenci\u00f3n para el coronavirus (COVID-19) para personas con s\u00edntomas | AB40: https://www.lvhn.org/locations/hnl-lab-medicine-allentown-lehigh-st | AC40: 91626
A41: HNL Lab Medicine–Allentown - Tilghman St | B41: Testing and Imaging Centers | E41: 4727 Tilghman Street | F41: 4727 Tilghman Street | H41: Allentown | I41: PA | J41: 18104 | K41: 40.590805 | L41: -75.561833 | M41: (484) 425-5304 | N41: (484) 425-5345 | O41: General Facility Hours | P41: 6:00 am - 5:00 pm | Q41: 6:00 am - 5:00 pm | R41: 6:00 am - 5:00 pm | S41: 6:00 am - 5:00 pm | T41: 6:00 am - 5:00 pm | U41: 7:00 am - 12:00 pm | V41: Closed | Y41: COVID-19 Testing for People Without Symptoms; COVID-19 Testing for People with Symptoms; Lab Tests; Pre-Procedure COVID-19 Testing; Prueba de COVID-19 para personas sin s\u00edntomas; Pruebas de detecci\u00f3n y atenci\u00f3n para el coronavirus (COVID-19) para personas con s\u00edntomas | AB41: https://www.lvhn.org/locations/hnl-lab-medicine-allentown-tilghman-st | AC41: 79340
A42: Hackerman-Patz House | B42: Specialty Care Facilities | C42: Lehigh Valley Hospital–Cedar Crest | E42: 1260 S. Cedar Crest Blvd. | F42: 1260 S. Cedar Crest Blvd. | H42: Allentown | I42: PA | J42: 18105 | K42: 40.565499 | L42: -75.523387 | M42: 610-402-9500 | O42: Hours vary by service | X42: Front desk hours: 8 a.m. to 4:30 p.m.; Check-in: 12-4 p.m.; After hours check-in: 5 p.m.-8 a.m. at the main entrance welcome desk at LVH–Cedar Crest. | Z42: Whether your loved one is a patient or you’re receiving care yourself, our goal remains the same: to offer you well-appointed, cozy accommodations and a supportive environment that allows you to focus on healing. Our house is located at 1260 S. Cedar Crest Blvd., Allentown, Pa. 18105. We are on the campus of LVH–Cedar Crest in Salisbury Township, directly off I-78 (Route 309) at Exit 55 (Cedar Crest Boulevard). You'll find us at the rear (south side) of the campus, on a lovely landscaped island across from the hospital's emergency room. We are a member of the Healthcare Hospitality Network (HHN), a nationwide network of more than 200 not-for-profit, family lodging facilities that offer warm, caring support to more than a quarter of a million people each year. House features Everything in our house is designed to help make a stressful time in your life a little easier. And because you’ll be staying with other families facing similar circumstances, you’ll quickly discover you are not alo | AB42: https://www.lvhn.org/locations/hackerman-patz-house | AC42: 69022
A43: Health & Wellness Center at Cedar Crest | B43: Health Centers | C43: Lehigh Valley Hospital–Cedar Crest | E43: 1243 S. Cedar Crest Blvd. | F43: 1243 S. Cedar Crest Blvd. | H43: Allentown | I43: PA | J43: 18103 | K43: 40.56708 | L43: -75.51757 | O43: Hours vary by service | Z43: The Health and Wellness Center at Cedar Crest offers a variety of services for the whole family. In one convenient location, only minutes from Lehigh Valley Hospital–Cedar Crest , you can see providers in endocrinology, plastic surgery, bariatric medicine and rehabilitation. We also offer LVHN Fitness, tobacco treatment and parent and family education classes. Lehigh Valley Hospital Services LVH Bariatric Medicine LVH Diabetes and Metabolism Center LVH Endocrinology Pediatric rehabilitation services Wellness Services LVHN Fitness Parent and family education Parking For your convenience, free valet parking is available at our front entrance from 8 a.m.-4:30 p.m. | AB43: https://www.lvhn.org/locations/health-wellness-center-cedar-crest | AC43: 65754
A44: Imaging Services - 250 Cetronia Road | B44: Testing and Imaging Centers | E44: 250 Cetronia Road | F44: 250 Cetronia Road | H44: Allentown | I44: PA | J44: 18104-9147 | K44: 40.583995 | L44: -75.559966 | M44: 610-674-4940 | O44: General Facility Hours | P44: 6:30 am - 8:00 pm | Q44: 6:30 am - 8:00 pm | R44: 6:30 am - 8:00 pm | S44: 6:30 am - 8:00 pm | T44: 6:30 am - 5:00 pm | U44: 8:00 am - 12:00 pm | V44: Closed | Y44: Bone Densitometry (DEXA); Breast Magnetic Resonance Imaging (MRI); CT (Computed Tomography) Scan; Magnetic Resonance Imaging (MRI); Ultrasound; X-Ray | Z44: The imaging services provided at this location are: Bone densitometry View Hours CT scan View Hours Ultrasound View Hours MRI View Hours X-ray View Hours A service of Lehigh Valley Hospital. | AB44: https://www.lvhn.org/locations/imaging-services-250-cetronia-road | AC44: 65444
A45: Imaging Services–1220 Cedar Crest | B45: Testing and Imaging Centers | C45: Lehigh Valley Hospital–Cedar Crest | E45: 1220 South Cedar Crest Boulevard | F45: 1220 South Cedar Crest Boulevard | H45: Allentown | I45: PA | J45: 18103 | K45: 40.533286 | L45: -75.514118 | M45: 610-402-1000 | O45: Hours vary by service | X45: Monday – Friday: 24 hours a day; Saturday: 7 a.m. – 3 p.m. | Y45: Magnetic Resonance Imaging (MRI) | Z45: A service of Lehigh Valley Hospital. | AB45: https://www.lvhn.org/locations/imaging-services-1220-cedar-crest | AC45: 65453
A46: Imaging Services–1230 Cedar Crest | B46: Testing and Imaging Centers | C46: Lehigh Valley Hospital–Cedar Crest | E46: 1230 S. Cedar Crest Blvd. | F46: 1230 S. Cedar Crest Blvd. | H46: Allentown | I46: PA | J46: 18103 | K46: 40.56605 | L46: -75.521384 | M46: 610-402-4200 | O46: Hours vary by service | Y46: Bone Densitometry (DEXA); Fluoroscopy and Urinary Tract Exams; Magnetic Resonance Imaging (MRI); PET\/CT scan; Ultrasound; X-Ray | Z46: The imaging services provided at this location are: Bone densitometry - Suite 104 Monday – Friday: 9 a.m. – 4 p.m. Fluoroscopy - Suite 104 Monday – Friday: 7:30 a.m. – 11 a.m. PET/CT scan - Suite 104 Monday – Thursday: 7 a.m. – 8 p.m. Friday: 7 a.m. – 5:30 p.m. Ultrasound - Suite 202 Monday, Tuesday: 7 a.m. – 6:30 p.m. Wednesday, Thursday, Friday: 7 a.m. – 5 p.m. MRI - Suite 103 Monday – Friday: 7:00 a.m. – 11:30 p.m. X-ray - Suite 104 Walk-in/No appointment needed Monday – Thursday: 7 a.m. – 8 p.m. Friday: 7 a.m. – 5:30 p.m. Saturday: 8 a.m. – noon A service of Lehigh Valley Hospital. | AB46: https://www.lvhn.org/locations/imaging-services-1230-cedar-crest | AC46: 65451
A47: Imaging Services–1247 Cedar Crest | B47: Testing and Imaging Centers | C47: Lehigh Valley Hospital–Cedar Crest | E47: 1247 S Cedar Crest Blvd | F47: 1247 S Cedar Crest Blvd | H47: Allentown | I47: PA | J47: 18103-6298 | K47: 40.566409 | L47: -75.514725 | M47: 610-402-1000 | O47: General Facility Hours | P47: 7:00 am - 11:30 pm | Q47: 7:00 am - 11:30 pm | R47: 7:00 am - 11:30 pm | S47: 7:00 am - 11:30 pm | T47: 7:00 am - 11:30 pm | U47: 7:00 am - 3:00 pm | V47: Closed | Y47: Magnetic Resonance Imaging (MRI) | Z47: Visit this location for complete magnetic resonance imaging (MRI) services. A service of Lehigh Valley Hospital. | AB47: https://www.lvhn.org/locations/imaging-services-1247-cedar-crest | AC47: 65455
A48: Imaging Services–1250 Cedar Crest | B48: Testing and Imaging Centers | C48: Lehigh Valley Hospital–Cedar Crest | E48: 1250 S. Cedar Crest Blvd., Suite 112 | F48: 1250 S. Cedar Crest Blvd. | G48: Suite 112 | H48: Allentown | I48: PA | J48: 18103 | K48: 40.566568 | L48: -75.519745 | M48: 610-402-4200 | O48: General Facility Hours | P48: 7:00 am - 8:00 pm | Q48: 7:00 am - 8:00 pm | R48: 7:00 am - 8:00 pm | S48: 7:00 am - 8:00 pm | T48: 7:00 am - 5:30 pm | U48: 8:00 am - 12:00 pm | V48: Closed | Y48: CT (Computed Tomography) Scan; Coronary CTA; Lung Cancer Screening | Z48: The imaging services provided at this location are: Computed tomography (CT) scans Coronary CT angiography Lung cancer CT screening A service of Lehigh Valley Hospital. | AB48: https://www.lvhn.org/locations/imaging-services-1250-cedar-crest | AC48: 65442
A49: Infusion Services at Lehigh Valley Hospital–Cedar Crest | B49: Specialty Care Facilities | C49: John and Dorothy Morgan Cancer Center | D49: Lehigh Valley Topper Cancer Institute | E49: 1240 S Cedar Crest Blvd | F49: 1240 S Cedar Crest Blvd | H49: Allentown | I49: PA | J49: 18103-6370 | K49: 40.566494 | L49: -75.521491 | O49: General Facility Hours | P49: 7:30 am - 6:00 pm | Q49: 7:30 am - 6:00 pm | R49: 7:30 am - 6:00 pm | S49: 7:30 am - 6:00 pm | T49: 7:30 am - 6:00 pm | U49: 8:00 am - 3:00 pm | V49: 7:45 am - 9:45 am | Y49: Chemotherapy; Infusions for Benign Medical Conditions; Infusions for Cancer | Z49: Lehigh Valley Hospital–Cedar Crest’s Infusion Services care team includes nurses trained in chemotherapy, biotherapy and immunotherapy. We offer private treatment areas with amenities such as individual televisions. Our Services Injections and intravenous medications for cancer and noncancerous conditions Biotherapy Blood products Chemotherapy Hydration Immunotherapy Scalp cooling Stem cell transplant and cellular therapy We are available by phone to assist with questions and collaborate with your care team to provide all the quality care you and your family need. | AB49: https://www.lvhn.org/locations/infusion-services-lehigh-valley-hospital-cedar-crest | AC49: 121016
A50: J.B. and Kathleen Reilly Children’s Surgery Center | B50: Children's Hospital | C50: Lehigh Valley Hospital–Cedar Crest | D50: Lehigh Valley Institute for Surgical Excellence and Lehigh Valley Reilly Children’s Hospital | E50: 1210 S. Cedar Crest Blvd., Third Floor | F50: 1210 S. Cedar Crest Blvd. | G50: Third Floor | H50: Allentown | I50: PA | J50: 18103-6245 | K50: 40.566633 | L50: -75.522356 | M50: 610-402-5590 | O50: Hours vary by service | Y50: General Pediatric Surgery; Pediatric Anesthesia and Sedation Services; Pediatric Gastroenterology; Pediatric Surgery; Second Opinion for Pediatric Surgery; Surgery | Z50: Dedicated to children, the J.B. and Kathleen Reilly Children's Surgery Center at Lehigh Valley Reilly Children's Hospital provides outpatient surgery in a state-of-the-art facility designed to care for children. Our team is comprised of specially educated surgeons, proceduralists and support staff who focus on kids' health. Outpatient pediatric surgery in a center designed just for kids and their parents Many procedures can be performed at the J.B. and Kathleen Reilly Children’s Surgery Center . This outpatient center is dedicated to children’s surgery needs. Using distractions like iPads® and administering anesthesia in the form of “silly juice,” we make surgery a little less scary for kids – and for parents. You and other family members can relax in a private waiting room knowing you’ll be alerted as soon as your child’s procedure is complete. Children’s Surgery Center services include: General pediatric surgery Urology Ear, nose and throat procedures Gastroenterology Plastic surgery | AB50: https://www.lvhn.org/locations/jb-and-kathleen-reilly-childrens-surgery-center | AC50: 60631
A51: JeffExpress Urgent Care-Airport Road | B51: ExpressCARE and JeffExpress Urgent Care | E51: 1791 Airport Road | F51: 1791 Airport Road | H51: Allentown | I51: PA | J51: 18109-9528 | K51: 40.637148 | L51: -75.434897 | M51: (484) 658-3010 | N51: (610) 264-2249 | O51: General Facility Hours | P51: 8:00 am - 8:00 pm | Q51: 8:00 am - 8:00 pm | R51: 8:00 am - 8:00 pm | S51: 8:00 am - 8:00 pm | T51: 8:00 am - 8:00 pm | U51: 8:00 am - 8:00 pm | V51: 8:00 am - 8:00 pm | Y51: Adolescent Gynecology; COVID-19 Testing for People with Symptoms; JeffExpress Urgent Care; Primary Care; Pruebas de detecci\u00f3n y atenci\u00f3n para el coronavirus (COVID-19) para personas con s\u00edntomas; Smoking Cessation Counseling; Sports Medicine | Z51: When you are feeling sick or have a minor injury, JeffExpress Urgent Care–Airport Road, formerly LVHN ExpressCARE–Airport Road, is here for you. We offer walk-in or by appointment care for common illnesses and minor injuries, such as sprains, cuts, rashes, seasonal allergies, flu symptoms, bronchitis, ear infections, sore throat, fever and more. X-ray imaging services are available on-site. JeffExpress Urgent Care is open seven days a week. Walk in or make an appointment for treatment of minor illnesses and injuries including, but not limited to: Injuries and illnesses Minor cuts Sprains and strains Allergies Coughs and colds Fever, flu or flu shot Nausea Sinus pain Acute back pain Bronchitis Eye irritation Ear pain Headaches Rashes Other medical needs you may have: Symptomatic COVID-19 testing Minor physicals – Please call our team for more information regarding physicals. X-ray available on-site. You will be billed as if this was a regular office visit. | AB51: https://www.lvhn.org/locations/jeffexpress-urgent-care-airport-road | AC51: 74241
A52: JeffExpress Urgent Care-Cedar Crest | B52: ExpressCARE and JeffExpress Urgent Care | E52: 1101 S Cedar Crest Blvd | F52: 1101 S Cedar Crest Blvd | H52: Allentown | I52: PA | J52: 18103-7902 | K52: 40.572847 | L52: -75.519203 | M52: (484) 240-4073 | N52: (484) 240-4077 | O52: General Facility Hours | P52: 8:00 am - 8:00 pm | Q52: 8:00 am - 8:00 pm | R52: 8:00 am - 8:00 pm | S52: 8:00 am - 8:00 pm | T52: 8:00 am - 8:00 pm | U52: 8:00 am - 8:00 pm | V52: 8:00 am - 8:00 pm | Y52: Adolescent Gynecology; COVID-19 Testing for People with Symptoms; JeffExpress Urgent Care; Primary Care; Pruebas de detecci\u00f3n y atenci\u00f3n para el coronavirus (COVID-19) para personas con s\u00edntomas; Smoking Cessation Counseling; Sports Medicine | Z52: When you are feeling sick or have a minor injury, JeffExpress Urgent Care–Cedar Crest, formerly LVHN ExpressCARE–Cedar Crest, is here for you. We offer walk-in or by appointment care for common illnesses and minor injuries, such as sprains, cuts, rashes, seasonal allergies, flu symptoms, bronchitis, ear infections, sore throat, fever and more. X-ray imaging services are available on-site. JeffExpress Urgent Care is open seven days a week. Walk in or make an appointment for treatment of minor illnesses and injuries including, but not limited to: Injuries and illnesses Minor cuts Sprains and strains Allergies Coughs and colds Fever, flu or flu shot Nausea Sinus pain Acute back pain Bronchitis Eye irritation Ear pain Headaches Rashes Other medical needs you may have: Symptomatic COVID-19 testing Minor physicals – Please call our team for more information regarding physicals. X-ray available on-site. You will be billed as if this was a regular office visit. | AB52: https://www.lvhn.org/locations/jeffexpress-urgent-care-cedar-crest | AC52: 64477
A53: John F. Wolf, MD | B53: Physician Practices | E53: 1255 S Cedar Crest Blvd, Suite 2200 | F53: 1255 S Cedar Crest Blvd | G53: Suite 2200 | H53: Allentown | I53: PA | J53: 18103-6226 | K53: 40.565378 | L53: -75.515204 | M53: 610-740-5547 | N53: 610-820-8172 | O53: General Facility Hours | P53: 8:00 am - 6:00 pm | Q53: 8:00 am - 5:00 pm | R53: 8:00 am - 5:00 pm | S53: 8:00 am - 6:00 pm | T53: 8:00 am - 5:00 pm | U53: Closed | V53: Closed | X53: Rotates days off on Wed., Thurs. and Fri. | Y53: Adolescent Gynecology; Primary Care; Smoking Cessation Counseling; Sports Medicine | AB53: https://www.lvhn.org/locations/john-f-wolf-md | AC53: 64802
A54: John and Dorothy Morgan Cancer Center | B54: Cancer Centers; Specialty Care Facilities; Testing and Imaging Centers | C54: Lehigh Valley Hospital–Cedar Crest | D54: Lehigh Valley Topper Cancer Institute | E54: 1240 S Cedar Crest Blvd | F54: 1240 S Cedar Crest Blvd | H54: Allentown | I54: PA | J54: 18103-6370 | K54: 40.566494 | L54: -75.521491 | M54: 610-402-0500 | O54: General Facility Hours | P54: 7:30 am - 5:00 pm | Q54: 7:30 am - 5:00 pm | R54: 7:30 am - 5:00 pm | S54: 7:30 am - 5:00 pm | T54: 7:30 am - 5:00 pm | U54: Closed | V54: Closed | Y54: COVID-19 Vaccine Boosters and Third Shots; Cancer Counseling and Support; Cancer Nutrition Services; Cancer Research and Clinical Trials; Cancer Risk Assessment; Cancer Treatments; Genetic Counseling for Cancer; Precision Medicine; Radiation Therapy Treatment Options; Second Opinion Service for Cancer; SurvivorPLACE | Z54: Programs offered at John and Dorothy Morgan Cancer Center include clinical trials , a variety of psychosocial supportive care and outreach programs, and home care and hospice services. Oncology-related education and training opportunities for health care professionals are also provided. Learn more about our services: LVH Hematology Oncology–1240 Cedar Crest LVPG Surgical Oncology–1240 Cedar Crest LVH Gynecologic Oncology–1240 Cedar Crest Breast Health Services Cancer support services Multidisciplinary clinics (MDC) Clinical trials Genetic risk assessment and counseling Infusion services Radiation therapy (radiation oncology) Cancer financial services Tumor boards Survivor PLACE In addition to John and Dorothy Morgan Cancer Center, Lehigh Valley Topper Cancer Institute has locations throughout the region for your convenience, comfort and access to expert oncology care: Cancer Center at LVH–Muhlenberg Cancer Center at LVH–Hecktown Oaks Cancer Center at LVH – Carbon Dale and Frances Hughe | AB54: https://www.lvhn.org/locations/john-and-dorothy-morgan-cancer-center | AC54: 54589
A55: Joseph A. Habig II, MD | B55: Physician Practices | E55: 798 Hausman Road, Suite 250 | F55: 798 Hausman Road | G55: Suite 250 | H55: Allentown | I55: PA | J55: 18104-9119 | K55: 40.592855 | L55: -75.563498 | M55: (610) 973-3868 | N55: (610) 973-3867 | O55: General Facility Hours | P55: 8:00 am - 5:00 pm | Q55: 8:00 am - 5:30 pm | R55: 8:00 am - 12:00 pm | S55: 8:00 am - 5:30 pm | T55: 8:00 am - 5:30 pm | U55: Closed | V55: Closed | Y55: Adolescent Gynecology; Primary Care; Smoking Cessation Counseling; Sports Medicine | AB55: https://www.lvhn.org/locations/joseph-habig-ii-md | AC55: 64814
A56: Kidney Care Specialists, LLC | B56: Physician Practices | E56: 1230 S Cedar Crest Blvd, Suites 301, 302, and 304 | F56: 1230 S Cedar Crest Blvd | G56: Suites 301, 302, and 304 | H56: Allentown | I56: PA | J56: 18103-6231 | K56: 40.56605 | L56: -75.521384 | M56: (610) 432-4529 | N56: (610) 432-2206 | O56: General Facility Hours | P56: 8:00 am - 5:00 pm | Q56: 8:00 am - 5:00 pm | R56: 8:00 am - 5:00 pm | S56: 8:00 am - 5:00 pm | T56: 8:00 am - 5:00 pm | U56: Closed | V56: Closed | Y56: Kidney Care (Nephrology) | AB56: https://www.lvhn.org/locations/kidney-care-specialists-llc | AC56: 64505
A57: LVH Adolescent Medicine-3080 Hamilton | B57: Children's Hospital | E57: 3080 Hamilton Blvd, Suite 200 | F57: 3080 Hamilton Blvd | G57: Suite 200 | H57: Allentown | I57: PA | J57: 18103-3692 | K57: 40.5812 | L57: -75.518799 | M57: (484) 661-4642 | N57: (484) 661-4644 | O57: Hours vary by service | Y57: Adolescent Gynecology; Adolescent Medicine | Z57: Children ages 12 to 25 may benefit from receiving their care from a specialist who recognizes their unique challenges. Adolescent medicine specialists have experience and training to care for many patient needs. Adolescent medicine specialists provide comprehensive care Health needs our specialists treat: Teen specific things such as acne, headaches, depression, etc. Reproductive health Sexuality concerns Developmental or intellectual concerns Social and emotional concerns Substance abuse Healthy nutrition Eating disorders | AB57: https://www.lvhn.org/locations/lvh-adolescent-medicine-3080-hamilton | AC57: 76928
A58: LVH Bariatric Medicine–1243 Cedar Crest | B58: Physician Practices | C58: Health & Wellness Center at Cedar Crest | E58: 1243 S Cedar Crest Blvd, Suite 2200 | F58: 1243 S Cedar Crest Blvd | G58: Suite 2200 | H58: Allentown | I58: PA | J58: 18103-6268 | K58: 40.56708 | L58: -75.51757 | M58: (610) 402-5000 | N58: (610) 402-2506 | O58: General Facility Hours | P58: 7:00 am - 7:00 pm | Q58: 7:00 am - 7:00 pm | R58: 7:00 am - 5:00 pm | S58: 7:00 am - 5:00 pm | T58: 7:00 am - 5:00 pm | U58: Closed | V58: Closed | Y58: Adolescent Gynecology; Bariatric Surgery (Gastric Sleeve, Gastric Bypass); Change Your Weigh Meal Replacement Program; Endocrinology (Diabetes and Metabolism); Medical Weight Management; Nutrition; Obesity Treatment; Primary Care; Smoking Cessation Counseling; Sports Medicine; Weight Loss and Management | Z58: If you’ve tried diet after diet without success, Lehigh Valley Health Network Weight Management Center can help. Physician-monitored weight loss might be right for you if you are struggling to lose weight and ready to take action, repeated attempts to lose weight by dieting have failed, you have a body mass index (BMI) greater than 30 and you are 14 years of age or older. You must also be committed to lifestyle changes and agree to regular follow-up appointments. Services Our physician-monitored weight-loss program includes: Initial examination Diet and nutritional counseling Behavior modification Weight-loss medication Maintenance support If you choose weight-loss surgery , LVHN’s Weight Management Center provides the education and support you need so you can make permanent changes for the better. Lehigh Valley Health Network is accredited as a Level 1 facility by the Bariatric Surgery Center Network Accreditation Program of the American College of Surgeons. Parking For your convenien | AB58: https://www.lvhn.org/locations/lvh-bariatric-medicine-1243-cedar-crest | AC58: 54538
A59: LVH Cardiac and Thoracic Surgery-1250 Cedar Crest | B59: Physician Practices | C59: Lehigh Valley Hospital–Cedar Crest | D59: Lehigh Valley Heart and Vascular Institute | E59: 1250 S Cedar Crest Blvd, Suite 310 | F59: 1250 S Cedar Crest Blvd | G59: Suite 310 | H59: Allentown | I59: PA | J59: 18103-6381 | K59: 40.566568 | L59: -75.519745 | M59: (610) 402-6890 | N59: (610) 402-6892 | O59: General Facility Hours | P59: 7:30 am - 5:00 pm | Q59: 7:30 am - 5:00 pm | R59: 7:30 am - 5:00 pm | S59: 7:30 am - 5:00 pm | T59: 7:30 am - 5:00 pm | U59: Closed | V59: Closed | Y59: Cancer Surgery; Cardiology; Cardiothoracic Surgery (Heart and Lung Surgery); Oncology | Z59: Our team of caring physicians, cardiac nurse specialists, and physician assistants will answer all of your questions and outline all of your treatment options. If you require an interventional procedure, such as a cardiac catheterization, stenting or an electrophysiology study, we will explain what will happen to you from the beginning to its conclusion. You will be provided with educational material to help you make lifestyle changes to improve your heart health. You will receive follow-up care with your cardiologist and primary care physician. We believe this team approach will give you the heart care that you need and the expertise and experience you deserve. When you choose us, you have peace of mind knowing you will be taken care of at Lehigh Valley Health Network, which consistently ranks in the top 1 percent in the nation for heart attack survival. A service of Lehigh Valley Hospital. | AB59: https://www.lvhn.org/locations/lvh-cardiac-and-thoracic-surgery-1250-cedar-crest | AC59: 54553
A60: LVH Cardiology-1250 Cedar Crest | B60: Physician Practices | C60: Lehigh Valley Hospital–Cedar Crest | D60: Lehigh Valley Heart and Vascular Institute | E60: 1250 S Cedar Crest Blvd, Suite 300 | F60: 1250 S Cedar Crest Blvd | G60: Suite 300 | H60: Allentown | I60: PA | J60: 18103-6381 | K60: 40.566568 | L60: -75.519745 | M60: (610) 402-3110 | N60: (610) 402-3112 | O60: General Facility Hours | P60: 8:00 am - 5:00 pm | Q60: 8:00 am - 5:00 pm | R60: 8:00 am - 5:00 pm | S60: 8:00 am - 5:00 pm | T60: 8:00 am - 5:00 pm | U60: Closed | V60: Closed | Y60: Advanced Lipid Management and Cardiac Prevention Program; Cardiac Electrophysiology; Cardiology; Centro del Coraz\u00f3n Hispanic Heart Program; Primary Care; Sports Cardiology | Z60: Our team of caring physicians, cardiac nurse specialists, and physician assistants will answer all of your questions and outline all of your treatment options. If you require an interventional procedure, such as a cardiac catheterization, stenting or an electrophysiology study, we will explain what will happen to you from the beginning to its conclusion. You will be provided with educational material to help you make lifestyle changes to improve your heart health. You will receive follow-up care with your cardiologist and primary care physician. We believe this team approach will give you the heart care that you need and the expertise and experience you deserve. When you choose us, you have peace of mind knowing you will be taken care of at Lehigh Valley Health Network, which consistently ranks among the best in the nation for heart attack survival. A service of Lehigh Valley Hospital. | AB60: https://www.lvhn.org/locations/lvh-cardiology-1250-cedar-crest | AC60: 54561
A61: LVH Diabetes and Metabolism Center–1243 Cedar Crest | C61: Health & Wellness Center at Cedar Crest | E61: 1243 S Cedar Crest Blvd, Suite 2800 | F61: 1243 S Cedar Crest Blvd | G61: Suite 2800 | H61: Allentown | I61: PA | J61: 18103-6268 | K61: 40.567117 | L61: -75.517458 | M61: (610) 402-3422 | N61: (610) 402-8539 | O61: Hours vary by service | P61: Closed | Q61: Closed | R61: Closed | S61: Closed | T61: Closed | U61: Closed | V61: Closed | Y61: Endocrinology (Diabetes and Metabolism); Primary Care | Z61: For your convenience, free valet parking is available at our front entrance from 8 a.m.-4:30 p.m. | AB61: https://www.lvhn.org/locations/lvh-diabetes-and-metabolism-center-1243-cedar-crest | AC61: 100732
A62: LVH Endocrinology–1243 Cedar Crest | B62: Physician Practices | C62: Health & Wellness Center at Cedar Crest | E62: 1243 S Cedar Crest Blvd, Suite 2800 | F62: 1243 S Cedar Crest Blvd | G62: Suite 2800 | H62: Allentown | I62: PA | J62: 18103-6268 | K62: 40.567117 | L62: -75.517458 | M62: (833) 363-6274 | N62: (610) 402-6979 | O62: General Facility Hours | P62: 8:00 am - 5:00 pm | Q62: 8:00 am - 5:00 pm | R62: 8:00 am - 5:00 pm | S62: 8:00 am - 5:00 pm | T62: 8:00 am - 5:00 pm | U62: Closed | V62: Closed | Y62: A1C Testing (Diabetes Blood Test); Continuous Glucose Monitoring; Diabetes and Metabolism Center; Endocrinology (Diabetes and Metabolism); Thyroid Fine Needle Aspiration Biopsy; Thyroid Nodule Biopsy; Thyroid Screening; Ultrasound-guided Fine Needle Aspiration | Z62: Our doctors work with you to develop the best plan of care for your condition. We welcome patients from adolescents through older adults. Services We treat all diseases and disorders related to the endocrine system, including: Diabetes Thyroid disorders Metabolic syndrome Osteoporosis Polyendocrine metabolic ovarian syndrome (PMOS) Parking For your convenience, free valet parking is available at our front entrance from 8 a.m.-4:30 p.m. | AB62: https://www.lvhn.org/locations/lvh-endocrinology-1243-cedar-crest | AC62: 54609
A63: LVH Gastroenterology–1501 N Cedar Crest | B63: Physician Practices | E63: 1501 N Cedar Crest Blvd, Suite 110 | F63: 1501 N Cedar Crest Blvd | G63: Suite 110 | H63: Allentown | I63: PA | J63: 18104-2309 | K63: 40.646768 | L63: -75.548603 | M63: (610) 821-2828 | N63: (610) 821-7915 | O63: General Facility Hours | P63: 7:30 am - 5:00 pm | Q63: 7:30 am - 5:00 pm | R63: 7:30 am - 5:00 pm | S63: 7:30 am - 5:00 pm | T63: 7:30 am - 5:00 pm | U63: Closed | V63: Closed | Y63: Endoscopy; Gastroenterology; Gastroenterology Tests | Z63: LVPG Gastroenterology specializes in the treatment of digestive system disorders using the most advanced diagnostic and therapeutic options. Our specialized clinicians and staff provide skilled testing and treatment and friendly, compassionate care. Conditions treated include: Barrett’s esophagus Celiac disease Colorectal cancer Crohn’s disease Gastric ulcers Gastroesophageal reflux disease (GERD) Hemorrhoids Hepatitis Irritable bowel syndrome Liver disease Motility disorders Ulcerative colitis | AB63: https://www.lvhn.org/locations/lvh-gastroenterology-1501-n-cedar-crest | AC63: 64990
A64: LVH Gynecologic Oncology-1240 Cedar Crest | B64: Physician Practices | C64: John and Dorothy Morgan Cancer Center | D64: Lehigh Valley Topper Cancer Institute | E64: 1240 S Cedar Crest Blvd, Suite 401 | F64: 1240 S Cedar Crest Blvd | G64: Suite 401 | H64: Allentown | I64: PA | J64: 18103-6218 | K64: 40.566494 | L64: -75.521491 | M64: (610) 402-3650 | N64: (610) 402-3673 | O64: General Facility Hours | P64: 8:00 am - 5:00 pm | Q64: 8:00 am - 5:00 pm | R64: 8:00 am - 5:00 pm | S64: 8:00 am - 5:00 pm | T64: 8:00 am - 5:00 pm | U64: Closed | V64: Closed | Y64: Cancer Surgery; Cancer Treatments; Oncology | Z64: LVH Gynecologic Oncology–1240 Cedar Crest, part of Lehigh Valley Topper Cancer Institute , provides you with the most progressive treatments available, without having to leave the area. Same-day appointments are available for urgent problems. Your care Your treatment plan will be designed just for you by doctors who are experts in every treatment you might need, including: Complex and radical gynecologic surgery reconstructive pelvic surgery Advanced laparoscopic or minimally invasive surgery Robotic surgery Multidisciplinary approach Our multidisciplinary teams include a variety of specialists working together to ensure you the best possible care throughout your journey. And through our clinical trials research programs, we have access to the most advanced therapies. Our strengths Affiliations and accreditations – We are part of the National Cancer Institute Gynecologic Oncology Group and accredited as a Network Cancer Program with commendation by the American College of Surgeons’ Com | AB64: https://www.lvhn.org/locations/lvh-gynecologic-oncology-1240-cedar-crest | AC64: 54525
A65: LVH Hematology Oncology-1240 Cedar Crest | B65: Physician Practices | C65: John and Dorothy Morgan Cancer Center | D65: Lehigh Valley Topper Cancer Institute | E65: 1240 S Cedar Crest Blvd, Suite 401 | F65: 1240 S Cedar Crest Blvd | G65: Suite 401 | H65: Allentown | I65: PA | J65: 18103-6218 | K65: 40.566494 | L65: -75.521491 | M65: (610) 402-7880 | N65: (610) 402-7881 | O65: General Facility Hours | P65: 7:30 am - 5:00 pm | Q65: 7:30 am - 5:00 pm | R65: 7:30 am - 5:00 pm | S65: 7:30 am - 5:00 pm | T65: 7:30 am - 5:00 pm | U65: Closed | V65: Closed | Y65: Cancer Treatments; Cardiology; Oncology; Stem Cell Transplant and Cellular Therapy Program | Z65: LVH Hematology Oncology–1240 Cedar Crest is part of Lehigh Valley Topper Cancer Institute , a national leader in cancer care. We care for individuals with cancer and blood-related diseases in a friendly, relaxed and confidential environment. We serve as patient advocates, working with our community partners to provide the best quality of life to those with cancer and their caregivers. Programs offered here include clinical trials , a variety of diagnostic, treatment and supportive care programs. Learn about our services: Cancer support services Clinical trials Infusion services Cancer financial services In addition to LVH Hematology Oncology–1240 Cedar Crest, Lehigh Valley Topper Cancer Institute has locations throughout the region for your convenience, comfort and access to expert oncology care: John and Dorothy Morgan Cancer Center (campus of Lehigh Valley Hospital–Cedar Crest) Cancer Center at Lehigh Valley Hospital–Muhlenberg LVPG Hematology Oncology-Hecktown Oaks Dale and Frances | AB65: https://www.lvhn.org/locations/lvh-hematology-oncology-1240-cedar-crest | AC65: 54528
A66: LVH Neurology-1250 Cedar Crest | B66: Physician Practices | C66: Lehigh Valley Hospital–Cedar Crest | D66: Lehigh Valley Fleming Neuroscience Institute | E66: 1250 S Cedar Crest Blvd, Suite 405 | F66: 1250 S Cedar Crest Blvd | G66: Suite 405 | H66: Allentown | I66: PA | J66: 18103-6224 | K66: 40.566568 | L66: -75.519745 | M66: (610) 402-8420 | N66: (610) 402-1689 | O66: General Facility Hours | P66: 8:00 am - 5:00 pm | Q66: 8:00 am - 5:00 pm | R66: 8:00 am - 5:00 pm | S66: 8:00 am - 5:00 pm | T66: 8:00 am - 5:00 pm | U66: Closed | V66: Closed | Y66: ALS Center; Deep Brain Stimulation; Epilepsy Center; MS Center; Neuro-Ophthalmology; Neurology; Oncology; Second Opinion for Neurology; Trigeminal Neuralgia Surgery | Z66: We provide comprehensive care for all neurological diseases, disorders and conditions, including: Headache Stroke Neuromuscular disorders such as ALS (Lou Gehrig’s disease) Movement disorders such as Parkinson’s disease Dementia, Alzheimer’s disease and other degenerative brain disorders Epilepsy and other seizure disorders Multiple sclerosis Brain tumors and spinal cord tumors Degenerative spine disease Disk herniations In addition to medical care, we provide a wide range of support services to help you manage your chronic neurological disease more effectively. We work as a team to create an individualized treatment and support plan for you and your family. A service of Lehigh Valley Hospital. | AB66: https://www.lvhn.org/locations/lvh-neurology-1250-cedar-crest | AC66: 54536
A67: LVH Neuropsychology-1250 Cedar Crest | B67: Physician Practices | C67: Lehigh Valley Hospital–Cedar Crest | D67: Lehigh Valley Fleming Neuroscience Institute | E67: 1250 S Cedar Crest Blvd, Suite 410 | F67: 1250 S Cedar Crest Blvd | G67: Suite 410 | H67: Allentown | I67: PA | J67: 18103-6224 | K67: 40.566568 | L67: -75.519745 | M67: (610) 402-3500 | N67: (610) 402-3505 | O67: Hours vary by service | Z67: A service of Lehigh Valley Hospital. | AB67: https://www.lvhn.org/locations/lvh-neuropsychology-1250-cedar-crest | AC67: 64955
A68: LVH Neurosurgery-1250 Cedar Crest | B68: Physician Practices | C68: Lehigh Valley Hospital–Cedar Crest | D68: Lehigh Valley Fleming Neuroscience Institute | E68: 1250 S Cedar Crest Blvd, Suite 400 | F68: 1250 S Cedar Crest Blvd | G68: Suite 400 | H68: Allentown | I68: PA | J68: 18103-6224 | K68: 40.566568 | L68: -75.519745 | M68: (610) 402-6555 | N68: (610) 402-6550 | O68: General Facility Hours | P68: 8:00 am - 5:00 pm | Q68: 8:00 am - 5:00 pm | R68: 8:00 am - 5:00 pm | S68: 8:00 am - 5:00 pm | T68: 8:00 am - 5:00 pm | U68: Closed | V68: Closed | Y68: Cancer Surgery; Cerebrovascular Surgery; Deep Brain Stimulation; Degenerative Disk Disease Surgery; Epilepsy Surgery; Head, Neck and Spine Care; Kyphoplasty; Lumbar and Cervical Disk Disease Surgery; Movement Disorders Surgery; Neurostimulation; Neurosurgery; Orthopedics; Pediatric Neurosurgery; Second Opinion for Neurosurgery; Skull Base Surgery; Spinal Instability Surgery; Spinal Stenosis Surgery; Spondylolisthesis Surgery; Surgery For Sciatica; Trigeminal Neuralgia Surgery; Vagus Nerve Stimulation (VNS) for Stroke | Z68: Our services We offer patients world-class care for a wide variety of neurological diseases and conditions that require surgical intervention, including aneurysms, brain tumors, arteriovenous malformation (AVM), stroke, conditions of the spine and more. We use the latest surgical methods and technologies, including a range of minimally invasive techniques, such as microsurgery, stereotactic radiosurgery and endoscopic surgery. Our surgeons are actively involved in research designed to advance the surgical treatment of neurological disorders. We understand that each patient's needs are unique. We work closely with nurses, social workers and care team partners to create an individualized treatment and support plan for each person and his or her family. We're conveniently located at Lehigh Valley Hospital–Cedar Crest and Lehigh Valley Hospital–Muhlenberg. A service of Lehigh Valley Hospital. | AB68: https://www.lvhn.org/locations/lvh-neurosurgery-1250-cedar-crest | AC68: 54631
A69: LVH Pediatric Endocrinology-3080 Hamilton Blvd | B69: Children's Hospital; Physician Practices | E69: 3080 Hamilton St, Suite 250 | F69: 3080 Hamilton St | G69: Suite 250 | H69: Allentown | I69: PA | J69: 18103-3692 | K69: 40.591314 | L69: -75.511071 | M69: (484) 661-4641 | N69: (484) 661-4844 | O69: General Facility Hours | P69: 8:00 am - 5:00 pm | Q69: 8:00 am - 5:00 pm | R69: 8:00 am - 5:00 pm | S69: 8:00 am - 5:00 pm | T69: 8:00 am - 5:00 pm | U69: Closed | V69: Closed | Y69: Pediatric Endocrinology | Z69: The conditions we treat at LVH Pediatric Endocrinology-3080 Hamilton Blvd include: Type 1 and type 2 diabetes Obesity Hypoglycemia Convenient appointments are available, so you won’t have to travel away from home to get your child the care he or she needs. If your child ever needs to be hospitalized, you can continue to stay close to home, because we are part of Lehigh Valley Reilly Children’s Hospital . | AB69: https://www.lvhn.org/locations/lvh-pediatric-endocrinology-3080-hamilton-blvd | AC69: 75901
A70: LVH Pediatric Rheumatology-3080 Hamilton Blvd | B70: Children's Hospital; Physician Practices | E70: 3080 Hamilton Blvd., Suite 200 | F70: 3080 Hamilton Blvd. | G70: Suite 200 | H70: Allentown | I70: PA | J70: 18103-3692 | K70: 40.581218 | L70: -75.518826 | M70: (484) 661-4642 | N70: (484) 661-4644 | O70: Hours vary by service | Y70: Pediatric Rheumatology | Z70: When your child or teen is in pain, you can rely on LVH Pediatric Rheumatology to support your family with compassionate care just for kids. Our services We treat a wide range of musculoskeletal and autoimmune conditions, including: Juvenile idiopathic arthritis Lupus Kawasaki disease Inflammatory disorders of joints, muscles, or eyes Extended, unexplained fevers Muscle pain, loss of appetite, and fatigue Our pediatric rheumatology team takes great care to evaluate and diagnose the underlying cause of your child’s condition or pain. The most important diagnostic tools a pediatric rheumatologist has are the child’s medical history and a physical examination. In some cases, a blood test may be needed to confirm a diagnosis. Treating rheumatoid diseases in children While no cures exist for pediatric rheumatic diseases, we offer evidence-based treatments that provide long-term relief from inflammation and pain. Our experts are committed to helping your child maintain an active, healthy lif | AB70: https://www.lvhn.org/locations/lvh-pediatric-rheumatology-3080-hamilton-blvd | AC70: 126139
A71: LVH Rheumatology-Hausman Road | C71: LVPG Musculoskeletal Center–Hausman Road | E71: 798 Hausman Road, 1st Floor | F71: 798 Hausman Road | G71: 1st Floor | H71: Allentown | I71: PA | J71: 18104-9108 | K71: 40.592815 | L71: -75.563384 | M71: (610) 776-5038 | N71: (610) 776-1967 | O71: General Facility Hours | P71: 8:00 am - 5:00 pm | Q71: 8:00 am - 5:00 pm | R71: 8:00 am - 5:00 pm | S71: 8:00 am - 5:00 pm | T71: 8:00 am - 5:00 pm | U71: Closed | V71: Closed | Y71: Rheumatology | Z71: Conditions we treat include: Osteoarthritis Rheumatoid arthritis Lupus Gout A service of Lehigh Valley Hospital. We conveniently offer injections and infusions at our spacious musculoskeletal suite on the first floor of the building in Suite 100. | AB71: https://www.lvhn.org/locations/lvh-rheumatology-hausman-road | AC71: 69344
A72: LVH Sleep Disorders Center-17th Street | B72: Sleep Centers; Testing and Imaging Centers | C72: Lehigh Valley Hospital–17th Street | E72: 1627 W. Chew St. | F72: 1627 W. Chew St. | H72: Allentown | I72: PA | J72: 18102 | K72: 40.602768 | L72: -75.494366 | M72: 610-969-4277 | N72: 610-969-4270 | O72: General Facility Hours | P72: 7:30 am - 4:00 pm | Q72: 7:30 am - 4:00 pm | R72: 7:30 am - 4:00 pm | S72: 7:30 am - 4:00 pm | T72: 7:30 am - 4:00 pm | U72: Closed | V72: Closed | Y72: Sleep Study; Smoking Cessation Counseling | Z72: Schedule a sleep study Testing is by appointment only. A physician referral is required to schedule a sleep test. Call 888-402-LVHN to schedule your In-lab or home sleep test. Sleep testing is a service of Lehigh Valley Hospital. Our services | AB72: https://www.lvhn.org/locations/lvh-sleep-disorders-center-17th-street | AC72: 54594
A73: LVH Surgical Oncology-1240 Cedar Crest | B73: Physician Practices | C73: John and Dorothy Morgan Cancer Center | D73: Lehigh Valley Topper Cancer Institute and Lehigh Valley Institute for Surgical Excellence | E73: 1240 S Cedar Crest Blvd, Suite 410 | F73: 1240 S Cedar Crest Blvd | G73: Suite 410 | H73: Allentown | I73: PA | J73: 18103-6218 | K73: 40.566381 | L73: -75.522215 | M73: (610) 402-7884 | N73: (610) 402-8876 | O73: General Facility Hours | P73: 7:30 am - 4:30 pm | Q73: 7:30 am - 4:30 pm | R73: 7:30 am - 4:30 pm | S73: 7:30 am - 4:30 pm | T73: 7:30 am - 4:30 pm | U73: Closed | V73: Closed | Y73: Cancer Surgery; Cancer Treatments; Oncology; Surgical Oncology | Z73: Our surgical oncology practices offer compassionate care delivered by board-certified, fellowship-trained surgeons. These surgical experts have vast experience treating a wide range of cancerous and noncancerous conditions, including: Adrenal masses Anal cancer Appendix/appendiceal cancer Bile duct cancer Breast cancer Breast pain, cysts and fibroadenomas Colorectal cancer Esophageal cancer Gallbladder cancer Goiters (thyroid gland swelling) Gynecomastia (enlarged breasts in men) Lipomas Liver cancer Liver lesions Melanoma Mesenteric masses Pancreatic cancer Pancreatic masses Peritoneal disease Sarcoma Stomach/gastric cancer Thyroid nodules We also provide monitoring for patients at high risk for developing breast cancer. In addition to providing state-of-the-art surgical care, our clinicians work closely with Lehigh Valley Topper Cancer Institute radiation oncologists and hematologist oncologists to develop multidisciplinary and personalized treatment plans. They also are involved in | AB73: https://www.lvhn.org/locations/lvh-surgical-oncology-1240-cedar-crest | AC73: 54577
A74: LVHN Adolescent Transitions Partial Program | B74: Specialty Care Facilities | E74: 1255 S Cedar Crest Blvd, Suite 1500 | F74: 1255 S Cedar Crest Blvd | G74: Suite 1500 | H74: Allentown | I74: PA | J74: 18103-6281 | K74: 40.565378 | L74: -75.515204 | M74: (610) 402-5930 | N74: (610) 402-8118 | O74: General Facility Hours | P74: 8:00 am - 4:30 pm | Q74: 8:00 am - 4:30 pm | R74: 8:00 am - 4:30 pm | S74: 8:00 am - 4:30 pm | T74: 8:00 am - 4:30 pm | U74: Closed | V74: Closed | X74: Patients ages 12-18 attend the program 9 a.m. to 3 p.m. | Y74: Child and Adolescent Psychiatry; Psychiatry (Behavioral Health) | Z74: A day in Lehigh Valley Health Network’s Adolescent Transitions Partial Program consists of morning and afternoon groups, focusing on therapy and skill-building workshops. Our goal is to empower adolescents and their caregiving system through tools that provide ongoing support after discharge. Our collaborative multidisciplinary approach allows patients to leave the treatment experience with evidence-based strategies and skills to continue their progress. Medication assessment and management also are integral parts of treatment. Let us be your safe haven, where we can partner together without shame, guilt or judgment, and you can get back to living your life. | AB74: https://www.lvhn.org/locations/lvhn-adolescent-transitions-partial-program | AC74: 67877
A75: LVHN Adult Transitions Partial Program | B75: Physician Practices; Specialty Care Facilities | E75: 1259 S Cedar Crest Blvd, Suite 205 | F75: 1259 S Cedar Crest Blvd | G75: Suite 205 | H75: Allentown | I75: PA | J75: 18103-6206 | K75: 40.564533 | L75: -75.517025 | M75: (610) 402-5950 | N75: (610) 402-5580 | O75: General Facility Hours | P75: 8:30 am - 3:00 pm | Q75: 8:30 am - 3:00 pm | R75: 8:30 am - 3:00 pm | S75: 8:30 am - 3:00 pm | T75: 8:30 am - 3:00 pm | U75: Closed | V75: Closed | Y75: Psychiatry (Behavioral Health) | Z75: The program day at Lehigh Valley Health Network’s Adult Transitions Partial Program consists of morning and afternoon groups, focusing on therapy and skills-building workshops. Patients leave the treatment experience with evidence-based strategies and skills to continue their progress. Medication assessment and management also are integral parts of treatment. Let us be your safe haven, where we can partner together without shame, guilt or judgment, and you can get back to living your life. | AB75: https://www.lvhn.org/locations/lvhn-adult-transitions-partial-program | AC75: 67878
A76: LVHN Comprehensive Health Services | B76: Community Clinics | C76: Lehigh Valley Hospital–17th Street | E76: 1627 W Chew Street, Third Floor | F76: 1627 W Chew Street | G76: Third Floor | H76: Allentown | I76: PA | J76: 18102-3648 | K76: 40.601282 | L76: -75.494303 | M76: (610) 969-2400 | N76: (610) 969-2325 | O76: General Facility Hours | P76: 9:00 am - 5:00 pm | Q76: 9:00 am - 5:00 pm | R76: 9:00 am - 7:30 pm | S76: 9:00 am - 5:00 pm | T76: 9:00 am - 5:00 pm | U76: Closed | V76: Closed | Y76: COVID-19 Vaccine Boosters and Third Shots; Endocrinology (Diabetes and Metabolism); HIV Screening; Infectious Disease Medicine | Z76: We offer the most comprehensive human immunodeficiency virus (HIV) care in the Lehigh Valley for those living with or affected by HIV – all at one location. Our team of specialists provides a personalized, multidisciplinary approach to care. Are you worried about HIV/AIDS? We offer free confidential and anonymous testing for HIV. The test is via oral swab and provides results in 20 minutes. If you are infected with HIV, we can get you the care you need immediately. HIV testing is conducted at the office during the following hours: Monday, Tuesday, Thursday: 9 a.m.-3 p.m. Friday: By appointment Second Wednesday of the month: 3 p.m.-5 p.m. Education Universal precautions training. Training and education on universal precautions and post-exposure prophylaxis (PEP) are provided at no cost to people employed in health care settings. Risk-assessment and risk-reduction counseling. Our prevention specialists will assess behaviors that may be putting you at risk for contracting HIV and work wit | AB76: https://www.lvhn.org/locations/lvhn-comprehensive-health-services | AC76: 54503
A77: LVHN ExpressCARE-Tilghman | B77: ExpressCARE and JeffExpress Urgent Care | E77: 4825 W Tilghman Street, Suite 101 | F77: 4825 W Tilghman Street | G77: Suite 101 | H77: Allentown | I77: PA | J77: 18104-9374 | K77: 40.590612 | L77: -75.563377 | M77: (610) 402-3900 | N77: (610) 402-4747 | O77: General Facility Hours | P77: 8:00 am - 8:00 pm | Q77: 8:00 am - 8:00 pm | R77: 8:00 am - 8:00 pm | S77: 8:00 am - 8:00 pm | T77: 8:00 am - 8:00 pm | U77: 8:00 am - 8:00 pm | V77: 8:00 am - 8:00 pm | X77: Open 365 days a year. | Y77: COVID-19 Testing for People with Symptoms; ExpressCARE; General Orthopedics; Orthopedics; Primary Care; Prueba de COVID-19 para personas sin s\u00edntomas; Pruebas de detecci\u00f3n y atenci\u00f3n para el coronavirus (COVID-19) para personas con s\u00edntomas; Smoking Cessation Counseling; X-Ray | Z77: This is not an urgent care facility, you will be billed as if you were being treated in an Emergency Room. A service of Lehigh Valley Hospital. Injuries & Illnesses Sprains/Joint injuries Lacerations/Cuts On-the-job injuries Burns/Skin conditions Colds/Flu Sore throat Earaches Urinary infections Bronchitis, pneumonia Asthma attacks Allergic reactions Eye infections Other common injuries & illnesses Other Medical Needs Symptomatic COVID-19 testing Flu shots X-ray | AB77: https://www.lvhn.org/locations/lvhn-expresscare-tilghman | AC77: 68674
A78: LVHN Fitness at One City Center | B78: Fitness Centers | C78: Lehigh Valley Health Network–One City Center | E78: 707 Hamilton St., 3rd Floor | F78: 707 Hamilton St. | G78: 3rd Floor | H78: Allentown | I78: PA | J78: 18101 | K78: 40.602318 | L78: -75.472343 | M78: 484-862-3002 | O78: General Facility Hours | P78: 5:00 am - 9:00 pm | Q78: 5:00 am - 9:00 pm | R78: 5:00 am - 9:00 pm | S78: 5:00 am - 9:00 pm | T78: 5:00 am - 9:00 pm | U78: 7:00 am - 3:30 pm | V78: 7:00 am - 3:30 pm | Z78: The 17,000-square-foot LVHN Fitness Center at One City Center offers: Cardiovascular machines, including spin bikes, crank cycles, treadmills, ellipticals, rowers, stair-climbers and upright bikes, many outfitted with personal televisions Weight-training equipment, including a full line of Hammer Strength equipment, dumbbells up to 120 pounds, Olympic bars, plate weights up to 45 pounds and squat racks Numerous group classes Personal training State-of-the-art multisport simulator where you can practice your golf swing or partake in other “virtual” events Integrated sports medicine services, including on-site physical and occupational therapy, concussion management, sports medicine, sports performance training and nutrition for the active adult sports nutrition A handicapped-accessible locker room with private showers, lockers and towel and toiletry service A café and reception area with healthy food options from Sodexo, free Wi-Fi and a pro shop A sports performance studio and 40-yard | AB78: https://www.lvhn.org/locations/lvhn-fitness-one-city-center | AC78: 54681
A79: LVHN Fitness–Cedar Crest | B79: Fitness Centers | C79: Health & Wellness Center at Cedar Crest | E79: 1243 S. Cedar Crest Blvd. | F79: 1243 S. Cedar Crest Blvd. | H79: Allentown | I79: PA | J79: 18103 | K79: 40.56708 | L79: -75.51757 | M79: 610-402-3699 | O79: General Facility Hours | P79: 5:00 am - 9:00 pm | Q79: 5:00 am - 9:00 pm | R79: 5:00 am - 9:00 pm | S79: 5:00 am - 9:00 pm | T79: 5:00 am - 9:00 pm | U79: 7:00 am - 3:30 pm | V79: 7:00 am - 3:30 pm | Y79: Rock Steady Boxing for Parkinson\u2019s Disease | Z79: LVHN Fitness is committed to helping you achieve your health and wellness goals. We offer a variety of equipment and group classes to meet your fitness needs. There are no joining fees or long-term contract commitments. Join today! Services Services and facilities available to all members include: Cardiovascular, strength and functional equipment Group fitness classes Personal training services Sports performance training programs Nutrition for the active adult Population-based specialty programs Locker room amenities, including towel service Members are also eligible for free injury screenings provided by Rehabilitation Services . Parking For your convenience, free valet parking is available at our front entrance from 8 a.m.-4:30 p.m. | AB79: https://www.lvhn.org/locations/lvhn-fitness-cedar-crest | AC79: 54558
A80: LVHN Hepatitis Care Center | B80: Specialty Care Facilities | C80: Lehigh Valley Hospital–17th Street | E80: 1627 W Chew Street, Third Floor | F80: 1627 W Chew Street | G80: Third Floor | H80: Allentown | I80: PA | J80: 18105-7017 | K80: 40.601285 | L80: -75.493146 | M80: (610) 969-3200 | N80: (610) 969-2783 | O80: General Facility Hours | P80: 9:00 am - 5:00 pm | Q80: 9:00 am - 5:00 pm | R80: 9:00 am - 5:00 pm | S80: 9:00 am - 5:00 pm | T80: 9:00 am - 5:00 pm | U80: Closed | V80: Closed | Y80: FibroScan; Infectious Disease Medicine | Z80: At Lehigh Valley Health Network’s Hepatitis Care Center – the only multidisciplinary hepatitis center in the region – we offer complete care, including the latest medications and therapies for people living with hepatitis B or hepatitis C. Our compassionate staff understands the complexities of living with chronic hepatitis and partners with your primary care provider to optimize your health. A dedicated nurse educator, adherence support and behavioral health specialists are available on-site. Our services Rapid testing for hepatitis C and HIV with results in 20 minutes Specialized medical care for people with hepatitis B and hepatitis C Vaccinations for hepatitis A, hepatitis B, influenza and other illnesses Opportunities to participate in research trials of state-of-the-art medicines High-quality care regardless of ability to pay We also offer FibroScan, an alternative to needle biopsy that uses sound waves to measure the degree of scarring (fibrosis) that’s present in the liver as a | AB80: https://www.lvhn.org/locations/lvhn-hepatitis-care-center | AC80: 54586
A81: LVHN Injury Center–1250 Cedar Crest | E81: 1250 S Cedar Crest Blvd, Suite 110 | F81: 1250 S Cedar Crest Blvd | G81: Suite 110 | H81: Allentown | I81: PA | J81: 18103-6224 | K81: 40.566568 | L81: -75.519745 | M81: 610-402-8900 | N81: 610-402-5656 | O81: General Facility Hours | P81: 8:00 am - 3:00 pm | Q81: 8:00 am - 3:00 pm | R81: 8:00 am - 3:00 pm | S81: 8:00 am - 3:00 pm | T81: 8:00 am - 3:00 pm | U81: Closed | V81: Closed | Y81: Orthopedic Injury Centers | Z81: Our comprehensive team at LVHN Injury Center specializes in treating non-life-threatening orthopedic injuries without an appointment so you can walk in, be treated and get back to what you love as quickly as possible. We see patients 5 years and older at this location. Conditions we treat Our team treats a variety of orthopedic conditions as a result of an incident or accident that occurred within the last 48 hours, such as: Athletic injuries Broken bones/fractures Joint separations Ligament and tendon injuries Muscle pulls and tears Slip and fall injuries Sprains and strains | AB81: https://www.lvhn.org/locations/lvhn-injury-center-1250-cedar-crest | AC81: 124903
A82: LVHN Preadmission Testing Department | B82: Testing and Imaging Centers | C82: Lehigh Valley Hospital–Cedar Crest | E82: 1200 S Cedar Crest Blvd | F82: 1200 S Cedar Crest Blvd | H82: Allentown | I82: PA | J82: 18103-6202 | K82: 40.566755 | L82: -75.524163 | M82: (610) 402-8877 | N82: (610) 402-0410 | O82: Hours vary by service | Y82: Adolescent Gynecology; Primary Care; Smoking Cessation Counseling; Sports Medicine | AB82: https://www.lvhn.org/locations/lvhn-preadmission-testing-department | AC82: 76001
A83: LVHN Surgery Center–Tilghman | B83: Specialty Care Facilities | C83: Lehigh Valley Health Network–Tilghman | D83: Lehigh Valley Institute for Surgical Excellence | E83: 4825 W Tilghman Street, Suite 101 | F83: 4825 W Tilghman Street | G83: Suite 101 | H83: Allentown | I83: PA | J83: 18104-9374 | K83: 40.590612 | L83: -75.563377 | M83: 610-402-4680 | O83: Hours vary by service | Y83: Joint Replacement; Knee Arthroplasty; Orthopedic Surgery; Surgery; Total Hip Replacement | AB83: https://www.lvhn.org/locations/lvhn-surgery-center-tilghman | AC83: 69478
A84: LVPG Addiction Medicine-Southside | B84: Physician Practices | E84: 1648 S 4th Street | F84: 1648 S 4th Street | H84: Allentown | I84: PA | J84: 18103-4922 | K84: 40.583707 | L84: -75.460551 | M84: 484-862-3068 | N84: 610-674-4554 | O84: General Facility Hours | P84: 9:00 am - 5:00 pm | Q84: 9:00 am - 5:00 pm | R84: 9:00 am - 5:00 pm | S84: 9:00 am - 5:00 pm | T84: 9:00 am - 5:00 pm | U84: Closed | V84: Closed | AB84: https://www.lvhn.org/locations/lvpg-addiction-medicine-southside | AC84: 79025
A85: LVPG Adult and Pediatric Psychiatry-1259 Cedar Crest | B85: Children's Hospital; Physician Practices | E85: 1259 S Cedar Crest Blvd, Suite 230 | F85: 1259 S Cedar Crest Blvd | G85: Suite 230 | H85: Allentown | I85: PA | J85: 18103-6376 | K85: 40.564533 | L85: -75.517025 | M85: (610) 402-5900 | N85: (610) 402-4650 | O85: General Facility Hours | P85: 8:00 am - 4:30 pm | Q85: 8:00 am - 4:30 pm | R85: 8:00 am - 4:30 pm | S85: 8:00 am - 4:30 pm | T85: 8:00 am - 4:30 pm | U85: Closed | V85: Closed | X85: Additional therapy appointments are available in the evenings and on weekends by appointment only. | Y85: Child and Adolescent Psychiatry; Psychiatry (Behavioral Health); Transcranial Magnetic Stimulation (TMS) | Z85: Whether you are seeking counseling during a stressful time, support for a lifelong condition that requires medication, or something in between, we are here to support you. We offer support for a variety of conditions and concerns, including but not limited to: Anxiety Depression Difficulty coping with physical illness Grief issues Marital and family problems We offer individual, couples, family, and group therapy, as well as medication management for children, adolescents, adults and older adults. We also offer leading-edge treatments, including transcranial magnetic stimulation therapy (TMS), for treatment-resistant mental health conditions. Our staff is highly experienced and dedicated to providing compassionate and comprehensive care. Our interdisciplinary team includes: Board-certified adult psychiatrists and board-certified child and adolescent psychiatrists Licensed clinical social workers and licensed professional counselors Licensed psychologists Nurse practitioners and physici | AB85: https://www.lvhn.org/locations/lvpg-adult-and-pediatric-psychiatry-1259-cedar-crest | AC85: 64757
A86: LVPG Advanced Spine Center-1621 N Cedar Crest | B86: Specialty Care Facilities | C86: Lehigh Valley Health Network-1621 N. Cedar Crest | D86: Lehigh Valley Orthopedic Institute | E86: 1621 N. Cedar Crest Blvd | F86: 1621 N. Cedar Crest Blvd | H86: Allentown | I86: PA | J86: 18104-2304 | K86: 40.613615 | L86: -75.531218 | M86: 610-402-3300 | N86: 610-402-3355 | O86: Hours vary by service | Z86: Make an appointment You or your primary care provider can reach the Advanced Spine Center directly by calling 888-402-LVHN (5846). Medical history During the call, you speak to a nurse navigator who specializes in neck, back and spine conditions. The nurse takes a detailed medical history including your symptoms, any injuries and previous imaging scans or treatments you’ve had. Next steps After the phone call, the nurse navigator: Reviews the information and uses sophisticated software to help determine your next steps Discusses treatment options with you Updates your referring and primary care physicians about treatment recommendations Helps you schedule your next appointment with a provider Sends a report of the phone call to the appropriate care provider before your appointment | AB86: https://www.lvhn.org/locations/lvpg-advanced-spine-center-1621-n-cedar-crest | AC86: 81083
